Workbook

Sheet 操作パネル
A1: ▶ 新規案件作成
A2: 株式会社 LinK - 見積・原価管理システム
A3: =HYPERLINK("#案件管理!A1","📋案件管理") -> 📋案件管理 | B3: =HYPERLINK("#ダッシュボード!A1","📊ダッシュボード") -> 📊ダッシュボード | C3: =HYPERLINK("#請求管理!A1","💰請求管理") -> 💰請求管理 | D3: =HYPERLINK("#支払管理!A1","🔧支払管理") -> 🔧支払管理
A4: ■ 新規案件作成
A5: ※ 以下の情報を入力して「Claudeに依頼」で新規案件シートを作成できます
A7: 顧客ID | B7: C-001 | C7: 顧客名 | D7: =IFERROR(VLOOKUP(B7,顧客マスタ!A:C,3,FALSE),"") -> 矢島不動産管理株式会社 | F7: 敬称 | G7: =IFERROR(VLOOKUP(B7,顧客マスタ!A:D,4,FALSE),"") -> 御中
A8: 工事名 | B8: 吉野様邸 キッチンリフォーム | E8: 施工場所 | F8: 東京都港区南麻布
A9: 担当者 | B9: 吉野博 | C9: 目標粗利率 | D9: 0.25
A10: 施工住所
A12: ▼ 作成手順
A13: 1️⃣ | B13: 上の顧客ID・工事名・施工場所・担当者を入力
A14: 2️⃣ | B14: Claudeに「新規案件作成」と伝える
A15: 3️⃣ | B15: 案件テンプレートが複製され、情報が自動入力されます
A16: 4️⃣ | B16: 原価管理表に工事項目を入力→客出し金額が自動算出
A17: 5️⃣ | B17: 発注書兼請求書も同時に発行可能
A19: ■ システム構成一覧
A20: シート名 | B20: 役割 | C20: 主な用途 | D20: 備考
A21: 操作パネル | B21: コントロールセンター | C21: 新規案件作成・操作マニュアル | D21: ※このシート
A22: マスター設定 | B22: マスターデータ管理 | C22: 顧客・業者・工事カテゴリ等の登録
A23: 工事項目DB | B23: 単価データベース | C23: 全工種の単価・業者を一元管理 | D23: ★2024年統合済
A24: 業者DB | B24: 業者データベース | C24: 全業者の連絡先・支払条件
A25: 見積書 | B25: 見積作成 | C25: 顧客提出用見積書作成
A26: 実行予算 | B26: 原価管理 | C26: 実行予算の計算・利益率管理
A27: 案件管理 | B27: 案件データベース | C27: 全案件の進捗・収支・請求状況 | D27: ★中核シート
A28: ダッシュボード | B28: 経営ダッシュボード | C28: 売上・原価・利益・KPI・キャッシュフロー | D28: ★2024年拡張済
A29: 請求管理 | B29: 請求・入金管理 | C29: 請求書発行・入金消込・残額管理 | D29: ★NEW
A30: 支払管理 | B30: 発注・支払管理 | C30: 業者への発注・支払消込・未払管理 | D30: ★NEW
A31: 設計図v3 | B31: 設計ドキュメント | C31: システム設計・実装記録
A33: ■ 請求管理の使い方
A34: 🔹 概要 | B34: 請求書の発行から入金消込までを一元管理するシートです
A36: 🔹 操作手順
A37: 1️⃣ | B37: 「請求管理」シートを開く
A38: 2️⃣ | B38: B列に案件ID（P-001等）を入力 → 案件名・顧客名が自動取得
A39: 3️⃣ | B39: E列で請求種別を選択（着手金/完工金/一括/中間金/その他）
A40: 4️⃣ | B40: F列に請求日、G列に請求額を入力
A41: 5️⃣ | B41: 入金時に H列（入金日）と I列（入金額）を入力
A42: ✅ | B42: J列（残額）とK列（ステータス）が自動計算されます
B43: ※ 案件管理のX列～AC列にも自動連携されます
A45: ■ 支払管理の使い方
A46: 🔹 概要 | B46: 業者への発注・支払状況を一元管理するシートです
A48: 🔹 操作手順
A49: 1️⃣ | B49: 「支払管理」シートを開く
A50: 2️⃣ | B50: B列に案件ID、C列に業者IDを入力 → 業者名・支払条件が自動取得
A51: 3️⃣ | B51: E列に発注内容、F列に発注日、G列に発注額を入力
A52: 4️⃣ | B52: 支払時に H列（支払日）と I列（支払額）を入力
A53: 5️⃣ | B53: J列（残額）とK列（ステータス）が自動計算されます
A54: ✅ | B54: ダッシュボードの「未支払業者一覧」にも自動反映されます
B55: ※ 業者DBに未登録の業者IDはエラーになります。先にマスター設定で登録してください
A57: ■ ダッシュボードの見方
A58: 🔹 収支セクション（新規追加） | B58: ダッシュボード下部に追加された10個のKPI指標です
A60: 指標名 | B60: 内容 | C60: 見方
A61: 請求総額 | B61: 全案件の請求額合計 | C61: 請求管理G列の合計
A62: 入金済額 | B62: 入金確認済みの合計 | C62: 請求管理I列の合計
A63: 未入金額 | B63: 請求済み未入金の合計 | C63: 請求総額 − 入金済額
A64: 入金率 | B64: 入金の進捗率 | C64: 入金済額 ÷ 請求総額 × 100
A65: 発注総額 | B65: 全業者への発注額合計 | C65: 支払管理G列の合計
A66: 支払済額 | B66: 支払完了の合計 | C66: 支払管理I列の合計
A67: 未支払額 | B67: 未払いの合計 | C67: 発注総額 − 支払済額
A68: キャッシュフロー | B68: 手元資金の増減 | C68: 入金済額 − 支払済額（★最重要指標）
A69: 未支払業者数 | B69: 支払残のある業者数 | C69: 早急に対応が必要な件数
A71: ■ よくある質問（FAQ）
A72: Q1 | B72: 新しい業者を追加したい
A73: A1 | B73: 「マスター設定」シートの業者DBエリアに新規行を追加してください
A75: Q2 | B75: 請求書のステータスが「❤未入金」のまま
A76: A2 | B76: 請求管理のH列（入金日）とI列（入金額）を入力すると自動で「✅入金済」に変わります
A78: Q3 | B78: 工事項目DBに新しい単価を追加したい
A79: A3 | B79: 「工事項目DB」シートの最終行に新規行を追加。カテゴリ・品名・単価・業者名を入力
A81: Q4 | B81: ダッシュボードのキャッシュフローがマイナスになっている
A82: A4 | B82: 支払済額が入金済額を上回っています。未入金の請求がないか確認してください
A84: Q5 | B84: 旧システムのデータを確認したい
A85: A5 | B85: 旧シートは削除されず非表示で保存されています。右クリック→「再表示」で閲覧可能
A88: ■ S表紙の案件切替
A89: 🔹 概要 | B89: S表紙（御見積書）を任意の案件に切り替えできます
A91: 🔹 操作手順
A92: 1️⃣ | B92: 「S表紙」シートを開く
A93: 2️⃣ | B93: J2セルに切替先のシート名を入力（例: P-004_○○様邸○○）
A94: 3️⃣ | B94: Claudeに「S表紙を切り替えて」と伝える
A95: ✅ | B95: I36～I55の20工種金額が指定案件の値に自動更新されます
B96: ※ INDIRECT関数がセキュリティ制限のため、Claudeが数式を書き換える方式です
A98: ■ 領収書の使い方
A99: 🔹 概要 | B99: 請求管理のデータから領収書を自動生成します
A101: 🔹 操作手順
A102: 1️⃣ | B102: 「領収書」シートを開く
A103: 2️⃣ | B103: J2セルに請求ID（INV-001等）を入力
A104: 3️⃣ | B104: 宛名・金額・但し書き・内訳が全て自動取得されます
A105: 4️⃣ | B105: PDF出力または印刷で発行（印刷範囲: A1:H26、A4縦）
A106: ■ システム更新履歴
A107: 2024年 | B107: 旧工種別シート→工事項目DB統合、請求管理・支払管理新規作成、ダッシュボード拡張
A109: ■ PDF出力ボタンエリア
B110: ※ 各ボタンにマクロを割り当ててください
B111: ▶ 見積書PDF出力
B112: ▶ 領収書PDF出力
B113: ▶ 発注書PDF出力

Sheet ダッシュボード
A1: CRM ダッシュボード
A2: 株式会社LinK - 営業・案件パフォーマンス分析
A3: ※ 案件管理・顧客マスタのデータをリアルタイムで集計表示します
A4: 受注金額合計 | D4: 粗利率平均 | G4: 未回収残高 | J4: キャッシュフロー
A5: =SUMIFS(案件管理!F5:F96,案件管理!I5:I96,"⑤受注")+SUMIFS(案件管理!F5:F96,案件管理!I5:I96,"⑦完工") -> 4754440 | D5: =IFERROR(AVERAGE(案件管理!H5:H96),0) -> 0.26950193 | G5: =SUM(請求管理!G:G)-SUM(請求管理!I:I) -> 627220 | J5: =SUM(請求管理!I:I)-SUM(支払管理!I:I) -> 3922220
A7: ■ KPI サマリー
A8: 総案件数 | C8: アクティブ案件 | E8: 受注数 | G8: 失注数 | I8: 成約率 | K8: 滞留案件数 | M8: 見積総額
A9: =COUNTA(案件管理!I5:I96) -> 3 | C9: =COUNTIFS(案件管理!I5:I96,"<>",案件管理!I5:I96,"<>⑥失注",案件管理!I5:I96,"<>⑦完工") -> 2 | E9: =COUNTIF(案件管理!I5:I96,"⑤受注")+COUNTIF(案件管理!I5:I96,"⑦完工") -> 2 | G9: =COUNTIF(案件管理!I5:I96,"⑥失注") -> 0 | I9: =IFERROR((COUNTIF(案件管理!I5:I96,"⑤受注")+COUNTIF(案件管理!I5:I96,"⑦完工"))/(COUNTIF(案件管理!I5:I96,"⑤受注")+COUNTIF(案件管理!I5:I96,"⑦完工")+COUNTIF(案件管理!I5:I96,"⑥失注")),0) -> 1 | K9: =COUNTIF(案件管理!L5:L96,"⚠滞留") -> 1 | M9: =SUMIF(案件管理!I5:I96,"<>",案件管理!F5:F96) -> 6554440
A10: 件 | C10: 件（進行中） | E10: 件 | G10: 件 | I10: （受注数 / 確定数） | K10: 件（30日超過） | M10: （全案件見積合計）
A11: 受注金額合計 | C11: アクティブ金額 | E11: 受注金額 | G11: 失注金額 | I11: 平均経過日数 | K11: 滞留平均日数 | M11: 金額ベース成約率
A12: =SUMIFS(案件管理!F5:F96,案件管理!I5:I96,"⑤受注")+SUMIFS(案件管理!F5:F96,案件管理!I5:I96,"⑦完工") -> 4754440 | C12: =SUMIFS(案件管理!F5:F96,案件管理!I5:I96,"<>",案件管理!I5:I96,"<>⑥失注",案件管理!I5:I96,"<>⑦完工") -> 5300000 | E12: =IFERROR(SUMIFS(案件管理!F5:F96,案件管理!I5:I96,"⑤受注")+SUMIFS(案件管理!F5:F96,案件管理!I5:I96,"⑦完工"),0) -> 4754440 | G12: =IFERROR(SUMIFS(案件管理!F5:F96,案件管理!I5:I96,"⑥失注"),0) -> 0 | I12: =IFERROR(AVERAGE(案件管理!K5:K96),0) -> 261 | K12: =IFERROR(AVERAGEIFS(案件管理!K5:K96,案件管理!L5:L96,"⚠滞留"),0) -> 385 | M12: =IFERROR((SUMIFS(案件管理!F5:F96,案件管理!I5:I96,"⑤受注")+SUMIFS(案件管理!F5:F96,案件管理!I5:I96,"⑦完工"))/SUMIF(案件管理!I5:I96,"<>",案件管理!F5:F96),0) -> 0.725377
A14: ■ ステータス別分布 | I14: ■ 担当者別実績
A15: ステータス | B15: 件数 | C15: 構成比 | D15: 見積金額合計 | E15: 平均経過日数 | F15: バーチャート | I15: 担当者 | J15: 担当案件数 | K15: 受注数 | L15: 受注率 | M15: 受注金額 | N15: 滞留数
A16: ①リード | B16: =COUNTIF(案件管理!I:I,"①リード") -> 0 | C16: =IFERROR(B16/SUM($B$16:$B$22),0) -> 0 | D16: =SUMIF(案件管理!I:I,"①リード",案件管理!F:F) -> 0 | E16: =IFERROR(AVERAGEIF(案件管理!I:I,"①リード",案件管理!K:K),"-") -> - | I16: =IF(マスター設定!J8<>"",マスター設定!J8,"") -> 吉野博 | J16: =IF(I16<>"",COUNTIF(案件管理!M:M,I16),"") -> 3 | K16: =IF(I16<>"",COUNTIFS(案件管理!M:M,I16,案件管理!I:I,"⑤受注")+COUNTIFS(案件管理!M:M,I16,案件管理!I:I,"⑦完工"),"") -> 2 | L16: =IF(AND(I16<>"",J16>0),K16/J16,"") -> 0.66666667 | M16: =IF(I16<>"",SUMIFS(案件管理!F:F,案件管理!M:M,I16,案件管理!I:I,"⑤受注")+SUMIFS(案件管理!F:F,案件管理!M:M,I16,案件管理!I:I,"⑦完工"),"") -> 4754440 | N16: =IF(I16<>"",COUNTIFS(案件管理!M:M,I16,案件管理!L:L,"⚠滞留"),"") -> 1
A17: ②商談中 | B17: =COUNTIF(案件管理!I:I,"②商談中") -> 0 | C17: =IFERROR(B17/SUM($B$16:$B$22),0) -> 0 | D17: =SUMIF(案件管理!I:I,"②商談中",案件管理!F:F) -> 0 | E17: =IFERROR(AVERAGEIF(案件管理!I:I,"②商談中",案件管理!K:K),"-") -> - | I17: =IF(マスター設定!J9<>"",マスター設定!J9,"") | J17: =IF(I17<>"",COUNTIF(案件管理!M:M,I17),"") | K17: =IF(I17<>"",COUNTIFS(案件管理!M:M,I17,案件管理!I:I,"⑤受注")+COUNTIFS(案件管理!M:M,I17,案件管理!I:I,"⑦完工"),"") | L17: =IF(AND(I17<>"",J17>0),K17/J17,"") | M17: =IF(I17<>"",SUMIFS(案件管理!F:F,案件管理!M:M,I17,案件管理!I:I,"⑤受注")+SUMIFS(案件管理!F:F,案件管理!M:M,I17,案件管理!I:I,"⑦完工"),"") | N17: =IF(I17<>"",COUNTIFS(案件管理!M:M,I17,案件管理!L:L,"⚠滞留"),"")
A18: ③見積作成中 | B18: =COUNTIF(案件管理!I:I,"③見積作成中") -> 0 | C18: =IFERROR(B18/SUM($B$16:$B$22),0) -> 0 | D18: =SUMIF(案件管理!I:I,"③見積作成中",案件管理!F:F) -> 0 | E18: =IFERROR(AVERAGEIF(案件管理!I:I,"③見積作成中",案件管理!K:K),"-") -> - | I18: =IF(マスター設定!J10<>"",マスター設定!J10,"") | J18: =IF(I18<>"",COUNTIF(案件管理!M:M,I18),"") | K18: =IF(I18<>"",COUNTIFS(案件管理!M:M,I18,案件管理!I:I,"⑤受注")+COUNTIFS(案件管理!M:M,I18,案件管理!I:I,"⑦完工"),"") | L18: =IF(AND(I18<>"",J18>0),K18/J18,"") | M18: =IF(I18<>"",SUMIFS(案件管理!F:F,案件管理!M:M,I18,案件管理!I:I,"⑤受注")+SUMIFS(案件管理!F:F,案件管理!M:M,I18,案件管理!I:I,"⑦完工"),"") | N18: =IF(I18<>"",COUNTIFS(案件管理!M:M,I18,案件管理!L:L,"⚠滞留"),"")
A19: ④見積提出済 | B19: =COUNTIF(案件管理!I:I,"④見積提出済") -> 1 | C19: =IFERROR(B19/SUM($B$16:$B$22),0) -> 0.33333333 | D19: =SUMIF(案件管理!I:I,"④見積提出済",案件管理!F:F) -> 1800000 | E19: =IFERROR(AVERAGEIF(案件管理!I:I,"④見積提出済",案件管理!K:K),"-") -> 385 | I19: =IF(マスター設定!J11<>"",マスター設定!J11,"") | J19: =IF(I19<>"",COUNTIF(案件管理!M:M,I19),"") | K19: =IF(I19<>"",COUNTIFS(案件管理!M:M,I19,案件管理!I:I,"⑤受注")+COUNTIFS(案件管理!M:M,I19,案件管理!I:I,"⑦完工"),"") | L19: =IF(AND(I19<>"",J19>0),K19/J19,"") | M19: =IF(I19<>"",SUMIFS(案件管理!F:F,案件管理!M:M,I19,案件管理!I:I,"⑤受注")+SUMIFS(案件管理!F:F,案件管理!M:M,I19,案件管理!I:I,"⑦完工"),"") | N19: =IF(I19<>"",COUNTIFS(案件管理!M:M,I19,案件管理!L:L,"⚠滞留"),"")
A20: ⑤受注 | B20: =COUNTIF(案件管理!I:I,"⑤受注") -> 1 | C20: =IFERROR(B20/SUM($B$16:$B$22),0) -> 0.33333333 | D20: =SUMIF(案件管理!I:I,"⑤受注",案件管理!F:F) -> 3500000 | E20: =IFERROR(AVERAGEIF(案件管理!I:I,"⑤受注",案件管理!K:K),"-") -> 398 | I20: =IF(マスター設定!J12<>"",マスター設定!J12,"") | J20: =IF(I20<>"",COUNTIF(案件管理!M:M,I20),"") | K20: =IF(I20<>"",COUNTIFS(案件管理!M:M,I20,案件管理!I:I,"⑤受注")+COUNTIFS(案件管理!M:M,I20,案件管理!I:I,"⑦完工"),"") | L20: =IF(AND(I20<>"",J20>0),K20/J20,"") | M20: =IF(I20<>"",SUMIFS(案件管理!F:F,案件管理!M:M,I20,案件管理!I:I,"⑤受注")+SUMIFS(案件管理!F:F,案件管理!M:M,I20,案件管理!I:I,"⑦完工"),"") | N20: =IF(I20<>"",COUNTIFS(案件管理!M:M,I20,案件管理!L:L,"⚠滞留"),"")
A21: ⑥失注 | B21: =COUNTIF(案件管理!I:I,"⑥失注") -> 0 | C21: =IFERROR(B21/SUM($B$16:$B$22),0) -> 0 | D21: =SUMIF(案件管理!I:I,"⑥失注",案件管理!F:F) -> 0 | E21: =IFERROR(AVERAGEIF(案件管理!I:I,"⑥失注",案件管理!K:K),"-") -> - | I21: =IF(マスター設定!J13<>"",マスター設定!J13,"") | J21: =IF(I21<>"",COUNTIF(案件管理!M:M,I21),"") | K21: =IF(I21<>"",COUNTIFS(案件管理!M:M,I21,案件管理!I:I,"⑤受注")+COUNTIFS(案件管理!M:M,I21,案件管理!I:I,"⑦完工"),"") | L21: =IF(AND(I21<>"",J21>0),K21/J21,"") | M21: =IF(I21<>"",SUMIFS(案件管理!F:F,案件管理!M:M,I21,案件管理!I:I,"⑤受注")+SUMIFS(案件管理!F:F,案件管理!M:M,I21,案件管理!I:I,"⑦完工"),"") | N21: =IF(I21<>"",COUNTIFS(案件管理!M:M,I21,案件管理!L:L,"⚠滞留"),"")
A22: ⑦完工 | B22: =COUNTIF(案件管理!I:I,"⑦完工") -> 1 | C22: =IFERROR(B22/SUM($B$16:$B$22),0) -> 0.33333333 | D22: =SUMIF(案件管理!I:I,"⑦完工",案件管理!F:F) -> 1254440 | E22: =IFERROR(AVERAGEIF(案件管理!I:I,"⑦完工",案件管理!K:K),"-") -> 0 | I22: =IF(マスター設定!J14<>"",マスター設定!J14,"") | J22: =IF(I22<>"",COUNTIF(案件管理!M:M,I22),"") | K22: =IF(I22<>"",COUNTIFS(案件管理!M:M,I22,案件管理!I:I,"⑤受注")+COUNTIFS(案件管理!M:M,I22,案件管理!I:I,"⑦完工"),"") | L22: =IF(AND(I22<>"",J22>0),K22/J22,"") | M22: =IF(I22<>"",SUMIFS(案件管理!F:F,案件管理!M:M,I22,案件管理!I:I,"⑤受注")+SUMIFS(案件管理!F:F,案件管理!M:M,I22,案件管理!I:I,"⑦完工"),"") | N22: =IF(I22<>"",COUNTIFS(案件管理!M:M,I22,案件管理!L:L,"⚠滞留"),"")
I23: =IF(マスター設定!J15<>"",マスター設定!J15,"") | J23: =IF(I23<>"",COUNTIF(案件管理!M:M,I23),"") | K23: =IF(I23<>"",COUNTIFS(案件管理!M:M,I23,案件管理!I:I,"⑤受注")+COUNTIFS(案件管理!M:M,I23,案件管理!I:I,"⑦完工"),"") | L23: =IF(AND(I23<>"",J23>0),K23/J23,"") | M23: =IF(I23<>"",SUMIFS(案件管理!F:F,案件管理!M:M,I23,案件管理!I:I,"⑤受注")+SUMIFS(案件管理!F:F,案件管理!M:M,I23,案件管理!I:I,"⑦完工"),"") | N23: =IF(I23<>"",COUNTIFS(案件管理!M:M,I23,案件管理!L:L,"⚠滞留"),"")
A24: ■ 滞留案件一覧（30日超過） | I24: =IF(マスター設定!J16<>"",マスター設定!J16,"") | J24: =IF(I24<>"",COUNTIF(案件管理!M:M,I24),"") | K24: =IF(I24<>"",COUNTIFS(案件管理!M:M,I24,案件管理!I:I,"⑤受注")+COUNTIFS(案件管理!M:M,I24,案件管理!I:I,"⑦完工"),"") | L24: =IF(AND(I24<>"",J24>0),K24/J24,"") | M24: =IF(I24<>"",SUMIFS(案件管理!F:F,案件管理!M:M,I24,案件管理!I:I,"⑤受注")+SUMIFS(案件管理!F:F,案件管理!M:M,I24,案件管理!I:I,"⑦完工"),"") | N24: =IF(I24<>"",COUNTIFS(案件管理!M:M,I24,案件管理!L:L,"⚠滞留"),"")
A25: 案件ID | B25: 顧客名 | C25: 案件名 | D25: ステータス | E25: 経過日数 | F25: 見積金額 | G25: 担当者 | H25: →詳細 | I25: =IF(マスター設定!J17<>"",マスター設定!J17,"") | J25: =IF(I25<>"",COUNTIF(案件管理!M:M,I25),"") | K25: =IF(I25<>"",COUNTIFS(案件管理!M:M,I25,案件管理!I:I,"⑤受注")+COUNTIFS(案件管理!M:M,I25,案件管理!I:I,"⑦完工"),"") | L25: =IF(AND(I25<>"",J25>0),K25/J25,"") | M25: =IF(I25<>"",SUMIFS(案件管理!F:F,案件管理!M:M,I25,案件管理!I:I,"⑤受注")+SUMIFS(案件管理!F:F,案件管理!M:M,I25,案件管理!I:I,"⑦完工"),"") | N25: =IF(I25<>"",COUNTIFS(案件管理!M:M,I25,案件管理!L:L,"⚠滞留"),"")
A26: {=IFERROR(_xlfn._xlws.FILTER(案件管理!A5:A96,(案件管理!L5:L96="⚠滞留")),"")} -> P-002 | B26: {=IFERROR(_xlfn._xlws.FILTER(案件管理!C5:C96,(案件管理!L5:L96="⚠滞留")),"")} -> 矢島不動産管理株式会社 | C26: {=IFERROR(_xlfn._xlws.FILTER(案件管理!D5:D96,(案件管理!L5:L96="⚠滞留")),"")} -> 吉野様邸 外壁塗装工事 | D26: {=IFERROR(_xlfn._xlws.FILTER(案件管理!I5:I96,(案件管理!L5:L96="⚠滞留")),"")} -> ④見積提出済 | E26: {=IFERROR(_xlfn._xlws.FILTER(案件管理!K5:K96,(案件管理!L5:L96="⚠滞留")),"")} -> 385 | F26: {=IFERROR(_xlfn._xlws.FILTER(案件管理!F5:F96,(案件管理!L5:L96="⚠滞留")),"")} -> 1800000 | G26: {=IFERROR(_xlfn._xlws.FILTER(案件管理!M5:M96,(案件管理!L5:L96="⚠滞留")),"")} -> 吉野博 | H26: =IF(A26="","",HYPERLINK("#案件管理!A1","→詳細")) -> →詳細
H27: =IF(A27="","",HYPERLINK("#案件管理!A1","→詳細"))
H28: =IF(A28="","",HYPERLINK("#案件管理!A1","→詳細")) | I28: ■ 顧客別実績（トップ10）
H29: =IF(A29="","",HYPERLINK("#案件管理!A1","→詳細")) | I29: 顧客ID | J29: 顧客名 | K29: 累計案件数 | L29: 累計受注額 | M29: ランク | N29: ステータス | O29: →詳細
H30: =IF(A30="","",HYPERLINK("#案件管理!A1","→詳細")) | I30: {=IFERROR(_xlfn.SORTBY(_xlfn._xlws.FILTER(顧客マスタ!A5:A104,顧客マスタ!L5:L104>0),_xlfn._xlws.FILTER(顧客マスタ!M5:M104,顧客マスタ!L5:L104>0),-1),"")} -> C-001 | J30: {=IFERROR(_xlfn.SORTBY(_xlfn._xlws.FILTER(顧客マスタ!C5:C104,顧客マスタ!L5:L104>0),_xlfn._xlws.FILTER(顧客マスタ!M5:M104,顧客マスタ!L5:L104>0),-1),"")} -> 矢島不動産管理株式会社 | K30: {=IFERROR(_xlfn.SORTBY(_xlfn._xlws.FILTER(顧客マスタ!L5:L104,顧客マスタ!L5:L104>0),_xlfn._xlws.FILTER(顧客マスタ!M5:M104,顧客マスタ!L5:L104>0),-1),"")} -> 3 | L30: {=IFERROR(_xlfn.SORTBY(_xlfn._xlws.FILTER(顧客マスタ!M5:M104,顧客マスタ!L5:L104>0),_xlfn._xlws.FILTER(顧客マスタ!M5:M104,顧客マスタ!L5:L104>0),-1),"")} -> 4754440 | M30: {=IFERROR(_xlfn.SORTBY(_xlfn._xlws.FILTER(顧客マスタ!O5:O104,顧客マスタ!L5:L104>0),_xlfn._xlws.FILTER(顧客マスタ!M5:M104,顧客マスタ!L5:L104>0),-1),"")} -> A | N30: {=IFERROR(_xlfn.SORTBY(_xlfn._xlws.FILTER(顧客マスタ!R5:R104,顧客マスタ!L5:L104>0),_xlfn._xlws.FILTER(顧客マスタ!M5:M104,顧客マスタ!L5:L104>0),-1),"")} -> アクティブ | O30: =IF(I30="","",HYPERLINK("#案件管理!A1","→詳細")) -> →詳細
O31: =IF(I31="","",HYPERLINK("#案件管理!A1","→詳細"))
A32: ■ 失注分析 | O32: =IF(I32="","",HYPERLINK("#案件管理!A1","→詳細"))
A33: ※ 案件管理の失注理由（R列）を集計。次回提案改善に活用してください。 | O33: =IF(I33="","",HYPERLINK("#案件管理!A1","→詳細"))
O34: =IF(I34="","",HYPERLINK("#案件管理!A1","→詳細"))
A35: 失注理由 | B35: 件数 | C35: 構成比 | D35: 失注金額合計 | E35: 平均見積金額 | F35: 直近失注日 | G35: 対策メモ | O35: =IF(I35="","",HYPERLINK("#案件管理!A1","→詳細"))
A36: 価格が合わない | B36: =COUNTIFS(案件管理!I:I,"⑥失注",案件管理!R:R,"*"&A36&"*") -> 0 | C36: =IFERROR(B36/SUM(B36:B40),0) -> 0 | D36: =SUMIFS(案件管理!F:F,案件管理!I:I,"⑥失注",案件管理!R:R,"*"&A36&"*") -> 0 | E36: =IFERROR(AVERAGEIFS(案件管理!F:F,案件管理!I:I,"⑥失注",案件管理!R:R,"*"&A36&"*"),0) -> 0 | F36: =IFERROR(_xlfn.MAXIFS(案件管理!J:J,案件管理!I:I,"⑥失注",案件管理!R:R,"*"&A36&"*"),"") -> 0 | O36: =IF(I36="","",HYPERLINK("#案件管理!A1","→詳細"))
A37: 工期が合わない | B37: =COUNTIFS(案件管理!I:I,"⑥失注",案件管理!R:R,"*"&A37&"*") -> 0 | C37: =IFERROR(B37/SUM(B36:B40),0) -> 0 | D37: =SUMIFS(案件管理!F:F,案件管理!I:I,"⑥失注",案件管理!R:R,"*"&A37&"*") -> 0 | E37: =IFERROR(AVERAGEIFS(案件管理!F:F,案件管理!I:I,"⑥失注",案件管理!R:R,"*"&A37&"*"),0) -> 0 | F37: =IFERROR(_xlfn.MAXIFS(案件管理!J:J,案件管理!I:I,"⑥失注",案件管理!R:R,"*"&A37&"*"),"") -> 0 | O37: =IF(I37="","",HYPERLINK("#案件管理!A1","→詳細"))
A38: 他社に決定 | B38: =COUNTIFS(案件管理!I:I,"⑥失注",案件管理!R:R,"*"&A38&"*") -> 0 | C38: =IFERROR(B38/SUM(B36:B40),0) -> 0 | D38: =SUMIFS(案件管理!F:F,案件管理!I:I,"⑥失注",案件管理!R:R,"*"&A38&"*") -> 0 | E38: =IFERROR(AVERAGEIFS(案件管理!F:F,案件管理!I:I,"⑥失注",案件管理!R:R,"*"&A38&"*"),0) -> 0 | F38: =IFERROR(_xlfn.MAXIFS(案件管理!J:J,案件管理!I:I,"⑥失注",案件管理!R:R,"*"&A38&"*"),"") -> 0 | O38: =IF(I38="","",HYPERLINK("#案件管理!A1","→詳細"))
A39: 対応・コミュニケーション | B39: =COUNTIFS(案件管理!I:I,"⑥失注",案件管理!R:R,"*"&A39&"*") -> 0 | C39: =IFERROR(B39/SUM(B36:B40),0) -> 0 | D39: =SUMIFS(案件管理!F:F,案件管理!I:I,"⑥失注",案件管理!R:R,"*"&A39&"*") -> 0 | E39: =IFERROR(AVERAGEIFS(案件管理!F:F,案件管理!I:I,"⑥失注",案件管理!R:R,"*"&A39&"*"),0) -> 0 | F39: =IFERROR(_xlfn.MAXIFS(案件管理!J:J,案件管理!I:I,"⑥失注",案件管理!R:R,"*"&A39&"*"),"") -> 0 | O39: =IF(I39="","",HYPERLINK("#案件管理!A1","→詳細"))
A40: その他・不明 | B40: =COUNTIFS(案件管理!I:I,"⑥失注",案件管理!R:R,"*"&A40&"*") -> 0 | C40: =IFERROR(B40/SUM(B36:B40),0) -> 0 | D40: =SUMIFS(案件管理!F:F,案件管理!I:I,"⑥失注",案件管理!R:R,"*"&A40&"*") -> 0 | E40: =IFERROR(AVERAGEIFS(案件管理!F:F,案件管理!I:I,"⑥失注",案件管理!R:R,"*"&A40&"*"),0) -> 0 | F40: =IFERROR(_xlfn.MAXIFS(案件管理!J:J,案件管理!I:I,"⑥失注",案件管理!R:R,"*"&A40&"*"),"") -> 0
A41: 合計 | B41: =SUM(B36:B40) -> 0 | C41: =IFERROR(B41/B41,0) -> 0 | D41: =SUM(D36:D40) -> 0 | E41: =IFERROR(D41/B41,0) -> 0
A43: ■ 請求・入金管理
A44: ※ 案件管理の請求書ステータス・入金ステータスを集計。未回収金額を即座に把握できます。
A46: 請求書発行済 | B46: 請求書未発行 | D46: 入金済 | E46: 未入金 | G46: 未回収率
A47: =COUNTIF(案件管理!X:X,"✅発行済") -> 2 | B47: =COUNTIF(案件管理!X:X,"❌未発行") -> 1 | D47: =COUNTIF(案件管理!AA:AA,"✅入金済") -> 1 | E47: =COUNTIF(案件管理!AA:AA,"❌未入金") -> 1 | G47: =IFERROR(SUMIFS(案件管理!Z:Z,案件管理!AA:AA,"❌未入金")/SUMIFS(案件管理!Z:Z,案件管理!X:X,"✅発行済"),0) -> 0.263846
A48: =SUMIFS(案件管理!Z:Z,案件管理!X:X,"✅発行済") -> 4754440 | B48: =SUMIFS(案件管理!Q:Q,案件管理!X:X,"❌未発行") -> 0 | D48: =SUMIFS(案件管理!AC:AC,案件管理!AA:AA,"✅入金済") -> 3500000 | E48: =SUMIFS(案件管理!Z:Z,案件管理!AA:AA,"❌未入金") -> 1254440 | G48: =SUMIFS(案件管理!Z:Z,案件管理!AA:AA,"❌未入金") -> 1254440
A49: （請求済金額） | B49: （未請求金額） | D49: （入金済金額） | E49: （未入金金額） | G49: （未回収残高）
A51: ▼ 未入金案件一覧
A52: 案件ID | B52: 顧客名 | C52: 案件名 | D52: 請求金額 | E52: 請求日 | F52: 経過日数 | G52: 担当者
A53: {=IFERROR(_xlfn._xlws.FILTER(案件管理!A5:A96,案件管理!AA5:AA96="❌未入金"),"未入金案件なし")} -> P-003 | B53: {=IFERROR(_xlfn._xlws.FILTER(案件管理!C5:C96,案件管理!AA5:AA96="❌未入金"),"")} -> 矢島不動産管理株式会社 | C53: {=IFERROR(_xlfn._xlws.FILTER(案件管理!D5:D96,案件管理!AA5:AA96="❌未入金"),"")} -> 吉野様邸 キッチンリフォーム | D53: {=IFERROR(_xlfn._xlws.FILTER(案件管理!Z5:Z96,案件管理!AA5:AA96="❌未入金"),"")} -> 1254440 | E53: {=IFERROR(_xlfn._xlws.FILTER(案件管理!Y5:Y96,案件管理!AA5:AA96="❌未入金"),"")} -> 46064 | F53: {=IFERROR(IF(_xlfn._xlws.FILTER(案件管理!Y5:Y96,案件管理!AA5:AA96="❌未入金")<>"",TODAY()-_xlfn._xlws.FILTER(案件管理!Y5:Y96,案件管理!AA5:AA96="❌未入金"),""),"")} -> 6 | G53: {=IFERROR(_xlfn._xlws.FILTER(案件管理!M5:M96,案件管理!AA5:AA96="❌未入金"),"")} -> 吉野博
A56: ▼ 請求書未発行案件一覧
A57: 案件ID | B57: 顧客名 | C57: 案件名 | D57: ステータス | E57: 見積金額 | F57: 経過日数 | G57: 担当者
A58: {=IFERROR(_xlfn._xlws.FILTER(案件管理!A5:A96,案件管理!X5:X96="❌未発行"),"未発行案件なし")} -> P-002 | B58: {=IFERROR(_xlfn._xlws.FILTER(案件管理!C5:C96,案件管理!X5:X96="❌未発行"),"")} -> 矢島不動産管理株式会社 | C58: {=IFERROR(_xlfn._xlws.FILTER(案件管理!D5:D96,案件管理!X5:X96="❌未発行"),"")} -> 吉野様邸 外壁塗装工事 | D58: {=IFERROR(_xlfn._xlws.FILTER(案件管理!I5:I96,案件管理!X5:X96="❌未発行"),"")} -> ④見積提出済 | E58: {=IFERROR(_xlfn._xlws.FILTER(案件管理!F5:F96,案件管理!X5:X96="❌未発行"),"")} -> 1800000 | F58: {=IFERROR(_xlfn._xlws.FILTER(案件管理!K5:K96,案件管理!X5:X96="❌未発行"),"")} -> 385 | G58: {=IFERROR(_xlfn._xlws.FILTER(案件管理!M5:M96,案件管理!X5:X96="❌未発行"),"")} -> 吉野博
A59: ■ 受注区分管理
A60: ※ 受注(⑤受注/⑦完工)・未受注(商談中)・失注(⑥失注) を自動集計
A62: 🟢受注 | B62: 🟡未受注（商談中） | C62: 🔴失注 | E62: 受注率 | F62: 受注金額合計 | G62: 失注金額合計
A63: =COUNTIF(案件管理!AD:AD,"🟢受注")&" 件" -> 2 件 | B63: =COUNTIF(案件管理!AD:AD,"🟡未受注")&" 件" -> 0 件 | C63: =COUNTIF(案件管理!AD:AD,"🔴失注")&" 件" -> 0 件 | E63: =IFERROR(COUNTIF(案件管理!AD:AD,"🟢受注")/(COUNTIF(案件管理!AD:AD,"🟢受注")+COUNTIF(案件管理!AD:AD,"🔴失注")),0) -> 1 | F63: =SUMIFS(案件管理!F:F,案件管理!AD:AD,"🟢受注") -> 4754440 | G63: =SUMIFS(案件管理!F:F,案件管理!AD:AD,"🔴失注") -> 0
A64: =SUMIFS(案件管理!F:F,案件管理!AD:AD,"🟢受注") -> 4754440 | B64: =SUMIFS(案件管理!F:F,案件管理!AD:AD,"🟡未受注") -> 0 | C64: =SUMIFS(案件管理!F:F,案件管理!AD:AD,"🔴失注") -> 0
A66: ▼ 未受注案件一覧（商談中）
A67: 案件ID | B67: 顧客名 | C67: 案件名 | D67: ステータス | E67: 見積金額 | F67: 経過日数 | G67: 担当者
A68: {=IFERROR(_xlfn._xlws.FILTER(案件管理!A5:A96,案件管理!AD5:AD96="🟡未受注"),"未受注案件なし")} -> 未受注案件なし | B68: {=IFERROR(_xlfn._xlws.FILTER(案件管理!C5:C96,案件管理!AD5:AD96="🟡未受注"),"")} | C68: {=IFERROR(_xlfn._xlws.FILTER(案件管理!D5:D96,案件管理!AD5:AD96="🟡未受注"),"")} | D68: {=IFERROR(_xlfn._xlws.FILTER(案件管理!I5:I96,案件管理!AD5:AD96="🟡未受注"),"")} | E68: {=IFERROR(_xlfn._xlws.FILTER(案件管理!F5:F96,案件管理!AD5:AD96="🟡未受注"),"")} | F68: {=IFERROR(_xlfn._xlws.FILTER(案件管理!K5:K96,案件管理!AD5:AD96="🟡未受注"),"")} | G68: {=IFERROR(_xlfn._xlws.FILTER(案件管理!M5:M96,案件管理!AD5:AD96="🟡未受注"),"")}
A70: ▼ 失注案件一覧
A71: 案件ID | B71: 顧客名 | C71: 案件名 | D71: 失注理由 | E71: 見積金額 | F71: 失注日 | G71: 担当者
A72: {=IFERROR(_xlfn._xlws.FILTER(案件管理!A5:A96,案件管理!AD5:AD96="🔴失注"),"失注案件なし")} -> 失注案件なし | B72: {=IFERROR(_xlfn._xlws.FILTER(案件管理!C5:C96,案件管理!AD5:AD96="🔴失注"),"")} | C72: {=IFERROR(_xlfn._xlws.FILTER(案件管理!D5:D96,案件管理!AD5:AD96="🔴失注"),"")} | D72: {=IFERROR(_xlfn._xlws.FILTER(案件管理!R5:R96,案件管理!AD5:AD96="🔴失注"),"")} | E72: {=IFERROR(_xlfn._xlws.FILTER(案件管理!F5:F96,案件管理!AD5:AD96="🔴失注"),"")} | F72: {=IFERROR(_xlfn._xlws.FILTER(案件管理!J5:J96,案件管理!AD5:AD96="🔴失注"),"")} | G72: {=IFERROR(_xlfn._xlws.FILTER(案件管理!M5:M96,案件管理!AD5:AD96="🔴失注"),"")}
A74: ■ 収支サマリー（キャッシュフロー）
A75: ※ 請求管理・支払管理シートのデータを自動集計。入金・支払の状況を即座に把握できます。
A77: 請求累計額 | B77: 入金累計額 | C77: 未回収残高 | E77: 発注累計額 | F77: 支払累計額 | G77: 未支払残高
A78: =SUM(請求管理!G:G) -> 4754440 | B78: =SUM(請求管理!I:I) -> 4127220 | C78: =SUM(請求管理!J:J) -> 627220 | E78: =SUM(支払管理!G:G) -> 250500 | F78: =SUM(支払管理!I:I) -> 205000 | G78: =SUM(支払管理!J:J) -> 45500
A79: （全請求額合計） | B79: （全入金額合計） | C79: （請求額－入金額） | E79: （全発注額合計） | F79: （全支払額合計） | G79: （発注額－支払額）
A81: 入金済粗利 | B81: 回収率 | C81: 支払率 | E81: キャッシュフロー
A82: =B78-F78 -> 3922220 | B82: =IFERROR(B78/A78,0) -> 0.868077 | C82: =IFERROR(F78/E78,0) -> 0.81836327 | E82: =B78-F78 -> 3922220
A83: （入金済－支払済） | B83: （入金額/請求額） | C83: （支払額/発注額） | E83: （入金済－支払済=手元資金）
A85: ▼ 未支払業者一覧
A86: 支払ID | B86: 案件ID | C86: 業者名 | D86: 工事内容 | E86: 発注額 | F86: 未支払残額 | G86: 支払条件
A87: {=IFERROR(_xlfn._xlws.FILTER(支払管理!A5:A104,支払管理!K5:K104="❌未支払"),"未支払なし")} -> PAY-003 | B87: {=IFERROR(_xlfn._xlws.FILTER(支払管理!B5:B104,支払管理!K5:K104="❌未支払"),"")} -> P-003 | C87: {=IFERROR(_xlfn._xlws.FILTER(支払管理!D5:D104,支払管理!K5:K104="❌未支払"),"")} -> chic工房 | D87: {=IFERROR(_xlfn._xlws.FILTER(支払管理!E5:E104,支払管理!K5:K104="❌未支払"),"")} -> クロス張替え・CFシート | E87: {=IFERROR(_xlfn._xlws.FILTER(支払管理!G5:G104,支払管理!K5:K104="❌未支払"),"")} -> 45500 | F87: {=IFERROR(_xlfn._xlws.FILTER(支払管理!J5:J104,支払管理!K5:K104="❌未支払"),"")} -> 45500 | G87: {=IFERROR(_xlfn._xlws.FILTER(支払管理!L5:L104,支払管理!K5:K104="❌未支払"),"")} -> 0
A89: ■ 顧客別売上ランキング
A90: 顧客ID | B90: 顧客名 | C90: 案件数 | D90: 売上合計 | E90: 平均粗利率 | F90: →詳細
A91: C-001 | B91: =IFERROR(VLOOKUP(A91,顧客マスタ!A:C,3,FALSE),"") -> 矢島不動産管理株式会社 | C91: =COUNTIFS(案件管理!B$5:B$96,A91) -> 3 | D91: =SUMIFS(案件管理!F$5:F$96,案件管理!B$5:B$96,A91) -> 6554440 | E91: =IFERROR(AVERAGEIFS(案件管理!H$5:H$96,案件管理!B$5:B$96,A91,案件管理!H$5:H$96,"<>"),"") -> 0.26950193 | F91: =IF(A91="","",HYPERLINK("#案件管理!A1","→詳細")) -> →詳細
A92: C-002 | B92: =IFERROR(VLOOKUP(A92,顧客マスタ!A:C,3,FALSE),"") -> 一建設 | C92: =COUNTIFS(案件管理!B$5:B$96,A92) -> 0 | D92: =SUMIFS(案件管理!F$5:F$96,案件管理!B$5:B$96,A92) -> 0 | E92: =IFERROR(AVERAGEIFS(案件管理!H$5:H$96,案件管理!B$5:B$96,A92,案件管理!H$5:H$96,"<>"),"") | F92: =IF(A92="","",HYPERLINK("#案件管理!A1","→詳細")) -> →詳細
A93: C-003 | B93: =IFERROR(VLOOKUP(A93,顧客マスタ!A:C,3,FALSE),"") -> フィガロ | C93: =COUNTIFS(案件管理!B$5:B$96,A93) -> 0 | D93: =SUMIFS(案件管理!F$5:F$96,案件管理!B$5:B$96,A93) -> 0 | E93: =IFERROR(AVERAGEIFS(案件管理!H$5:H$96,案件管理!B$5:B$96,A93,案件管理!H$5:H$96,"<>"),"") | F93: =IF(A93="","",HYPERLINK("#案件管理!A1","→詳細")) -> →詳細
A94: C-004 | B94: =IFERROR(VLOOKUP(A94,顧客マスタ!A:C,3,FALSE),"") -> 石澤クリーニング | C94: =COUNTIFS(案件管理!B$5:B$96,A94) -> 0 | D94: =SUMIFS(案件管理!F$5:F$96,案件管理!B$5:B$96,A94) -> 0 | E94: =IFERROR(AVERAGEIFS(案件管理!H$5:H$96,案件管理!B$5:B$96,A94,案件管理!H$5:H$96,"<>"),"") | F94: =IF(A94="","",HYPERLINK("#案件管理!A1","→詳細")) -> →詳細
A95: C-005 | B95: =IFERROR(VLOOKUP(A95,顧客マスタ!A:C,3,FALSE),"") -> 0 | C95: =COUNTIFS(案件管理!B$5:B$96,A95) -> 0 | D95: =SUMIFS(案件管理!F$5:F$96,案件管理!B$5:B$96,A95) -> 0 | E95: =IFERROR(AVERAGEIFS(案件管理!H$5:H$96,案件管理!B$5:B$96,A95,案件管理!H$5:H$96,"<>"),"") | F95: =IF(A95="","",HYPERLINK("#案件管理!A1","→詳細")) -> →詳細
A96: C-006 | B96: =IFERROR(VLOOKUP(A96,顧客マスタ!A:C,3,FALSE),"") -> 0 | C96: =COUNTIFS(案件管理!B$5:B$96,A96) -> 0 | D96: =SUMIFS(案件管理!F$5:F$96,案件管理!B$5:B$96,A96) -> 0 | E96: =IFERROR(AVERAGEIFS(案件管理!H$5:H$96,案件管理!B$5:B$96,A96,案件管理!H$5:H$96,"<>"),"") | F96: =IF(A96="","",HYPERLINK("#案件管理!A1","→詳細")) -> →詳細
A97: C-007 | B97: =IFERROR(VLOOKUP(A97,顧客マスタ!A:C,3,FALSE),"") -> 0 | C97: =COUNTIFS(案件管理!B$5:B$96,A97) -> 0 | D97: =SUMIFS(案件管理!F$5:F$96,案件管理!B$5:B$96,A97) -> 0 | E97: =IFERROR(AVERAGEIFS(案件管理!H$5:H$96,案件管理!B$5:B$96,A97,案件管理!H$5:H$96,"<>"),"") | F97: =IF(A97="","",HYPERLINK("#案件管理!A1","→詳細")) -> →詳細
A98: C-008 | B98: =IFERROR(VLOOKUP(A98,顧客マスタ!A:C,3,FALSE),"") -> 0 | C98: =COUNTIFS(案件管理!B$5:B$96,A98) -> 0 | D98: =SUMIFS(案件管理!F$5:F$96,案件管理!B$5:B$96,A98) -> 0 | E98: =IFERROR(AVERAGEIFS(案件管理!H$5:H$96,案件管理!B$5:B$96,A98,案件管理!H$5:H$96,"<>"),"") | F98: =IF(A98="","",HYPERLINK("#案件管理!A1","→詳細")) -> →詳細
A99: C-009 | B99: =IFERROR(VLOOKUP(A99,顧客マスタ!A:C,3,FALSE),"") -> 0 | C99: =COUNTIFS(案件管理!B$5:B$96,A99) -> 0 | D99: =SUMIFS(案件管理!F$5:F$96,案件管理!B$5:B$96,A99) -> 0 | E99: =IFERROR(AVERAGEIFS(案件管理!H$5:H$96,案件管理!B$5:B$96,A99,案件管理!H$5:H$96,"<>"),"") | F99: =IF(A99="","",HYPERLINK("#案件管理!A1","→詳細")) -> →詳細
A100: C-010 | B100: =IFERROR(VLOOKUP(A100,顧客マスタ!A:C,3,FALSE),"") -> 0 | C100: =COUNTIFS(案件管理!B$5:B$96,A100) -> 0 | D100: =SUMIFS(案件管理!F$5:F$96,案件管理!B$5:B$96,A100) -> 0 | E100: =IFERROR(AVERAGEIFS(案件管理!H$5:H$96,案件管理!B$5:B$96,A100,案件管理!H$5:H$96,"<>"),"") | F100: =IF(A100="","",HYPERLINK("#案件管理!A1","→詳細")) -> →詳細
A102: ■ 月別売上推移（2025/6～2026/5）
B103: 2025/6 | C103: 2025/7 | D103: 2025/8 | E103: 2025/9 | F103: 2025/10 | G103: 2025/11 | H103: 2025/12 | I103: 2026/1 | J103: 2026/2 | K103: 2026/3 | L103: 2026/4 | M103: 2026/5 | N103: 合計
A104: 受注件数 | B104: =COUNTIFS(案件管理!N$5:N$96,">="&DATE(2025,6,1),案件管理!N$5:N$96,"<"&DATE(2025,7,1)) -> 0 | C104: =COUNTIFS(案件管理!N$5:N$96,">="&DATE(2025,7,1),案件管理!N$5:N$96,"<"&DATE(2025,8,1)) -> 0 | D104: =COUNTIFS(案件管理!N$5:N$96,">="&DATE(2025,8,1),案件管理!N$5:N$96,"<"&DATE(2025,9,1)) -> 0 | E104: =COUNTIFS(案件管理!N$5:N$96,">="&DATE(2025,9,1),案件管理!N$5:N$96,"<"&DATE(2025,10,1)) -> 0 | F104: =COUNTIFS(案件管理!N$5:N$96,">="&DATE(2025,10,1),案件管理!N$5:N$96,"<"&DATE(2025,11,1)) -> 0 | G104: =COUNTIFS(案件管理!N$5:N$96,">="&DATE(2025,11,1),案件管理!N$5:N$96,"<"&DATE(2025,12,1)) -> 0 | H104: =COUNTIFS(案件管理!N$5:N$96,">="&DATE(2025,12,1),案件管理!N$5:N$96,"<"&DATE(2026,1,1)) -> 0 | I104: =COUNTIFS(案件管理!N$5:N$96,">="&DATE(2026,1,1),案件管理!N$5:N$96,"<"&DATE(2026,2,1)) -> 0 | J104: =COUNTIFS(案件管理!N$5:N$96,">="&DATE(2026,2,1),案件管理!N$5:N$96,"<"&DATE(2026,3,1)) -> 0 | K104: =COUNTIFS(案件管理!N$5:N$96,">="&DATE(2026,3,1),案件管理!N$5:N$96,"<"&DATE(2026,4,1)) -> 0 | L104: =COUNTIFS(案件管理!N$5:N$96,">="&DATE(2026,4,1),案件管理!N$5:N$96,"<"&DATE(2026,5,1)) -> 0 | M104: =COUNTIFS(案件管理!N$5:N$96,">="&DATE(2026,5,1),案件管理!N$5:N$96,"<"&DATE(2026,6,1)) -> 0 | N104: =SUM(B104:M104) -> 0
A105: 受注金額 | B105: =SUMIFS(案件管理!F$5:F$96,案件管理!N$5:N$96,">="&DATE(2025,6,1),案件管理!N$5:N$96,"<"&DATE(2025,7,1)) -> 0 | C105: =SUMIFS(案件管理!F$5:F$96,案件管理!N$5:N$96,">="&DATE(2025,7,1),案件管理!N$5:N$96,"<"&DATE(2025,8,1)) -> 0 | D105: =SUMIFS(案件管理!F$5:F$96,案件管理!N$5:N$96,">="&DATE(2025,8,1),案件管理!N$5:N$96,"<"&DATE(2025,9,1)) -> 0 | E105: =SUMIFS(案件管理!F$5:F$96,案件管理!N$5:N$96,">="&DATE(2025,9,1),案件管理!N$5:N$96,"<"&DATE(2025,10,1)) -> 0 | F105: =SUMIFS(案件管理!F$5:F$96,案件管理!N$5:N$96,">="&DATE(2025,10,1),案件管理!N$5:N$96,"<"&DATE(2025,11,1)) -> 0 | G105: =SUMIFS(案件管理!F$5:F$96,案件管理!N$5:N$96,">="&DATE(2025,11,1),案件管理!N$5:N$96,"<"&DATE(2025,12,1)) -> 0 | H105: =SUMIFS(案件管理!F$5:F$96,案件管理!N$5:N$96,">="&DATE(2025,12,1),案件管理!N$5:N$96,"<"&DATE(2026,1,1)) -> 0 | I105: =SUMIFS(案件管理!F$5:F$96,案件管理!N$5:N$96,">="&DATE(2026,1,1),案件管理!N$5:N$96,"<"&DATE(2026,2,1)) -> 0 | J105: =SUMIFS(案件管理!F$5:F$96,案件管理!N$5:N$96,">="&DATE(2026,2,1),案件管理!N$5:N$96,"<"&DATE(2026,3,1)) -> 0 | K105: =SUMIFS(案件管理!F$5:F$96,案件管理!N$5:N$96,">="&DATE(2026,3,1),案件管理!N$5:N$96,"<"&DATE(2026,4,1)) -> 0 | L105: =SUMIFS(案件管理!F$5:F$96,案件管理!N$5:N$96,">="&DATE(2026,4,1),案件管理!N$5:N$96,"<"&DATE(2026,5,1)) -> 0 | M105: =SUMIFS(案件管理!F$5:F$96,案件管理!N$5:N$96,">="&DATE(2026,5,1),案件管理!N$5:N$96,"<"&DATE(2026,6,1)) -> 0 | N105: =SUM(B105:M105) -> 0

Sheet 案件管理
A1: 案件管理 / プロジェクトパイプライン
A2: 株式会社LinK - CRM案件管理システム
A3: ※ 全案件の進捗・ステータスを一元管理。経過日数の自動計算で滞留案件を即座に把握できます。
A4: 案件ID | B4: 顧客ID | C4: 顧客名 | D4: 案件名 | E4: 工事内容 | F4: 見積金額 | G4: 実行予算 | H4: 粗利率 | I4: ステータス | J4: ステータス変更日 | K4: 経過日数 | L4: 滞留アラート | M4: 担当者 | N4: 受注日 | O4: 着工予定日 | P4: 完工日 | Q4: 請求予定額 | R4: 失注理由 | S4: 作成日 | T4: 備考 | U4: 完工予定日 | V4: 工期余日 | W4: 工期アラート | X4: 請求書ステータス | Y4: 請求日 | Z4: 請求金額 | AA4: 入金ステータス | AB4: 入金日 | AC4: 入金額 | AD4: 受注区分 | AE4: 施工住所 | AF4: 物件名
A5: P-001 | B5: C-001 | C5: =IFERROR(VLOOKUP(B5,顧客マスタ!A:C,3,FALSE),"") -> 矢島不動産管理株式会社 | D5: 吉野様邸 リフォーム工事 | E5: 内装・電気・給排水 | F5: 3500000 | G5: 2800000 | H5: =IF(AND(F5<>"",G5<>""),(F5-G5)/F5,"") -> 0.2 | I5: ⑤受注 | J5: 45672 | K5: =IF(J5<>"",TODAY()-J5,"") -> 398 | L5: =IF(AND(K5<>"",K5>30,NOT(OR(I5="⑤受注",I5="⑦完工",I5="⑥失注"))),"⚠滞留","") | M5: 吉野博 | N5: 45677 | O5: 45689 | P5: 45731 | Q5: 3500000 | S5: 45662 | T5: 受注済み・工事完了 | U5: 45731 | V5: =IF(AND(U5<>"",OR(I5="⑤受注",I5="③見積作成中",I5="④見積提出済")),U5-TODAY(),"") -> -339 | W5: =IF(V5="","",IF(V5<0,"⚠工期超過",IF(V5<=7,"⚠残り"&V5&"日",""))) -> ⚠工期超過 | X5: =IF(I5="","",IF(COUNTIFS(請求管理!B:B,A5)>0,"✅発行済","❌未発行")) -> ✅発行済 | Y5: =IF(I5="","",IFERROR(IF(COUNTIFS(請求管理!B:B,A5)=0,"",_xlfn.MAXIFS(請求管理!F:F,請求管理!B:B,A5)),"")) -> 45735 | Z5: =IF(I5="","",IFERROR(IF(COUNTIFS(請求管理!B:B,A5)=0,"",SUMIFS(請求管理!G:G,請求管理!B:B,A5)),"")) -> 3500000 | AA5: =IF(I5="","",IF(COUNTIFS(請求管理!B:B,A5)=0,"",IF(SUMIFS(請求管理!J:J,請求管理!B:B,A5)<=0,"✅入金済","❌未入金"))) -> ✅入金済 | AB5: =IF(I5="","",IFERROR(IF(COUNTIFS(請求管理!B:B,A5)=0,"",_xlfn.MAXIFS(請求管理!H:H,請求管理!B:B,A5)),"")) -> 45760 | AC5: =IF(I5="","",IFERROR(IF(COUNTIFS(請求管理!B:B,A5)=0,"",SUMIFS(請求管理!I:I,請求管理!B:B,A5)),"")) -> 3500000 | AD5: =IF(OR(I5="⑤受注",I5="⑦完工"),"🟢受注",IF(I5="⑥失注","🔴失注",IF(I5="","","🟡商談中"))) -> 🟢受注
A6: P-002 | B6: C-001 | C6: =IFERROR(VLOOKUP(B6,顧客マスタ!A:C,3,FALSE),"") -> 矢島不動産管理株式会社 | D6: 吉野様邸 外壁塗装工事 | E6: 外壁・屋根塗装 | F6: 1800000 | H6: =IF(AND(F6<>"",G6<>""),(F6-G6)/F6,"") | I6: ④見積提出済 | J6: 45685 | K6: =IF(J6<>"",TODAY()-J6,"") -> 385 | L6: =IF(AND(K6<>"",K6>30,NOT(OR(I6="⑤受注",I6="⑦完工",I6="⑥失注"))),"⚠滞留","") -> ⚠滞留 | M6: 吉野博 | S6: 45677 | T6: 見積提出済・返事待ち | V6: =IF(AND(U6<>"",OR(I6="⑤受注",I6="③見積作成中",I6="④見積提出済")),U6-TODAY(),"") | W6: =IF(V6="","",IF(V6<0,"⚠工期超過",IF(V6<=7,"⚠残り"&V6&"日",""))) | X6: =IF(I6="","",IF(COUNTIFS(請求管理!B:B,A6)>0,"✅発行済","❌未発行")) -> ❌未発行 | Y6: =IF(I6="","",IFERROR(IF(COUNTIFS(請求管理!B:B,A6)=0,"",_xlfn.MAXIFS(請求管理!F:F,請求管理!B:B,A6)),"")) | Z6: =IF(I6="","",IFERROR(IF(COUNTIFS(請求管理!B:B,A6)=0,"",SUMIFS(請求管理!G:G,請求管理!B:B,A6)),"")) | AA6: =IF(I6="","",IF(COUNTIFS(請求管理!B:B,A6)=0,"",IF(SUMIFS(請求管理!J:J,請求管理!B:B,A6)<=0,"✅入金済","❌未入金"))) | AB6: =IF(I6="","",IFERROR(IF(COUNTIFS(請求管理!B:B,A6)=0,"",_xlfn.MAXIFS(請求管理!H:H,請求管理!B:B,A6)),"")) | AC6: =IF(I6="","",IFERROR(IF(COUNTIFS(請求管理!B:B,A6)=0,"",SUMIFS(請求管理!I:I,請求管理!B:B,A6)),"")) | AD6: =IF(OR(I6="⑤受注",I6="⑦完工"),"🟢受注",IF(I6="⑥失注","🔴失注",IF(I6="","","🟡商談中"))) -> 🟡商談中
A7: P-003 | B7: C-001 | C7: =IFERROR(VLOOKUP(B7,顧客マスタ!A:C,3,FALSE),"") -> 矢島不動産管理株式会社 | D7: 吉野様邸 キッチンリフォーム | E7: キッチン設備・内装 | F7: ='P-003_吉野様邸キッチン'!K50 -> 1254440 | G7: ='P-003_吉野様邸キッチン'!G50 -> 829180 | H7: =IF(AND(F7<>"",G7<>""),(F7-G7)/F7,"") -> 0.33900386 | I7: ⑦完工 | J7: =TODAY() -> 46070 | K7: =IF(J7<>"",TODAY()-J7,"") -> 0 | L7: =IF(AND(K7<>"",K7>30,NOT(OR(I7="⑤受注",I7="⑦完工",I7="⑥失注"))),"⚠滞留","") | M7: 吉野博 | P7: =TODAY() -> 46070 | Q7: =F7 -> 1254440 | S7: =TODAY() -> 46070 | T7: ⑦完工 - 工事項目DB蓄積済み | V7: =IF(AND(U7<>"",OR(I7="⑤受注",I7="③見積作成中",I7="④見積提出済")),U7-TODAY(),"") | W7: =IF(V7="","",IF(V7<0,"⚠工期超過",IF(V7<=7,"⚠残り"&V7&"日",""))) | X7: =IF(I7="","",IF(COUNTIFS(請求管理!B:B,A7)>0,"✅発行済","❌未発行")) -> ✅発行済 | Y7: =IF(I7="","",IFERROR(IF(COUNTIFS(請求管理!B:B,A7)=0,"",_xlfn.MAXIFS(請求管理!F:F,請求管理!B:B,A7)),"")) -> 46064 | Z7: =IF(I7="","",IFERROR(IF(COUNTIFS(請求管理!B:B,A7)=0,"",SUMIFS(請求管理!G:G,請求管理!B:B,A7)),"")) -> 1254440 | AA7: =IF(I7="","",IF(COUNTIFS(請求管理!B:B,A7)=0,"",IF(SUMIFS(請求管理!J:J,請求管理!B:B,A7)<=0,"✅入金済","❌未入金"))) -> ❌未入金 | AB7: =IF(I7="","",IFERROR(IF(COUNTIFS(請求管理!B:B,A7)=0,"",_xlfn.MAXIFS(請求管理!H:H,請求管理!B:B,A7)),"")) -> 46040 | AC7: =IF(I7="","",IFERROR(IF(COUNTIFS(請求管理!B:B,A7)=0,"",SUMIFS(請求管理!I:I,請求管理!B:B,A7)),"")) -> 627220 | AD7: =IF(OR(I7="⑤受注",I7="⑦完工"),"🟢受注",IF(I7="⑥失注","🔴失注",IF(I7="","","🟡商談中"))) -> 🟢受注
A8: P-012 | C8: =IFERROR(VLOOKUP(B8,顧客マスタ!A:C,3,FALSE),"") | H8: =IF(AND(F8<>"",G8<>""),(F8-G8)/F8,"") | K8: =IF(J8<>"",TODAY()-J8,"") | L8: =IF(AND(K8<>"",K8>30,NOT(OR(I8="⑤受注",I8="⑦完工",I8="⑥失注"))),"⚠滞留","") | V8: =IF(AND(U8<>"",OR(I8="⑤受注",I8="③見積作成中",I8="④見積提出済")),U8-TODAY(),"") | W8: =IF(V8="","",IF(V8<0,"⚠工期超過",IF(V8<=7,"⚠残り"&V8&"日",""))) | X8: =IF(I8="","",IF(COUNTIFS(請求管理!B:B,A8)>0,"✅発行済","❌未発行")) | Y8: =IF(I8="","",IFERROR(IF(COUNTIFS(請求管理!B:B,A8)=0,"",_xlfn.MAXIFS(請求管理!F:F,請求管理!B:B,A8)),"")) | Z8: =IF(I8="","",IFERROR(IF(COUNTIFS(請求管理!B:B,A8)=0,"",SUMIFS(請求管理!G:G,請求管理!B:B,A8)),"")) | AA8: =IF(I8="","",IF(COUNTIFS(請求管理!B:B,A8)=0,"",IF(SUMIFS(請求管理!J:J,請求管理!B:B,A8)<=0,"✅入金済","❌未入金"))) | AB8: =IF(I8="","",IFERROR(IF(COUNTIFS(請求管理!B:B,A8)=0,"",_xlfn.MAXIFS(請求管理!H:H,請求管理!B:B,A8)),"")) | AC8: =IF(I8="","",IFERROR(IF(COUNTIFS(請求管理!B:B,A8)=0,"",SUMIFS(請求管理!I:I,請求管理!B:B,A8)),"")) | AD8: =IF(OR(I8="⑤受注",I8="⑦完工"),"🟢受注",IF(I8="⑥失注","🔴失注",IF(I8="","","🟡商談中")))
A9: P-013 | C9: =IFERROR(VLOOKUP(B9,顧客マスタ!A:C,3,FALSE),"") | H9: =IF(AND(F9<>"",G9<>""),(F9-G9)/F9,"") | K9: =IF(J9<>"",TODAY()-J9,"") | L9: =IF(AND(K9<>"",K9>30,NOT(OR(I9="⑤受注",I9="⑦完工",I9="⑥失注"))),"⚠滞留","") | V9: =IF(AND(U9<>"",OR(I9="⑤受注",I9="③見積作成中",I9="④見積提出済")),U9-TODAY(),"") | W9: =IF(V9="","",IF(V9<0,"⚠工期超過",IF(V9<=7,"⚠残り"&V9&"日",""))) | X9: =IF(I9="","",IF(COUNTIFS(請求管理!B:B,A9)>0,"✅発行済","❌未発行")) | Y9: =IF(I9="","",IFERROR(IF(COUNTIFS(請求管理!B:B,A9)=0,"",_xlfn.MAXIFS(請求管理!F:F,請求管理!B:B,A9)),"")) | Z9: =IF(I9="","",IFERROR(IF(COUNTIFS(請求管理!B:B,A9)=0,"",SUMIFS(請求管理!G:G,請求管理!B:B,A9)),"")) | AA9: =IF(I9="","",IF(COUNTIFS(請求管理!B:B,A9)=0,"",IF(SUMIFS(請求管理!J:J,請求管理!B:B,A9)<=0,"✅入金済","❌未入金"))) | AB9: =IF(I9="","",IFERROR(IF(COUNTIFS(請求管理!B:B,A9)=0,"",_xlfn.MAXIFS(請求管理!H:H,請求管理!B:B,A9)),"")) | AC9: =IF(I9="","",IFERROR(IF(COUNTIFS(請求管理!B:B,A9)=0,"",SUMIFS(請求管理!I:I,請求管理!B:B,A9)),"")) | AD9: =IF(OR(I9="⑤受注",I9="⑦完工"),"🟢受注",IF(I9="⑥失注","🔴失注",IF(I9="","","🟡商談中")))
A10: P-014 | C10: =IFERROR(VLOOKUP(B10,顧客マスタ!A:C,3,FALSE),"") | H10: =IF(AND(F10<>"",G10<>""),(F10-G10)/F10,"") | K10: =IF(J10<>"",TODAY()-J10,"") | L10: =IF(AND(K10<>"",K10>30,NOT(OR(I10="⑤受注",I10="⑦完工",I10="⑥失注"))),"⚠滞留","") | V10: =IF(AND(U10<>"",OR(I10="⑤受注",I10="③見積作成中",I10="④見積提出済")),U10-TODAY(),"") | W10: =IF(V10="","",IF(V10<0,"⚠工期超過",IF(V10<=7,"⚠残り"&V10&"日",""))) | X10: =IF(I10="","",IF(COUNTIFS(請求管理!B:B,A10)>0,"✅発行済","❌未発行")) | Y10: =IF(I10="","",IFERROR(IF(COUNTIFS(請求管理!B:B,A10)=0,"",_xlfn.MAXIFS(請求管理!F:F,請求管理!B:B,A10)),"")) | Z10: =IF(I10="","",IFERROR(IF(COUNTIFS(請求管理!B:B,A10)=0,"",SUMIFS(請求管理!G:G,請求管理!B:B,A10)),"")) | AA10: =IF(I10="","",IF(COUNTIFS(請求管理!B:B,A10)=0,"",IF(SUMIFS(請求管理!J:J,請求管理!B:B,A10)<=0,"✅入金済","❌未入金"))) | AB10: =IF(I10="","",IFERROR(IF(COUNTIFS(請求管理!B:B,A10)=0,"",_xlfn.MAXIFS(請求管理!H:H,請求管理!B:B,A10)),"")) | AC10: =IF(I10="","",IFERROR(IF(COUNTIFS(請求管理!B:B,A10)=0,"",SUMIFS(請求管理!I:I,請求管理!B:B,A10)),"")) | AD10: =IF(OR(I10="⑤受注",I10="⑦完工"),"🟢受注",IF(I10="⑥失注","🔴失注",IF(I10="","","🟡商談中")))
A11: P-015 | C11: =IFERROR(VLOOKUP(B11,顧客マスタ!A:C,3,FALSE),"") | H11: =IF(AND(F11<>"",G11<>""),(F11-G11)/F11,"") | K11: =IF(J11<>"",TODAY()-J11,"") | L11: =IF(AND(K11<>"",K11>30,NOT(OR(I11="⑤受注",I11="⑦完工",I11="⑥失注"))),"⚠滞留","") | V11: =IF(AND(U11<>"",OR(I11="⑤受注",I11="③見積作成中",I11="④見積提出済")),U11-TODAY(),"") | W11: =IF(V11="","",IF(V11<0,"⚠工期超過",IF(V11<=7,"⚠残り"&V11&"日",""))) | X11: =IF(I11="","",IF(COUNTIFS(請求管理!B:B,A11)>0,"✅発行済","❌未発行")) | Y11: =IF(I11="","",IFERROR(IF(COUNTIFS(請求管理!B:B,A11)=0,"",_xlfn.MAXIFS(請求管理!F:F,請求管理!B:B,A11)),"")) | Z11: =IF(I11="","",IFERROR(IF(COUNTIFS(請求管理!B:B,A11)=0,"",SUMIFS(請求管理!G:G,請求管理!B:B,A11)),"")) | AA11: =IF(I11="","",IF(COUNTIFS(請求管理!B:B,A11)=0,"",IF(SUMIFS(請求管理!J:J,請求管理!B:B,A11)<=0,"✅入金済","❌未入金"))) | AB11: =IF(I11="","",IFERROR(IF(COUNTIFS(請求管理!B:B,A11)=0,"",_xlfn.MAXIFS(請求管理!H:H,請求管理!B:B,A11)),"")) | AC11: =IF(I11="","",IFERROR(IF(COUNTIFS(請求管理!B:B,A11)=0,"",SUMIFS(請求管理!I:I,請求管理!B:B,A11)),"")) | AD11: =IF(OR(I11="⑤受注",I11="⑦完工"),"🟢受注",IF(I11="⑥失注","🔴失注",IF(I11="","","🟡商談中")))
A12: P-016 | C12: =IFERROR(VLOOKUP(B12,顧客マスタ!A:C,3,FALSE),"") | H12: =IF(AND(F12<>"",G12<>""),(F12-G12)/F12,"") | K12: =IF(J12<>"",TODAY()-J12,"") | L12: =IF(AND(K12<>"",K12>30,NOT(OR(I12="⑤受注",I12="⑦完工",I12="⑥失注"))),"⚠滞留","") | V12: =IF(AND(U12<>"",OR(I12="⑤受注",I12="③見積作成中",I12="④見積提出済")),U12-TODAY(),"") | W12: =IF(V12="","",IF(V12<0,"⚠工期超過",IF(V12<=7,"⚠残り"&V12&"日",""))) | X12: =IF(I12="","",IF(COUNTIFS(請求管理!B:B,A12)>0,"✅発行済","❌未発行")) | Y12: =IF(I12="","",IFERROR(IF(COUNTIFS(請求管理!B:B,A12)=0,"",_xlfn.MAXIFS(請求管理!F:F,請求管理!B:B,A12)),"")) | Z12: =IF(I12="","",IFERROR(IF(COUNTIFS(請求管理!B:B,A12)=0,"",SUMIFS(請求管理!G:G,請求管理!B:B,A12)),"")) | AA12: =IF(I12="","",IF(COUNTIFS(請求管理!B:B,A12)=0,"",IF(SUMIFS(請求管理!J:J,請求管理!B:B,A12)<=0,"✅入金済","❌未入金"))) | AB12: =IF(I12="","",IFERROR(IF(COUNTIFS(請求管理!B:B,A12)=0,"",_xlfn.MAXIFS(請求管理!H:H,請求管理!B:B,A12)),"")) | AC12: =IF(I12="","",IFERROR(IF(COUNTIFS(請求管理!B:B,A12)=0,"",SUMIFS(請求管理!I:I,請求管理!B:B,A12)),"")) | AD12: =IF(OR(I12="⑤受注",I12="⑦完工"),"🟢受注",IF(I12="⑥失注","🔴失注",IF(I12="","","🟡商談中")))
A13: P-017 | C13: =IFERROR(VLOOKUP(B13,顧客マスタ!A:C,3,FALSE),"") | H13: =IF(AND(F13<>"",G13<>""),(F13-G13)/F13,"") | K13: =IF(J13<>"",TODAY()-J13,"") | L13: =IF(AND(K13<>"",K13>30,NOT(OR(I13="⑤受注",I13="⑦完工",I13="⑥失注"))),"⚠滞留","") | V13: =IF(AND(U13<>"",OR(I13="⑤受注",I13="③見積作成中",I13="④見積提出済")),U13-TODAY(),"") | W13: =IF(V13="","",IF(V13<0,"⚠工期超過",IF(V13<=7,"⚠残り"&V13&"日",""))) | X13: =IF(I13="","",IF(COUNTIFS(請求管理!B:B,A13)>0,"✅発行済","❌未発行")) | Y13: =IF(I13="","",IFERROR(IF(COUNTIFS(請求管理!B:B,A13)=0,"",_xlfn.MAXIFS(請求管理!F:F,請求管理!B:B,A13)),"")) | Z13: =IF(I13="","",IFERROR(IF(COUNTIFS(請求管理!B:B,A13)=0,"",SUMIFS(請求管理!G:G,請求管理!B:B,A13)),"")) | AA13: =IF(I13="","",IF(COUNTIFS(請求管理!B:B,A13)=0,"",IF(SUMIFS(請求管理!J:J,請求管理!B:B,A13)<=0,"✅入金済","❌未入金"))) | AB13: =IF(I13="","",IFERROR(IF(COUNTIFS(請求管理!B:B,A13)=0,"",_xlfn.MAXIFS(請求管理!H:H,請求管理!B:B,A13)),"")) | AC13: =IF(I13="","",IFERROR(IF(COUNTIFS(請求管理!B:B,A13)=0,"",SUMIFS(請求管理!I:I,請求管理!B:B,A13)),"")) | AD13: =IF(OR(I13="⑤受注",I13="⑦完工"),"🟢受注",IF(I13="⑥失注","🔴失注",IF(I13="","","🟡商談中")))
A14: P-018 | C14: =IFERROR(VLOOKUP(B14,顧客マスタ!A:C,3,FALSE),"") | H14: =IF(AND(F14<>"",G14<>""),(F14-G14)/F14,"") | K14: =IF(J14<>"",TODAY()-J14,"") | L14: =IF(AND(K14<>"",K14>30,NOT(OR(I14="⑤受注",I14="⑦完工",I14="⑥失注"))),"⚠滞留","") | V14: =IF(AND(U14<>"",OR(I14="⑤受注",I14="③見積作成中",I14="④見積提出済")),U14-TODAY(),"") | W14: =IF(V14="","",IF(V14<0,"⚠工期超過",IF(V14<=7,"⚠残り"&V14&"日",""))) | X14: =IF(I14="","",IF(COUNTIFS(請求管理!B:B,A14)>0,"✅発行済","❌未発行")) | Y14: =IF(I14="","",IFERROR(IF(COUNTIFS(請求管理!B:B,A14)=0,"",_xlfn.MAXIFS(請求管理!F:F,請求管理!B:B,A14)),"")) | Z14: =IF(I14="","",IFERROR(IF(COUNTIFS(請求管理!B:B,A14)=0,"",SUMIFS(請求管理!G:G,請求管理!B:B,A14)),"")) | AA14: =IF(I14="","",IF(COUNTIFS(請求管理!B:B,A14)=0,"",IF(SUMIFS(請求管理!J:J,請求管理!B:B,A14)<=0,"✅入金済","❌未入金"))) | AB14: =IF(I14="","",IFERROR(IF(COUNTIFS(請求管理!B:B,A14)=0,"",_xlfn.MAXIFS(請求管理!H:H,請求管理!B:B,A14)),"")) | AC14: =IF(I14="","",IFERROR(IF(COUNTIFS(請求管理!B:B,A14)=0,"",SUMIFS(請求管理!I:I,請求管理!B:B,A14)),"")) | AD14: =IF(OR(I14="⑤受注",I14="⑦完工"),"🟢受注",IF(I14="⑥失注","🔴失注",IF(I14="","","🟡商談中")))
A15: P-019 | C15: =IFERROR(VLOOKUP(B15,顧客マスタ!A:C,3,FALSE),"") | H15: =IF(AND(F15<>"",G15<>""),(F15-G15)/F15,"") | K15: =IF(J15<>"",TODAY()-J15,"") | L15: =IF(AND(K15<>"",K15>30,NOT(OR(I15="⑤受注",I15="⑦完工",I15="⑥失注"))),"⚠滞留","") | V15: =IF(AND(U15<>"",OR(I15="⑤受注",I15="③見積作成中",I15="④見積提出済")),U15-TODAY(),"") | W15: =IF(V15="","",IF(V15<0,"⚠工期超過",IF(V15<=7,"⚠残り"&V15&"日",""))) | X15: =IF(I15="","",IF(COUNTIFS(請求管理!B:B,A15)>0,"✅発行済","❌未発行")) | Y15: =IF(I15="","",IFERROR(IF(COUNTIFS(請求管理!B:B,A15)=0,"",_xlfn.MAXIFS(請求管理!F:F,請求管理!B:B,A15)),"")) | Z15: =IF(I15="","",IFERROR(IF(COUNTIFS(請求管理!B:B,A15)=0,"",SUMIFS(請求管理!G:G,請求管理!B:B,A15)),"")) | AA15: =IF(I15="","",IF(COUNTIFS(請求管理!B:B,A15)=0,"",IF(SUMIFS(請求管理!J:J,請求管理!B:B,A15)<=0,"✅入金済","❌未入金"))) | AB15: =IF(I15="","",IFERROR(IF(COUNTIFS(請求管理!B:B,A15)=0,"",_xlfn.MAXIFS(請求管理!H:H,請求管理!B:B,A15)),"")) | AC15: =IF(I15="","",IFERROR(IF(COUNTIFS(請求管理!B:B,A15)=0,"",SUMIFS(請求管理!I:I,請求管理!B:B,A15)),"")) | AD15: =IF(OR(I15="⑤受注",I15="⑦完工"),"🟢受注",IF(I15="⑥失注","🔴失注",IF(I15="","","🟡商談中")))
A16: P-020 | C16: =IFERROR(VLOOKUP(B16,顧客マスタ!A:C,3,FALSE),"") | H16: =IF(AND(F16<>"",G16<>""),(F16-G16)/F16,"") | K16: =IF(J16<>"",TODAY()-J16,"") | L16: =IF(AND(K16<>"",K16>30,NOT(OR(I16="⑤受注",I16="⑦完工",I16="⑥失注"))),"⚠滞留","") | V16: =IF(AND(U16<>"",OR(I16="⑤受注",I16="③見積作成中",I16="④見積提出済")),U16-TODAY(),"") | W16: =IF(V16="","",IF(V16<0,"⚠工期超過",IF(V16<=7,"⚠残り"&V16&"日",""))) | X16: =IF(I16="","",IF(COUNTIFS(請求管理!B:B,A16)>0,"✅発行済","❌未発行")) | Y16: =IF(I16="","",IFERROR(IF(COUNTIFS(請求管理!B:B,A16)=0,"",_xlfn.MAXIFS(請求管理!F:F,請求管理!B:B,A16)),"")) | Z16: =IF(I16="","",IFERROR(IF(COUNTIFS(請求管理!B:B,A16)=0,"",SUMIFS(請求管理!G:G,請求管理!B:B,A16)),"")) | AA16: =IF(I16="","",IF(COUNTIFS(請求管理!B:B,A16)=0,"",IF(SUMIFS(請求管理!J:J,請求管理!B:B,A16)<=0,"✅入金済","❌未入金"))) | AB16: =IF(I16="","",IFERROR(IF(COUNTIFS(請求管理!B:B,A16)=0,"",_xlfn.MAXIFS(請求管理!H:H,請求管理!B:B,A16)),"")) | AC16: =IF(I16="","",IFERROR(IF(COUNTIFS(請求管理!B:B,A16)=0,"",SUMIFS(請求管理!I:I,請求管理!B:B,A16)),"")) | AD16: =IF(OR(I16="⑤受注",I16="⑦完工"),"🟢受注",IF(I16="⑥失注","🔴失注",IF(I16="","","🟡商談中")))
C17: =IFERROR(VLOOKUP(B17,顧客マスタ!A:C,3,FALSE),"") | H17: =IF(AND(F17<>"",G17<>""),(F17-G17)/F17,"") | K17: =IF(J17<>"",TODAY()-J17,"") | L17: =IF(AND(K17<>"",K17>30,NOT(OR(I17="⑤受注",I17="⑦完工",I17="⑥失注"))),"⚠滞留","") | V17: =IF(AND(U17<>"",OR(I17="⑤受注",I17="③見積作成中",I17="④見積提出済")),U17-TODAY(),"") | W17: =IF(V17="","",IF(V17<0,"⚠工期超過",IF(V17<=7,"⚠残り"&V17&"日",""))) | X17: =IF(I17="","",IF(COUNTIFS(請求管理!B:B,A17)>0,"✅発行済","❌未発行")) | Y17: =IF(I17="","",IFERROR(IF(COUNTIFS(請求管理!B:B,A17)=0,"",_xlfn.MAXIFS(請求管理!F:F,請求管理!B:B,A17)),"")) | Z17: =IF(I17="","",IFERROR(IF(COUNTIFS(請求管理!B:B,A17)=0,"",SUMIFS(請求管理!G:G,請求管理!B:B,A17)),"")) | AA17: =IF(I17="","",IF(COUNTIFS(請求管理!B:B,A17)=0,"",IF(SUMIFS(請求管理!J:J,請求管理!B:B,A17)<=0,"✅入金済","❌未入金"))) | AB17: =IF(I17="","",IFERROR(IF(COUNTIFS(請求管理!B:B,A17)=0,"",_xlfn.MAXIFS(請求管理!H:H,請求管理!B:B,A17)),"")) | AC17: =IF(I17="","",IFERROR(IF(COUNTIFS(請求管理!B:B,A17)=0,"",SUMIFS(請求管理!I:I,請求管理!B:B,A17)),"")) | AD17: =IF(OR(I17="⑤受注",I17="⑦完工"),"🟢受注",IF(I17="⑥失注","🔴失注",IF(I17="","","🟡商談中")))
C18: =IFERROR(VLOOKUP(B18,顧客マスタ!A:C,3,FALSE),"") | H18: =IF(AND(F18<>"",G18<>""),(F18-G18)/F18,"") | K18: =IF(J18<>"",TODAY()-J18,"") | L18: =IF(AND(K18<>"",K18>30,NOT(OR(I18="⑤受注",I18="⑦完工",I18="⑥失注"))),"⚠滞留","") | V18: =IF(AND(U18<>"",OR(I18="⑤受注",I18="③見積作成中",I18="④見積提出済")),U18-TODAY(),"") | W18: =IF(V18="","",IF(V18<0,"⚠工期超過",IF(V18<=7,"⚠残り"&V18&"日",""))) | X18: =IF(I18="","",IF(COUNTIFS(請求管理!B:B,A18)>0,"✅発行済","❌未発行")) | Y18: =IF(I18="","",IFERROR(IF(COUNTIFS(請求管理!B:B,A18)=0,"",_xlfn.MAXIFS(請求管理!F:F,請求管理!B:B,A18)),"")) | Z18: =IF(I18="","",IFERROR(IF(COUNTIFS(請求管理!B:B,A18)=0,"",SUMIFS(請求管理!G:G,請求管理!B:B,A18)),"")) | AA18: =IF(I18="","",IF(COUNTIFS(請求管理!B:B,A18)=0,"",IF(SUMIFS(請求管理!J:J,請求管理!B:B,A18)<=0,"✅入金済","❌未入金"))) | AB18: =IF(I18="","",IFERROR(IF(COUNTIFS(請求管理!B:B,A18)=0,"",_xlfn.MAXIFS(請求管理!H:H,請求管理!B:B,A18)),"")) | AC18: =IF(I18="","",IFERROR(IF(COUNTIFS(請求管理!B:B,A18)=0,"",SUMIFS(請求管理!I:I,請求管理!B:B,A18)),"")) | AD18: =IF(OR(I18="⑤受注",I18="⑦完工"),"🟢受注",IF(I18="⑥失注","🔴失注",IF(I18="","","🟡商談中")))
C19: =IFERROR(VLOOKUP(B19,顧客マスタ!A:C,3,FALSE),"") | H19: =IF(AND(F19<>"",G19<>""),(F19-G19)/F19,"") | K19: =IF(J19<>"",TODAY()-J19,"") | L19: =IF(AND(K19<>"",K19>30,NOT(OR(I19="⑤受注",I19="⑦完工",I19="⑥失注"))),"⚠滞留","") | V19: =IF(AND(U19<>"",OR(I19="⑤受注",I19="③見積作成中",I19="④見積提出済")),U19-TODAY(),"") | W19: =IF(V19="","",IF(V19<0,"⚠工期超過",IF(V19<=7,"⚠残り"&V19&"日",""))) | X19: =IF(I19="","",IF(COUNTIFS(請求管理!B:B,A19)>0,"✅発行済","❌未発行")) | Y19: =IF(I19="","",IFERROR(IF(COUNTIFS(請求管理!B:B,A19)=0,"",_xlfn.MAXIFS(請求管理!F:F,請求管理!B:B,A19)),"")) | Z19: =IF(I19="","",IFERROR(IF(COUNTIFS(請求管理!B:B,A19)=0,"",SUMIFS(請求管理!G:G,請求管理!B:B,A19)),"")) | AA19: =IF(I19="","",IF(COUNTIFS(請求管理!B:B,A19)=0,"",IF(SUMIFS(請求管理!J:J,請求管理!B:B,A19)<=0,"✅入金済","❌未入金"))) | AB19: =IF(I19="","",IFERROR(IF(COUNTIFS(請求管理!B:B,A19)=0,"",_xlfn.MAXIFS(請求管理!H:H,請求管理!B:B,A19)),"")) | AC19: =IF(I19="","",IFERROR(IF(COUNTIFS(請求管理!B:B,A19)=0,"",SUMIFS(請求管理!I:I,請求管理!B:B,A19)),"")) | AD19: =IF(OR(I19="⑤受注",I19="⑦完工"),"🟢受注",IF(I19="⑥失注","🔴失注",IF(I19="","","🟡商談中")))
C20: =IFERROR(VLOOKUP(B20,顧客マスタ!A:C,3,FALSE),"") | H20: =IF(AND(F20<>"",G20<>""),(F20-G20)/F20,"") | K20: =IF(J20<>"",TODAY()-J20,"") | L20: =IF(AND(K20<>"",K20>30,NOT(OR(I20="⑤受注",I20="⑦完工",I20="⑥失注"))),"⚠滞留","") | V20: =IF(AND(U20<>"",OR(I20="⑤受注",I20="③見積作成中",I20="④見積提出済")),U20-TODAY(),"") | W20: =IF(V20="","",IF(V20<0,"⚠工期超過",IF(V20<=7,"⚠残り"&V20&"日",""))) | X20: =IF(I20="","",IF(COUNTIFS(請求管理!B:B,A20)>0,"✅発行済","❌未発行")) | Y20: =IF(I20="","",IFERROR(IF(COUNTIFS(請求管理!B:B,A20)=0,"",_xlfn.MAXIFS(請求管理!F:F,請求管理!B:B,A20)),"")) | Z20: =IF(I20="","",IFERROR(IF(COUNTIFS(請求管理!B:B,A20)=0,"",SUMIFS(請求管理!G:G,請求管理!B:B,A20)),"")) | AA20: =IF(I20="","",IF(COUNTIFS(請求管理!B:B,A20)=0,"",IF(SUMIFS(請求管理!J:J,請求管理!B:B,A20)<=0,"✅入金済","❌未入金"))) | AB20: =IF(I20="","",IFERROR(IF(COUNTIFS(請求管理!B:B,A20)=0,"",_xlfn.MAXIFS(請求管理!H:H,請求管理!B:B,A20)),"")) | AC20: =IF(I20="","",IFERROR(IF(COUNTIFS(請求管理!B:B,A20)=0,"",SUMIFS(請求管理!I:I,請求管理!B:B,A20)),"")) | AD20: =IF(OR(I20="⑤受注",I20="⑦完工"),"🟢受注",IF(I20="⑥失注","🔴失注",IF(I20="","","🟡商談中")))
C21: =IFERROR(VLOOKUP(B21,顧客マスタ!A:C,3,FALSE),"") | H21: =IF(AND(F21<>"",G21<>""),(F21-G21)/F21,"") | K21: =IF(J21<>"",TODAY()-J21,"") | L21: =IF(AND(K21<>"",K21>30,NOT(OR(I21="⑤受注",I21="⑦完工",I21="⑥失注"))),"⚠滞留","") | V21: =IF(AND(U21<>"",OR(I21="⑤受注",I21="③見積作成中",I21="④見積提出済")),U21-TODAY(),"") | W21: =IF(V21="","",IF(V21<0,"⚠工期超過",IF(V21<=7,"⚠残り"&V21&"日",""))) | X21: =IF(I21="","",IF(COUNTIFS(請求管理!B:B,A21)>0,"✅発行済","❌未発行")) | Y21: =IF(I21="","",IFERROR(IF(COUNTIFS(請求管理!B:B,A21)=0,"",_xlfn.MAXIFS(請求管理!F:F,請求管理!B:B,A21)),"")) | Z21: =IF(I21="","",IFERROR(IF(COUNTIFS(請求管理!B:B,A21)=0,"",SUMIFS(請求管理!G:G,請求管理!B:B,A21)),"")) | AA21: =IF(I21="","",IF(COUNTIFS(請求管理!B:B,A21)=0,"",IF(SUMIFS(請求管理!J:J,請求管理!B:B,A21)<=0,"✅入金済","❌未入金"))) | AB21: =IF(I21="","",IFERROR(IF(COUNTIFS(請求管理!B:B,A21)=0,"",_xlfn.MAXIFS(請求管理!H:H,請求管理!B:B,A21)),"")) | AC21: =IF(I21="","",IFERROR(IF(COUNTIFS(請求管理!B:B,A21)=0,"",SUMIFS(請求管理!I:I,請求管理!B:B,A21)),"")) | AD21: =IF(OR(I21="⑤受注",I21="⑦完工"),"🟢受注",IF(I21="⑥失注","🔴失注",IF(I21="","","🟡商談中")))
C22: =IFERROR(VLOOKUP(B22,顧客マスタ!A:C,3,FALSE),"") | H22: =IF(AND(F22<>"",G22<>""),(F22-G22)/F22,"") | K22: =IF(J22<>"",TODAY()-J22,"") | L22: =IF(AND(K22<>"",K22>30,NOT(OR(I22="⑤受注",I22="⑦完工",I22="⑥失注"))),"⚠滞留","") | V22: =IF(AND(U22<>"",OR(I22="⑤受注",I22="③見積作成中",I22="④見積提出済")),U22-TODAY(),"") | W22: =IF(V22="","",IF(V22<0,"⚠工期超過",IF(V22<=7,"⚠残り"&V22&"日",""))) | X22: =IF(I22="","",IF(COUNTIFS(請求管理!B:B,A22)>0,"✅発行済","❌未発行")) | Y22: =IF(I22="","",IFERROR(IF(COUNTIFS(請求管理!B:B,A22)=0,"",_xlfn.MAXIFS(請求管理!F:F,請求管理!B:B,A22)),"")) | Z22: =IF(I22="","",IFERROR(IF(COUNTIFS(請求管理!B:B,A22)=0,"",SUMIFS(請求管理!G:G,請求管理!B:B,A22)),"")) | AA22: =IF(I22="","",IF(COUNTIFS(請求管理!B:B,A22)=0,"",IF(SUMIFS(請求管理!J:J,請求管理!B:B,A22)<=0,"✅入金済","❌未入金"))) | AB22: =IF(I22="","",IFERROR(IF(COUNTIFS(請求管理!B:B,A22)=0,"",_xlfn.MAXIFS(請求管理!H:H,請求管理!B:B,A22)),"")) | AC22: =IF(I22="","",IFERROR(IF(COUNTIFS(請求管理!B:B,A22)=0,"",SUMIFS(請求管理!I:I,請求管理!B:B,A22)),"")) | AD22: =IF(OR(I22="⑤受注",I22="⑦完工"),"🟢受注",IF(I22="⑥失注","🔴失注",IF(I22="","","🟡商談中")))
C23: =IFERROR(VLOOKUP(B23,顧客マスタ!A:C,3,FALSE),"") | H23: =IF(AND(F23<>"",G23<>""),(F23-G23)/F23,"") | K23: =IF(J23<>"",TODAY()-J23,"") | L23: =IF(AND(K23<>"",K23>30,NOT(OR(I23="⑤受注",I23="⑦完工",I23="⑥失注"))),"⚠滞留","") | V23: =IF(AND(U23<>"",OR(I23="⑤受注",I23="③見積作成中",I23="④見積提出済")),U23-TODAY(),"") | W23: =IF(V23="","",IF(V23<0,"⚠工期超過",IF(V23<=7,"⚠残り"&V23&"日",""))) | X23: =IF(I23="","",IF(COUNTIFS(請求管理!B:B,A23)>0,"✅発行済","❌未発行")) | Y23: =IF(I23="","",IFERROR(IF(COUNTIFS(請求管理!B:B,A23)=0,"",_xlfn.MAXIFS(請求管理!F:F,請求管理!B:B,A23)),"")) | Z23: =IF(I23="","",IFERROR(IF(COUNTIFS(請求管理!B:B,A23)=0,"",SUMIFS(請求管理!G:G,請求管理!B:B,A23)),"")) | AA23: =IF(I23="","",IF(COUNTIFS(請求管理!B:B,A23)=0,"",IF(SUMIFS(請求管理!J:J,請求管理!B:B,A23)<=0,"✅入金済","❌未入金"))) | AB23: =IF(I23="","",IFERROR(IF(COUNTIFS(請求管理!B:B,A23)=0,"",_xlfn.MAXIFS(請求管理!H:H,請求管理!B:B,A23)),"")) | AC23: =IF(I23="","",IFERROR(IF(COUNTIFS(請求管理!B:B,A23)=0,"",SUMIFS(請求管理!I:I,請求管理!B:B,A23)),"")) | AD23: =IF(OR(I23="⑤受注",I23="⑦完工"),"🟢受注",IF(I23="⑥失注","🔴失注",IF(I23="","","🟡商談中")))
C24: =IFERROR(VLOOKUP(B24,顧客マスタ!A:C,3,FALSE),"") | H24: =IF(AND(F24<>"",G24<>""),(F24-G24)/F24,"") | K24: =IF(J24<>"",TODAY()-J24,"") | L24: =IF(AND(K24<>"",K24>30,NOT(OR(I24="⑤受注",I24="⑦完工",I24="⑥失注"))),"⚠滞留","") | V24: =IF(AND(U24<>"",OR(I24="⑤受注",I24="③見積作成中",I24="④見積提出済")),U24-TODAY(),"") | W24: =IF(V24="","",IF(V24<0,"⚠工期超過",IF(V24<=7,"⚠残り"&V24&"日",""))) | X24: =IF(I24="","",IF(COUNTIFS(請求管理!B:B,A24)>0,"✅発行済","❌未発行")) | Y24: =IF(I24="","",IFERROR(IF(COUNTIFS(請求管理!B:B,A24)=0,"",_xlfn.MAXIFS(請求管理!F:F,請求管理!B:B,A24)),"")) | Z24: =IF(I24="","",IFERROR(IF(COUNTIFS(請求管理!B:B,A24)=0,"",SUMIFS(請求管理!G:G,請求管理!B:B,A24)),"")) | AA24: =IF(I24="","",IF(COUNTIFS(請求管理!B:B,A24)=0,"",IF(SUMIFS(請求管理!J:J,請求管理!B:B,A24)<=0,"✅入金済","❌未入金"))) | AB24: =IF(I24="","",IFERROR(IF(COUNTIFS(請求管理!B:B,A24)=0,"",_xlfn.MAXIFS(請求管理!H:H,請求管理!B:B,A24)),"")) | AC24: =IF(I24="","",IFERROR(IF(COUNTIFS(請求管理!B:B,A24)=0,"",SUMIFS(請求管理!I:I,請求管理!B:B,A24)),"")) | AD24: =IF(OR(I24="⑤受注",I24="⑦完工"),"🟢受注",IF(I24="⑥失注","🔴失注",IF(I24="","","🟡商談中")))
C25: =IFERROR(VLOOKUP(B25,顧客マスタ!A:C,3,FALSE),"") | H25: =IF(AND(F25<>"",G25<>""),(F25-G25)/F25,"") | K25: =IF(J25<>"",TODAY()-J25,"") | L25: =IF(AND(K25<>"",K25>30,NOT(OR(I25="⑤受注",I25="⑦完工",I25="⑥失注"))),"⚠滞留","") | V25: =IF(AND(U25<>"",OR(I25="⑤受注",I25="③見積作成中",I25="④見積提出済")),U25-TODAY(),"") | W25: =IF(V25="","",IF(V25<0,"⚠工期超過",IF(V25<=7,"⚠残り"&V25&"日",""))) | X25: =IF(I25="","",IF(COUNTIFS(請求管理!B:B,A25)>0,"✅発行済","❌未発行")) | Y25: =IF(I25="","",IFERROR(IF(COUNTIFS(請求管理!B:B,A25)=0,"",_xlfn.MAXIFS(請求管理!F:F,請求管理!B:B,A25)),"")) | Z25: =IF(I25="","",IFERROR(IF(COUNTIFS(請求管理!B:B,A25)=0,"",SUMIFS(請求管理!G:G,請求管理!B:B,A25)),"")) | AA25: =IF(I25="","",IF(COUNTIFS(請求管理!B:B,A25)=0,"",IF(SUMIFS(請求管理!J:J,請求管理!B:B,A25)<=0,"✅入金済","❌未入金"))) | AB25: =IF(I25="","",IFERROR(IF(COUNTIFS(請求管理!B:B,A25)=0,"",_xlfn.MAXIFS(請求管理!H:H,請求管理!B:B,A25)),"")) | AC25: =IF(I25="","",IFERROR(IF(COUNTIFS(請求管理!B:B,A25)=0,"",SUMIFS(請求管理!I:I,請求管理!B:B,A25)),"")) | AD25: =IF(OR(I25="⑤受注",I25="⑦完工"),"🟢受注",IF(I25="⑥失注","🔴失注",IF(I25="","","🟡商談中")))
C26: =IFERROR(VLOOKUP(B26,顧客マスタ!A:C,3,FALSE),"") | H26: =IF(AND(F26<>"",G26<>""),(F26-G26)/F26,"") | K26: =IF(J26<>"",TODAY()-J26,"") | L26: =IF(AND(K26<>"",K26>30,NOT(OR(I26="⑤受注",I26="⑦完工",I26="⑥失注"))),"⚠滞留","") | V26: =IF(AND(U26<>"",OR(I26="⑤受注",I26="③見積作成中",I26="④見積提出済")),U26-TODAY(),"") | W26: =IF(V26="","",IF(V26<0,"⚠工期超過",IF(V26<=7,"⚠残り"&V26&"日",""))) | X26: =IF(I26="","",IF(COUNTIFS(請求管理!B:B,A26)>0,"✅発行済","❌未発行")) | Y26: =IF(I26="","",IFERROR(IF(COUNTIFS(請求管理!B:B,A26)=0,"",_xlfn.MAXIFS(請求管理!F:F,請求管理!B:B,A26)),"")) | Z26: =IF(I26="","",IFERROR(IF(COUNTIFS(請求管理!B:B,A26)=0,"",SUMIFS(請求管理!G:G,請求管理!B:B,A26)),"")) | AA26: =IF(I26="","",IF(COUNTIFS(請求管理!B:B,A26)=0,"",IF(SUMIFS(請求管理!J:J,請求管理!B:B,A26)<=0,"✅入金済","❌未入金"))) | AB26: =IF(I26="","",IFERROR(IF(COUNTIFS(請求管理!B:B,A26)=0,"",_xlfn.MAXIFS(請求管理!H:H,請求管理!B:B,A26)),"")) | AC26: =IF(I26="","",IFERROR(IF(COUNTIFS(請求管理!B:B,A26)=0,"",SUMIFS(請求管理!I:I,請求管理!B:B,A26)),"")) | AD26: =IF(OR(I26="⑤受注",I26="⑦完工"),"🟢受注",IF(I26="⑥失注","🔴失注",IF(I26="","","🟡商談中")))
C27: =IFERROR(VLOOKUP(B27,顧客マスタ!A:C,3,FALSE),"") | H27: =IF(AND(F27<>"",G27<>""),(F27-G27)/F27,"") | K27: =IF(J27<>"",TODAY()-J27,"") | L27: =IF(AND(K27<>"",K27>30,NOT(OR(I27="⑤受注",I27="⑦完工",I27="⑥失注"))),"⚠滞留","") | V27: =IF(AND(U27<>"",OR(I27="⑤受注",I27="③見積作成中",I27="④見積提出済")),U27-TODAY(),"") | W27: =IF(V27="","",IF(V27<0,"⚠工期超過",IF(V27<=7,"⚠残り"&V27&"日",""))) | X27: =IF(I27="","",IF(COUNTIFS(請求管理!B:B,A27)>0,"✅発行済","❌未発行")) | Y27: =IF(I27="","",IFERROR(IF(COUNTIFS(請求管理!B:B,A27)=0,"",_xlfn.MAXIFS(請求管理!F:F,請求管理!B:B,A27)),"")) | Z27: =IF(I27="","",IFERROR(IF(COUNTIFS(請求管理!B:B,A27)=0,"",SUMIFS(請求管理!G:G,請求管理!B:B,A27)),"")) | AA27: =IF(I27="","",IF(COUNTIFS(請求管理!B:B,A27)=0,"",IF(SUMIFS(請求管理!J:J,請求管理!B:B,A27)<=0,"✅入金済","❌未入金"))) | AB27: =IF(I27="","",IFERROR(IF(COUNTIFS(請求管理!B:B,A27)=0,"",_xlfn.MAXIFS(請求管理!H:H,請求管理!B:B,A27)),"")) | AC27: =IF(I27="","",IFERROR(IF(COUNTIFS(請求管理!B:B,A27)=0,"",SUMIFS(請求管理!I:I,請求管理!B:B,A27)),"")) | AD27: =IF(OR(I27="⑤受注",I27="⑦完工"),"🟢受注",IF(I27="⑥失注","🔴失注",IF(I27="","","🟡商談中")))
C28: =IFERROR(VLOOKUP(B28,顧客マスタ!A:C,3,FALSE),"") | H28: =IF(AND(F28<>"",G28<>""),(F28-G28)/F28,"") | K28: =IF(J28<>"",TODAY()-J28,"") | L28: =IF(AND(K28<>"",K28>30,NOT(OR(I28="⑤受注",I28="⑦完工",I28="⑥失注"))),"⚠滞留","") | V28: =IF(AND(U28<>"",OR(I28="⑤受注",I28="③見積作成中",I28="④見積提出済")),U28-TODAY(),"") | W28: =IF(V28="","",IF(V28<0,"⚠工期超過",IF(V28<=7,"⚠残り"&V28&"日",""))) | X28: =IF(I28="","",IF(COUNTIFS(請求管理!B:B,A28)>0,"✅発行済","❌未発行")) | Y28: =IF(I28="","",IFERROR(IF(COUNTIFS(請求管理!B:B,A28)=0,"",_xlfn.MAXIFS(請求管理!F:F,請求管理!B:B,A28)),"")) | Z28: =IF(I28="","",IFERROR(IF(COUNTIFS(請求管理!B:B,A28)=0,"",SUMIFS(請求管理!G:G,請求管理!B:B,A28)),"")) | AA28: =IF(I28="","",IF(COUNTIFS(請求管理!B:B,A28)=0,"",IF(SUMIFS(請求管理!J:J,請求管理!B:B,A28)<=0,"✅入金済","❌未入金"))) | AB28: =IF(I28="","",IFERROR(IF(COUNTIFS(請求管理!B:B,A28)=0,"",_xlfn.MAXIFS(請求管理!H:H,請求管理!B:B,A28)),"")) | AC28: =IF(I28="","",IFERROR(IF(COUNTIFS(請求管理!B:B,A28)=0,"",SUMIFS(請求管理!I:I,請求管理!B:B,A28)),"")) | AD28: =IF(OR(I28="⑤受注",I28="⑦完工"),"🟢受注",IF(I28="⑥失注","🔴失注",IF(I28="","","🟡商談中")))
... C96: =IFERROR(VLOOKUP(B96,顧客マスタ!A:C,3,FALSE),"") | H96: =IF(AND(F96<>"",G96<>""),(F96-G96)/F96,"") | K96: =IF(J96<>"",TODAY()-J96,"") | L96: =IF(AND(K96<>"",K96>30,NOT(OR(I96="⑤受注",I96="⑦完工",I96="⑥失注"))),"⚠滞留","") | V96: =IF(AND(U96<>"",OR(I96="⑤受注",I96="③見積作成中",I96="④見積提出済")),U96-TODAY(),"") | W96: =IF(V96="","",IF(V96<0,"⚠工期超過",IF(V96<=7,"⚠残り"&V96&"日",""))) | X96: =IF(I96="","",IF(COUNTIFS(請求管理!B:B,A96)>0,"✅発行済","❌未発行")) | Y96: =IF(I96="","",IFERROR(IF(COUNTIFS(請求管理!B:B,A96)=0,"",_xlfn.MAXIFS(請求管理!F:F,請求管理!B:B,A96)),"")) | Z96: =IF(I96="","",IFERROR(IF(COUNTIFS(請求管理!B:B,A96)=0,"",SUMIFS(請求管理!G:G,請求管理!B:B,A96)),"")) | AA96: =IF(I96="","",IF(COUNTIFS(請求管理!B:B,A96)=0,"",IF(SUMIFS(請求管理!J:J,請求管理!B:B,A96)<=0,"✅入金済","❌未入金"))) | AB96: =IF(I96="","",IFERROR(IF(COUNTIFS(請求管理!B:B,A96)=0,"",_xlfn.MAXIFS(請求管理!H:H,請求管理!B:B,A96)),"")) | AC96: =IF(I96="","",IFERROR(IF(COUNTIFS(請求管理!B:B,A96)=0,"",SUMIFS(請求管理!I:I,請求管理!B:B,A96)),"")) | AD96: =IF(OR(I96="⑤受注",I96="⑦完工"),"🟢受注",IF(I96="⑥失注","🔴失注",IF(I96="","","🟡商談中")))

Sheet Ｓ表紙
I1: ▼ 案件切替 | J1: ▼ 案件切替（J2にシート名を入力→Claudeに「S表紙切替」と依頼）
I2: シート名▶ | J2: P-003_吉野様邸キッチン
I3: 案件ID▶ | J3: P-003
B5: 御 見 積 書 | G5: 株式会社LinK
G6: 〒134-0081 東京都江戸川区北葬西1丁目2番22号
G7: TEL: 03-6825-2464 | J7: =TODAY() -> 46070
C10: =IFERROR(VLOOKUP($J$3,案件管理!A:D,3,FALSE),"") -> 矢島不動産管理株式会社 | F10: =IFERROR(VLOOKUP(VLOOKUP($J$3,案件管理!A:B,2,FALSE),顧客マスタ!A:D,4,FALSE),"様") -> 御中 | H10: エントランス以外 追加工事
E14: 御見積金額 | F14: ￥ | G14: =I61 -> 1573406 | I14: （税込）
C20: 工事名： | D20: =IFERROR(VLOOKUP($J$3,案件管理!A:D,4,FALSE),"") -> 吉野様邸 キッチンリフォーム
C22: 工 場 所 ： | D22: =操作パネル!F8 -> 東京都港区南麻布
C24: 有効期間 ： | D24: 30日間
C26: 別途工事 ： | D26: 見積記載無き項目
A32: 内 訳 明 細 書
A35: Ｎｏ， | B35: 名称形状 | F35: 数量 | G35: 単位 | H35: 単価 | I35: 金額 | J35: 備考
A36: 1 | B36: 解体工事 | I36: ='P-003_吉野様邸キッチン'!B105 -> 113333
A37: 2 | B37: 造作工事 | I37: ='P-003_吉野様邸キッチン'!B106 -> 0
A38: 3 | B38: 建具工事 | I38: ='P-003_吉野様邸キッチン'!B107 -> 0
A39: 4 | B39: 家具工事 | I39: ='P-003_吉野様邸キッチン'!B108 -> 680000
A40: 5 | B40: 電気設備 | I40: ='P-003_吉野様邸キッチン'!B109 -> 86667
A41: 6 | B41: タイル左官工事 | I41: ='P-003_吉野様邸キッチン'!B110 -> 0
A42: 7 | B42: 仕上げ工事 | I42: ='P-003_吉野様邸キッチン'!B111 -> 52400
A43: 8 | B43: 衛生設備 | I43: ='P-003_吉野様邸キッチン'!B112 -> 160000
A44: 9 | B44: 共通 | I44: ='P-003_吉野様邸キッチン'!B113 -> 48000
A45: 10 | B45: 下地工事 | I45: ='P-003_吉野様邸キッチン'!B114 -> 0
A46: 11 | B46: 新規壁工事 | I46: ='P-003_吉野様邸キッチン'!B115 -> 0
A47: 12 | B47: 床 | I47: ='P-003_吉野様邸キッチン'!B116 -> 0 | K47: 0
A48: 13 | B48: 空調 | I48: ='P-003_吉野様邸キッチン'!B117 -> 0
A49: 14 | B49: シート工事 | I49: ='P-003_吉野様邸キッチン'!B118 -> 0
A50: 15 | B50: 塗装工事 | I50: ='P-003_吉野様邸キッチン'!B119 -> 0
A51: 16 | B51: 雑工事 | I51: ='P-003_吉野様邸キッチン'!B120 -> 0
A52: 17 | B52: 防災工事 | I52: ='P-003_吉野様邸キッチン'!B121 -> 0
A53: 18 | B53: ガス工事 | I53: ='P-003_吉野様邸キッチン'!B122 -> 0
A54: 19 | B54: 産廃費 | I54: ='P-003_吉野様邸キッチン'!B123 -> 0
A55: 20 | B55: 仮設工事 | I55: ='P-003_吉野様邸キッチン'!B124 -> 0
A56: 21 | B56: 会社経費 | F56: =マスター設定!K20*100 -> 10 | G56: ％ | H56: =マスター設定!K22 -> 25000 | I56: =SUM(I36:I54)*マスター設定!K20 -> 114040
A57: 22 | B57: 現場経費 | F57: =マスター設定!K21*100 -> 5 | G57: ％ | H57: =マスター設定!K22 -> 25000 | I57: =SUM(I36:I54)*マスター設定!K21 -> 57020
A58: 23 | B58: 現場管理費 | F58: =マスター設定!K23 -> 5 | G58: 人工 | H58: =マスター設定!K22 -> 25000 | I58: =マスター設定!K23*マスター設定!K22 -> 125000
A59: 24 | B59: 消費税 | F59: 10 | G59: ％ | I59: =SUM(I36:I58)*マスター設定!K24 -> 143646
A60: 25 | I60: -6700
B61: 小計 | I61: =SUM(I36:I60) -> 1573406

Sheet P-003_吉野様邸キッチン
A1: P-003 吉野様邸 キッチンリフォーム
A2: ※ 新規案件作成時にこのシートを複製して使用します
A4: ▼ 案件基本情報
A5: 案件ID | B5: P-003 | D5: 顧客ID | E5: C-001 | F5: 顧客名 | G5: =IFERROR(VLOOKUP(E5,顧客マスタ!A:C,3,FALSE),"") -> 矢島不動産管理株式会社 | I5: 敬称 | J5: =IFERROR(VLOOKUP(E5,顧客マスタ!A:D,4,FALSE),"") -> 御中 | M5: 担当者 | N5: 吉野博
A6: 工事名 | B6: 吉野様邸 キッチンリフォーム | F6: 施工場所 | G6: 東京都港区南麻布 | M6: 作成日 | N6: =TODAY() -> 46070
A7: 目標粗利率 | B7: 0.25 | D7: ※原価逆算型のデフォルト
A9: ▼ 原価管理表（見積 → 原価 → 客出し金額 → 発注管理）
A11: ※ A=原価逆算型（原価÷(1-粗利率)） B=定価固定型（客出し固定） C=単価固定型（クロス等市場単価×数量）
A12: 青字=手入力 黒字=自動計算 ★=発注情報 ◆E/F/H列はDB自動参照（上書きOK）
B13: 原価情報 | H13: 客出し情報 | L13: 利益 | N13: ★ 発注管理
A14: No. | B14: タイプ | C14: 工事カテゴリ | D14: 品名（小項目） | E14: 仕様・形状 | F14: 原価単価 | G14: 原価金額 | H14: 単位 | I14: 数量 | J14: 客出し単価 | K14: 客出し金額 | L14: 利益額 | M14: 利益率 | N14: 発注先 | O14: 発注日 | P14: 発注額 | Q14: 支払済 | R14: 備考
A15: 1 | B15: A | C15: 解体工事 | D15: 既存キッチン解体・撤去 | E15: 材工共 | F15: 85000 | G15: =IF(F15<>"",F15*I15,"") -> 85000 | H15: 式 | I15: 1 | J15: =IF(B15="A",IF(AND(F15<>"",I15<>""),ROUND(F15/(1-$B$7),0),""),"") -> 113333 | K15: =IF(AND(J15<>"",I15<>""),J15*I15,"") -> 113333 | L15: =IF(AND(K15<>"",G15<>""),K15-G15,"") -> 28333 | M15: =IF(AND(K15<>"",K15<>0),L15/K15,"") -> 0.24999779 | P15: =IF(N15<>"",G15,"")
A16: 2 | B16: A | C16: 衛生設備 | D16: 給排水配管工事 | E16: 材工共 | F16: 120000 | G16: =IF(F16<>"",F16*I16,"") -> 120000 | H16: 式 | I16: 1 | J16: =IF(B16="A",IF(AND(F16<>"",I16<>""),ROUND(F16/(1-$B$7),0),""),"") -> 160000 | K16: =IF(AND(J16<>"",I16<>""),J16*I16,"") -> 160000 | L16: =IF(AND(K16<>"",G16<>""),K16-G16,"") -> 40000 | M16: =IF(AND(K16<>"",K16<>0),L16/K16,"") -> 0.25 | P16: =IF(N16<>"",G16,"")
A17: 3 | B17: B | C17: 家具工事 | D17: LIXIL システムキッチン シエラS | E17: W2550 IH・食洗機付 | F17: 420000 | G17: =IF(F17<>"",F17*I17,"") -> 420000 | H17: 台 | I17: 1 | J17: 680000 | K17: =IF(AND(J17<>"",I17<>""),J17*I17,"") -> 680000 | L17: =IF(AND(K17<>"",G17<>""),K17-G17,"") -> 260000 | M17: =IF(AND(K17<>"",K17<>0),L17/K17,"") -> 0.38235294 | P17: =IF(N17<>"",G17,"")
A18: 4 | B18: C | C18: 仕上げ工事 | D18: クロス張替え | E18: 量産クロス SP級 | F18: 650 | G18: =IF(F18<>"",F18*I18,"") -> 18200 | H18: ㎡ | I18: 28 | J18: 1100 | K18: =IF(AND(J18<>"",I18<>""),J18*I18,"") -> 30800 | L18: =IF(AND(K18<>"",G18<>""),K18-G18,"") -> 12600 | M18: =IF(AND(K18<>"",K18<>0),L18/K18,"") -> 0.40909091 | P18: =IF(N18<>"",G18,"")
A19: 5 | B19: C | C19: 仕上げ工事 | D19: CFシート張替え | E19: サンゲツ HM-10108 | F19: 800 | G19: =IF(F19<>"",F19*I19,"") -> 9600 | H19: ㎡ | I19: 12 | J19: 1800 | K19: =IF(AND(J19<>"",I19<>""),J19*I19,"") -> 21600 | L19: =IF(AND(K19<>"",G19<>""),K19-G19,"") -> 12000 | M19: =IF(AND(K19<>"",K19<>0),L19/K19,"") -> 0.55555556 | P19: =IF(N19<>"",G19,"")
A20: 6 | B20: A | C20: 電気設備 | D20: コンセント増設・照明移設 | E20: 材工共 | F20: 65000 | G20: =IF(F20<>"",F20*I20,"") -> 65000 | H20: 式 | I20: 1 | J20: =IF(B20="A",IF(AND(F20<>"",I20<>""),ROUND(F20/(1-$B$7),0),""),"") -> 86667 | K20: =IF(AND(J20<>"",I20<>""),J20*I20,"") -> 86667 | L20: =IF(AND(K20<>"",G20<>""),K20-G20,"") -> 21667 | M20: =IF(AND(K20<>"",K20<>0),L20/K20,"") -> 0.25000288 | P20: =IF(N20<>"",G20,"")
A21: 7 | B21: A | C21: 共通 | D21: 産廃処理費 | E21: 混載 | F21: 18000 | G21: =IF(F21<>"",F21*I21,"") -> 36000 | H21: ㎥ | I21: 2 | J21: =IF(B21="A",IF(AND(F21<>"",I21<>""),ROUND(F21/(1-$B$7),0),""),"") -> 24000 | K21: =IF(AND(J21<>"",I21<>""),J21*I21,"") -> 48000 | L21: =IF(AND(K21<>"",G21<>""),K21-G21,"") -> 12000 | M21: =IF(AND(K21<>"",K21<>0),L21/K21,"") -> 0.25 | P21: =IF(N21<>"",G21,"")
A22: 8 | E22: =IF(AND(C22<>"",D22<>""),IFERROR(INDEX(工事項目DB!D:D,MATCH(C22&"|"&D22,工事項目DB!L:L,0)),""),"") | F22: =IF(AND(C22<>"",D22<>""),IFERROR(INDEX(工事項目DB!F:F,MATCH(C22&"|"&D22,工事項目DB!L:L,0)),""),"") | G22: =IF(F22<>"",F22*I22,"") | H22: =IF(AND(C22<>"",D22<>""),IFERROR(INDEX(工事項目DB!E:E,MATCH(C22&"|"&D22,工事項目DB!L:L,0)),""),"") | J22: =IF(B22="A",IF(AND(F22<>"",I22<>""),ROUND(F22/(1-$B$7),0),""),"") | K22: =IF(AND(J22<>"",I22<>""),J22*I22,"") | L22: =IF(AND(K22<>"",G22<>""),K22-G22,"") | M22: =IF(AND(K22<>"",K22<>0),L22/K22,"") | P22: =IF(N22<>"",G22,"")
A23: 9 | E23: =IF(AND(C23<>"",D23<>""),IFERROR(INDEX(工事項目DB!D:D,MATCH(C23&"|"&D23,工事項目DB!L:L,0)),""),"") | F23: =IF(AND(C23<>"",D23<>""),IFERROR(INDEX(工事項目DB!F:F,MATCH(C23&"|"&D23,工事項目DB!L:L,0)),""),"") | G23: =IF(F23<>"",F23*I23,"") | H23: =IF(AND(C23<>"",D23<>""),IFERROR(INDEX(工事項目DB!E:E,MATCH(C23&"|"&D23,工事項目DB!L:L,0)),""),"") | J23: =IF(B23="A",IF(AND(F23<>"",I23<>""),ROUND(F23/(1-$B$7),0),""),"") | K23: =IF(AND(J23<>"",I23<>""),J23*I23,"") | L23: =IF(AND(K23<>"",G23<>""),K23-G23,"") | M23: =IF(AND(K23<>"",K23<>0),L23/K23,"") | P23: =IF(N23<>"",G23,"")
A24: 10 | E24: =IF(AND(C24<>"",D24<>""),IFERROR(INDEX(工事項目DB!D:D,MATCH(C24&"|"&D24,工事項目DB!L:L,0)),""),"") | F24: =IF(AND(C24<>"",D24<>""),IFERROR(INDEX(工事項目DB!F:F,MATCH(C24&"|"&D24,工事項目DB!L:L,0)),""),"") | G24: =IF(F24<>"",F24*I24,"") | H24: =IF(AND(C24<>"",D24<>""),IFERROR(INDEX(工事項目DB!E:E,MATCH(C24&"|"&D24,工事項目DB!L:L,0)),""),"") | J24: =IF(B24="A",IF(AND(F24<>"",I24<>""),ROUND(F24/(1-$B$7),0),""),"") | K24: =IF(AND(J24<>"",I24<>""),J24*I24,"") | L24: =IF(AND(K24<>"",G24<>""),K24-G24,"") | M24: =IF(AND(K24<>"",K24<>0),L24/K24,"") | P24: =IF(N24<>"",G24,"")
A25: 11 | E25: =IF(AND(C25<>"",D25<>""),IFERROR(INDEX(工事項目DB!D:D,MATCH(C25&"|"&D25,工事項目DB!L:L,0)),""),"") | F25: =IF(AND(C25<>"",D25<>""),IFERROR(INDEX(工事項目DB!F:F,MATCH(C25&"|"&D25,工事項目DB!L:L,0)),""),"") | G25: =IF(F25<>"",F25*I25,"") | H25: =IF(AND(C25<>"",D25<>""),IFERROR(INDEX(工事項目DB!E:E,MATCH(C25&"|"&D25,工事項目DB!L:L,0)),""),"") | J25: =IF(B25="A",IF(AND(F25<>"",I25<>""),ROUND(F25/(1-$B$7),0),""),"") | K25: =IF(AND(J25<>"",I25<>""),J25*I25,"") | L25: =IF(AND(K25<>"",G25<>""),K25-G25,"") | M25: =IF(AND(K25<>"",K25<>0),L25/K25,"") | P25: =IF(N25<>"",G25,"")
A26: 12 | E26: =IF(AND(C26<>"",D26<>""),IFERROR(INDEX(工事項目DB!D:D,MATCH(C26&"|"&D26,工事項目DB!L:L,0)),""),"") | F26: =IF(AND(C26<>"",D26<>""),IFERROR(INDEX(工事項目DB!F:F,MATCH(C26&"|"&D26,工事項目DB!L:L,0)),""),"") | G26: =IF(F26<>"",F26*I26,"") | H26: =IF(AND(C26<>"",D26<>""),IFERROR(INDEX(工事項目DB!E:E,MATCH(C26&"|"&D26,工事項目DB!L:L,0)),""),"") | J26: =IF(B26="A",IF(AND(F26<>"",I26<>""),ROUND(F26/(1-$B$7),0),""),"") | K26: =IF(AND(J26<>"",I26<>""),J26*I26,"") | L26: =IF(AND(K26<>"",G26<>""),K26-G26,"") | M26: =IF(AND(K26<>"",K26<>0),L26/K26,"") | P26: =IF(N26<>"",G26,"")
A27: 13 | E27: =IF(AND(C27<>"",D27<>""),IFERROR(INDEX(工事項目DB!D:D,MATCH(C27&"|"&D27,工事項目DB!L:L,0)),""),"") | F27: =IF(AND(C27<>"",D27<>""),IFERROR(INDEX(工事項目DB!F:F,MATCH(C27&"|"&D27,工事項目DB!L:L,0)),""),"") | G27: =IF(F27<>"",F27*I27,"") | H27: =IF(AND(C27<>"",D27<>""),IFERROR(INDEX(工事項目DB!E:E,MATCH(C27&"|"&D27,工事項目DB!L:L,0)),""),"") | J27: =IF(B27="A",IF(AND(F27<>"",I27<>""),ROUND(F27/(1-$B$7),0),""),"") | K27: =IF(AND(J27<>"",I27<>""),J27*I27,"") | L27: =IF(AND(K27<>"",G27<>""),K27-G27,"") | M27: =IF(AND(K27<>"",K27<>0),L27/K27,"") | P27: =IF(N27<>"",G27,"")
A28: 14 | E28: =IF(AND(C28<>"",D28<>""),IFERROR(INDEX(工事項目DB!D:D,MATCH(C28&"|"&D28,工事項目DB!L:L,0)),""),"") | F28: =IF(AND(C28<>"",D28<>""),IFERROR(INDEX(工事項目DB!F:F,MATCH(C28&"|"&D28,工事項目DB!L:L,0)),""),"") | G28: =IF(F28<>"",F28*I28,"") | H28: =IF(AND(C28<>"",D28<>""),IFERROR(INDEX(工事項目DB!E:E,MATCH(C28&"|"&D28,工事項目DB!L:L,0)),""),"") | J28: =IF(B28="A",IF(AND(F28<>"",I28<>""),ROUND(F28/(1-$B$7),0),""),"") | K28: =IF(AND(J28<>"",I28<>""),J28*I28,"") | L28: =IF(AND(K28<>"",G28<>""),K28-G28,"") | M28: =IF(AND(K28<>"",K28<>0),L28/K28,"") | P28: =IF(N28<>"",G28,"")
A29: 15 | E29: =IF(AND(C29<>"",D29<>""),IFERROR(INDEX(工事項目DB!D:D,MATCH(C29&"|"&D29,工事項目DB!L:L,0)),""),"") | F29: =IF(AND(C29<>"",D29<>""),IFERROR(INDEX(工事項目DB!F:F,MATCH(C29&"|"&D29,工事項目DB!L:L,0)),""),"") | G29: =IF(F29<>"",F29*I29,"") | H29: =IF(AND(C29<>"",D29<>""),IFERROR(INDEX(工事項目DB!E:E,MATCH(C29&"|"&D29,工事項目DB!L:L,0)),""),"") | J29: =IF(B29="A",IF(AND(F29<>"",I29<>""),ROUND(F29/(1-$B$7),0),""),"") | K29: =IF(AND(J29<>"",I29<>""),J29*I29,"") | L29: =IF(AND(K29<>"",G29<>""),K29-G29,"") | M29: =IF(AND(K29<>"",K29<>0),L29/K29,"") | P29: =IF(N29<>"",G29,"")
A30: 16 | E30: =IF(AND(C30<>"",D30<>""),IFERROR(INDEX(工事項目DB!D:D,MATCH(C30&"|"&D30,工事項目DB!L:L,0)),""),"") | F30: =IF(AND(C30<>"",D30<>""),IFERROR(INDEX(工事項目DB!F:F,MATCH(C30&"|"&D30,工事項目DB!L:L,0)),""),"") | G30: =IF(F30<>"",F30*I30,"") | H30: =IF(AND(C30<>"",D30<>""),IFERROR(INDEX(工事項目DB!E:E,MATCH(C30&"|"&D30,工事項目DB!L:L,0)),""),"") | J30: =IF(B30="A",IF(AND(F30<>"",I30<>""),ROUND(F30/(1-$B$7),0),""),"") | K30: =IF(AND(J30<>"",I30<>""),J30*I30,"") | L30: =IF(AND(K30<>"",G30<>""),K30-G30,"") | M30: =IF(AND(K30<>"",K30<>0),L30/K30,"") | P30: =IF(N30<>"",G30,"")
A31: 17 | E31: =IF(AND(C31<>"",D31<>""),IFERROR(INDEX(工事項目DB!D:D,MATCH(C31&"|"&D31,工事項目DB!L:L,0)),""),"") | F31: =IF(AND(C31<>"",D31<>""),IFERROR(INDEX(工事項目DB!F:F,MATCH(C31&"|"&D31,工事項目DB!L:L,0)),""),"") | G31: =IF(F31<>"",F31*I31,"") | H31: =IF(AND(C31<>"",D31<>""),IFERROR(INDEX(工事項目DB!E:E,MATCH(C31&"|"&D31,工事項目DB!L:L,0)),""),"") | J31: =IF(B31="A",IF(AND(F31<>"",I31<>""),ROUND(F31/(1-$B$7),0),""),"") | K31: =IF(AND(J31<>"",I31<>""),J31*I31,"") | L31: =IF(AND(K31<>"",G31<>""),K31-G31,"") | M31: =IF(AND(K31<>"",K31<>0),L31/K31,"") | P31: =IF(N31<>"",G31,"")
A32: 18 | E32: =IF(AND(C32<>"",D32<>""),IFERROR(INDEX(工事項目DB!D:D,MATCH(C32&"|"&D32,工事項目DB!L:L,0)),""),"") | F32: =IF(AND(C32<>"",D32<>""),IFERROR(INDEX(工事項目DB!F:F,MATCH(C32&"|"&D32,工事項目DB!L:L,0)),""),"") | G32: =IF(F32<>"",F32*I32,"") | H32: =IF(AND(C32<>"",D32<>""),IFERROR(INDEX(工事項目DB!E:E,MATCH(C32&"|"&D32,工事項目DB!L:L,0)),""),"") | J32: =IF(B32="A",IF(AND(F32<>"",I32<>""),ROUND(F32/(1-$B$7),0),""),"") | K32: =IF(AND(J32<>"",I32<>""),J32*I32,"") | L32: =IF(AND(K32<>"",G32<>""),K32-G32,"") | M32: =IF(AND(K32<>"",K32<>0),L32/K32,"") | P32: =IF(N32<>"",G32,"")
A33: 19 | E33: =IF(AND(C33<>"",D33<>""),IFERROR(INDEX(工事項目DB!D:D,MATCH(C33&"|"&D33,工事項目DB!L:L,0)),""),"") | F33: =IF(AND(C33<>"",D33<>""),IFERROR(INDEX(工事項目DB!F:F,MATCH(C33&"|"&D33,工事項目DB!L:L,0)),""),"") | G33: =IF(F33<>"",F33*I33,"") | H33: =IF(AND(C33<>"",D33<>""),IFERROR(INDEX(工事項目DB!E:E,MATCH(C33&"|"&D33,工事項目DB!L:L,0)),""),"") | J33: =IF(B33="A",IF(AND(F33<>"",I33<>""),ROUND(F33/(1-$B$7),0),""),"") | K33: =IF(AND(J33<>"",I33<>""),J33*I33,"") | L33: =IF(AND(K33<>"",G33<>""),K33-G33,"") | M33: =IF(AND(K33<>"",K33<>0),L33/K33,"") | P33: =IF(N33<>"",G33,"")
... A44: 30 | E44: =IF(AND(C44<>"",D44<>""),IFERROR(INDEX(工事項目DB!D:D,MATCH(C44&"|"&D44,工事項目DB!L:L,0)),""),"") | F44: =IF(AND(C44<>"",D44<>""),IFERROR(INDEX(工事項目DB!F:F,MATCH(C44&"|"&D44,工事項目DB!L:L,0)),""),"") | G44: =IF(F44<>"",F44*I44,"") | H44: =IF(AND(C44<>"",D44<>""),IFERROR(INDEX(工事項目DB!E:E,MATCH(C44&"|"&D44,工事項目DB!L:L,0)),""),"") | J44: =IF(B44="A",IF(AND(F44<>"",I44<>""),ROUND(F44/(1-$B$7),0),""),"") | K44: =IF(AND(J44<>"",I44<>""),J44*I44,"") | L44: =IF(AND(K44<>"",G44<>""),K44-G44,"") | M44: =IF(AND(K44<>"",K44<>0),L44/K44,"") | P44: =IF(N44<>"",G44,"")
F45: 原価合計 | G45: =SUM(G15:G44) -> 753800 | J45: 客出し合計 | K45: =SUM(K15:K44) -> 1140400 | L45: =K45-G45 -> 386600 | M45: =IF(K45<>0,L45/K45,"") -> 0.33900386 | P45: =SUM(P15:P44) -> 0
A47: ▼ 税計算
A48: 小計（税抜） | G48: =G45 -> 753800 | K48: =K45 -> 1140400 | L48: =L45 -> 386600 | M48: =M45 -> 0.33900386
A49: 消費税（10%） | G49: =ROUND(G48*マスター設定!K24,0) -> 75380 | K49: =ROUND(K48*マスター設定!K24,0) -> 114040
A50: 合計（税込） | G50: =G48+G49 -> 829180 | K50: =K48+K49 -> 1254440 | L50: =K50-G50 -> 425260 | M50: =IF(K50<>0,L50/K50,"") -> 0.33900386
A53: ▼ 行操作ツール
A54: クリアしたい行No. | C54: ← 行No.を入力してClaudeに「行クリア」と伝えてください
A55: 入替え: 行A ↔ 行B | C55: ← | E55: ← 2つのNo.を入力してClaudeに「行入替え」と伝えてください
A56: ※ 直接セルを選択してDeleteキーでもクリアできます（数式は自動復元）
A60: ▼ DB参照（過去実績から自動表示）
A61: ※ 上の原価管理表で工事カテゴリ(C列)を入力すると、工事項目DBの過去実績がここに表示されます
A62: 💡 品名(D列)を入力 → 工事カテゴリ+品名がDBに一致すると仕様・単価・単位が自動入力されます。新規項目は手入力OK。
A63: 工事カテゴリ | B63: 品名 | C63: 仕様 | D63: 単位 | E63: 標準単価 | F63: 業者名 | G63: 最終使用日 | H63: 利益率 | I63: 使用回数 | J63: 案件名 | K63: → 転記方法
A64: {=IFERROR(_xlfn._xlws.SORT(_xlfn._xlws.FILTER(工事項目DB!B5:K50, (工事項目DB!A5:A50<>""), "データなし"), 1, 1), "データなし")} -> タイル左官工事 | B64: 浴槽タイルまし張り 壁床 | C64: 大判タイル 材料支給 | D64: 人工 | E64: 30000 | F64: 0 | G64: 45759 | H64: 0 | I64: 1 | J64: 南麻布レジデンス
A65: タイル左官工事 | B65: 目地 材工共 | C65: 0 | D65: 式 | E65: 65000 | F65: 0 | G65: 45759 | H65: 0 | I65: 1 | J65: 南麻布レジデンス
A66: タイル左官工事 | B66: 水回り コーキング | C66: 材工共 | D66: 式 | E66: 55000 | F66: 0 | G66: 45759 | H66: 0 | I66: 1 | J66: 南麻布レジデンス
A67: タイル左官工事 | B67: 既存ブロック塀 左官材工共 | C67: Magic coat flex クラウド仕上色 | D67: 式 | E67: 100000 | F67: 0 | G67: 45759 | H67: 0 | I67: 1 | J67: 南麻布レジデンス
A68: 衛生設備 | B68: 給排水配管工事 | C68: 材工共 | D68: 式 | E68: 120000 | F68: 0 | G68: 46070 | H68: 0.25 | I68: 1 | J68: P-003 吉野様邸 キッチンリフォーム
A69: 家具工事 | B69: 収納内部 引き出し付き什器 | C69: スライドレール取手金物込 | D69: 台 | E69: 248500 | F69: 0 | G69: 45759 | H69: 0 | I69: 1 | J69: 南麻布レジデンス
A70: 家具工事 | B70: ドロワー 本体代 | C70: 0 | D70: 台 | E70: 224850 | F70: 0 | G70: 45759 | H70: 0 | I70: 1 | J70: 南麻布レジデンス
A71: 家具工事 | B71: 大型障子 本体代 ワーロン | C71: 1800*1500x2 金物込 | D71: 組 | E71: 466500 | F71: 0 | G71: 45759 | H71: 0 | I71: 1 | J71: 南麻布レジデンス
A72: 家具工事 | B72: ベッド土台 ヘッドパネル | C72: ナラ突板 マットレス下脱着式 | D72: 組 | E72: 178560 | F72: 0 | G72: 45759 | H72: 0 | I72: 1 | J72: 南麻布レジデンス
A73: 家具工事 | B73: サイドボード ナラ突板 | C73: 照明コンセントスイッチ支給 | D73: 台 | E73: 78660 | F73: 0 | G73: 45759 | H73: 0 | I73: 1 | J73: 南麻布レジデンス
A74: 家具工事 | B74: 洗面台 ドレッサー コーリアン | C74: 0 | D74: 枚 | E74: 56000 | F74: 0 | G74: 45759 | H74: 0 | I74: 1 | J74: 南麻布レジデンス
A75: 家具工事 | B75: LIXIL システムキッチン シエラS | C75: W2550 IH・食洗機付 | D75: 台 | E75: 420000 | F75: 0 | G75: 46070 | H75: 0.25 | I75: 1 | J75: P-003 吉野様邸 キッチンリフォーム
A76: 解体工事 | B76: 発生材処理費 | C76: 混載 | D76: ㎥ | E76: 20000 | F76: 0 | G76: 45759 | H76: 0 | I76: 1 | J76: 南麻布レジデンス
A77: 解体工事 | B77: トラック | C77: 0 | D77: 台 | E77: 18000 | F77: 0 | G77: 45759 | H77: 0 | I77: 1 | J77: 南麻布レジデンス
A78: 解体工事 | B78: 運搬費 | C78: 0 | D78: 人工 | E78: 20000 | F78: 0 | G78: 45759 | H78: 0 | I78: 1 | J78: 南麻布レジデンス
A79: 解体工事 | B79: 既存キッチン解体・撤去 | C79: 材工共 | D79: 式 | E79: 85000 | F79: 0 | G79: 46070 | H79: 0 | I79: 1 | J79: P-003 吉野様邸 キッチンリフォーム
A80: 共通 | B80: 搬入費 | C80: 0 | D80: 式 | E80: 25000 | F80: 0 | G80: 45759 | H80: 0 | I80: 1 | J80: 南麻布レジデンス
A81: 共通 | B81: 副資材 | C81: 0 | D81: 式 | E81: 15200 | F81: 0 | G81: 45759 | H81: 0 | I81: 1 | J81: 南麻布レジデンス
A82: 共通 | B82: 発生材処理費 | C82: 0 | D82: 式 | E82: 6850 | F82: 0 | G82: 45759 | H82: 0 | I82: 1 | J82: 南麻布レジデンス
A83: 共通 | B83: 運搬費 | C83: 4t 2回分 | D83: 式 | E83: 100000 | F83: 0 | G83: 45759 | H83: 0 | I83: 1 | J83: 南麻布レジデンス
A84: 共通 | B84: 労務費（取付・現場加工） | C84: 0 | D84: 人工 | E84: 30000 | F84: 0 | G84: 45759 | H84: 0 | I84: 1 | J84: 南麻布レジデンス
A85: 共通 | B85: 資材運搬搬入費 | C85: 0 | D85: 式 | E85: 18000 | F85: 0 | G85: 45759 | H85: 0 | I85: 1 | J85: 南麻布レジデンス
A86: 共通 | B86: 産廃処理費 | C86: 混載 | D86: ㎥ | E86: 18000 | F86: 0 | G86: 46070 | H86: 0.25 | I86: 1 | J86: P-003 吉野様邸 キッチンリフォーム
A87: 建具工事 | B87: 1F-2F踊り場 障子 | C87: 797*474 金物含む | D87: 枚 | E87: 96520 | F87: 0 | G87: 45759 | H87: 0 | I87: 1 | J87: 南麻布レジデンス
A88: 建具工事 | B88: 2F廊下 障子 | C88: 500*572 金物含む | D88: 枚 | E88: 94500 | F88: 0 | G88: 45759 | H88: 0 | I88: 1 | J88: 南麻布レジデンス
A89: 建具工事 | B89: 2F廊下+2Fキッチン部分 障子 | C89: 2064*575 金物含む | D89: 枚 | E89: 166500 | F89: 0 | G89: 45759 | H89: 0 | I89: 1 | J89: 南麻布レジデンス
A90: 建具工事 | B90: WD2 新規建具 ナラ突板 | C90: 2121*667*36 金物取手枠込 | D90: 組 | E90: 200000 | F90: 0 | G90: 45759 | H90: 0 | I90: 1 | J90: 南麻布レジデンス
A91: 建具工事 | B91: WD3 新規引き戸 塗装仕上げ | C91: 2178*650*36 金物取手含む | D91: 組 | E91: 180000 | F91: 0 | G91: 45759 | H91: 0 | I91: 1 | J91: 南麻布レジデンス
A92: 建具工事 | B92: 運搬費 | C92: 新規建具３回 | D92: 式 | E92: 85000 | F92: 0 | G92: 45759 | H92: 0 | I92: 1 | J92: 南麻布レジデンス
A93: 建具工事 | B93: 副資材 | C93: 0 | D93: 式 | E93: 15200 | F93: 0 | G93: 45759 | H93: 0 | I93: 1 | J93: 南麻布レジデンス
A94: 仕上げ工事 | B94: 階段下 新規ベニヤ貼り後 塗装 | C94: 材工共 | D94: 式 | E94: 65000 | F94: 0 | G94: 45759 | H94: 0 | I94: 1 | J94: 南麻布レジデンス
A95: 仕上げ工事 | B95: クロス張替え | C95: 量産クロス SP級 | D95: ㎡ | E95: 650 | F95: 0 | G95: 46070 | H95: 0.38235294 | I95: 1 | J95: P-003 吉野様邸 キッチンリフォーム
A96: 仕上げ工事 | B96: CFシート張替え | C96: サンゲツ HM-10108 | D96: ㎡ | E96: 800 | F96: 0 | G96: 46070 | H96: 0.40909091 | I96: 1 | J96: P-003 吉野様邸 キッチンリフォーム
A97: 造作工事 | B97: 階段室下 シナベニヤ t12 材料費 | C97: 0 | D97: 枚 | E97: 11000 | F97: 0 | G97: 45759 | H97: 0 | I97: 1 | J97: 南麻布レジデンス
A98: 造作工事 | B98: 階段室下 間接照明隠蔽用 モクヒモ材 | C98: 0 | D98: 本 | E98: 15000 | F98: 0 | G98: 45759 | H98: 0 | I98: 1 | J98: 南麻布レジデンス
A99: 造作工事 | B99: シナベニヤ ダボ掘り込み 取付 | C99: 0 | D99: 式 | E99: 25000 | F99: 0 | G99: 45759 | H99: 0 | I99: 1 | J99: 南麻布レジデンス
A100: 造作工事 | B100: 折り上げ天井部 ナラ突板 | C100: 2m | D100: 本 | E100: 18500 | F100: 0 | G100: 45759 | H100: 0 | I100: 1 | J100: 南麻布レジデンス
A101: 造作工事 | B101: 労務費 | C101: 0 | D101: 人工 | E101: 30000 | F101: 0 | G101: 45759 | H101: 0 | I101: 1 | J101: 南麻布レジデンス
A102: 電気設備 | B102: コンセント増設・照明移設 | C102: 材工共 | D102: 式 | E102: 65000 | F102: 0 | G102: 46070 | H102: 0.55555556 | I102: 1 | J102: P-003 吉野様邸 キッチンリフォーム
A104: ▼ S表紙用 カテゴリ別集計
A105: 解体工事 | B105: =SUMIFS(K15:K44,C15:C44,A105) -> 113333
A106: 造作工事 | B106: =SUMIFS(K15:K44,C15:C44,A106) -> 0
A107: 建具工事 | B107: =SUMIFS(K15:K44,C15:C44,A107) -> 0
A108: 家具工事 | B108: =SUMIFS(K15:K44,C15:C44,A108) -> 680000
A109: 電気設備 | B109: =SUMIFS(K15:K44,C15:C44,A109) -> 86667
A110: タイル左官工事 | B110: =SUMIFS(K15:K44,C15:C44,A110) -> 0
A111: 仕上げ工事 | B111: =SUMIFS(K15:K44,C15:C44,A111) -> 52400
A112: 衛生設備 | B112: =SUMIFS(K15:K44,C15:C44,A112) -> 160000
A113: 共通 | B113: =SUMIFS(K15:K44,C15:C44,A113) -> 48000
A114: 下地工事 | B114: =SUMIFS(K15:K44,C15:C44,A114) -> 0
A115: 新規壁工事 | B115: =SUMIFS(K15:K44,C15:C44,A115) -> 0
A116: 床 | B116: =SUMIFS(K15:K44,C15:C44,A116) -> 0
A117: 空調 | B117: =SUMIFS(K15:K44,C15:C44,A117) -> 0
A118: シート工事 | B118: =SUMIFS(K15:K44,C15:C44,A118) -> 0
A119: 塗装工事 | B119: =SUMIFS(K15:K44,C15:C44,A119) -> 0
A120: 雑工事 | B120: =SUMIFS(K15:K44,C15:C44,A120) -> 0
...

Sheet 発注書兼請求書
A1: 帳票切替 | B1: 発注書 | C1: 案件ID▶ | D1: P-003 | E1: 業者ID▶ | G1: 1
A3: =IF(B1="発注書","【 発 注 書 】","【 請 求 書 】") -> 【 発 注 書 】
A5: 宛先業者 | B5: =IFERROR(VLOOKUP(G1,業者DB!A:B,2,FALSE),"") -> 株式会社M-Pros | F5: 御中 | G5: 株式会社LinK
B6: =IFERROR(VLOOKUP(B5,業者DB!B:F,3,FALSE)&" "&VLOOKUP(B5,業者DB!B:F,4,FALSE),"") | G6: 〒134-0081 東京都江戸川区北葛西1-2-22
G7: TEL: 03-6825-2464
G8: Email: info@link-8.jp
A10: 施 工 場 所 | B10: =IFERROR(VLOOKUP(D1,案件管理!A:E,5,FALSE),"") -> キッチン設備・内装 | G10: =IF(B1="発注書","発 注 日","請 求 日") -> 発 注 日 | H10: =TODAY() -> 46070
A11: 工 事 件 名 | B11: =IFERROR(VLOOKUP(D1,案件管理!A:D,4,FALSE),"") -> 吉野様邸 キッチンリフォーム | G11: =IF(B1="請求書","支 払 期 日","")
A12: 受 渡 期 限
A13: 支 払 条 件 | B13: =IFERROR(VLOOKUP(G1,業者DB!A:I,9,FALSE),"") -> 0 | H13: 【社判】
A14: 総 金 額 | B14: ￥ | D14: =I42 -> 0 | F14: （税込）
A16: =IF(B1="発注書","下記の通り発注いたします。","下記の通りご請求申し上げます。") -> 下記の通り発注いたします。
A18: No. | B18: 名称 | D18: 仕様・形状 | F18: 数量 | G18: 単位 | H18: 単価 | I18: 金額
A19: 1 | I19: =IF(AND(F19<>"",H19<>""),F19*H19,"")
A20: 2 | I20: =IF(AND(F20<>"",H20<>""),F20*H20,"")
A21: 3 | I21: =IF(AND(F21<>"",H21<>""),F21*H21,"")
A22: 4 | I22: =IF(AND(F22<>"",H22<>""),F22*H22,"")
A23: 5 | I23: =IF(AND(F23<>"",H23<>""),F23*H23,"")
A24: 6 | I24: =IF(AND(F24<>"",H24<>""),F24*H24,"")
A25: 7 | I25: =IF(AND(F25<>"",H25<>""),F25*H25,"")
A26: 8 | I26: =IF(AND(F26<>"",H26<>""),F26*H26,"")
A27: 9 | I27: =IF(AND(F27<>"",H27<>""),F27*H27,"")
A28: 10 | I28: =IF(AND(F28<>"",H28<>""),F28*H28,"")
A29: 11 | I29: =IF(AND(F29<>"",H29<>""),F29*H29,"")
A30: 12 | I30: =IF(AND(F30<>"",H30<>""),F30*H30,"")
... A38: 20 | I38: =IF(AND(F38<>"",H38<>""),F38*H38,"")
A39: 小 計 | I39: =SUM(I19:I38) -> 0
A40: 消費税（10%） | I40: =ROUND(I39*マスター設定!K24,0) -> 0
A42: 合 計（税込） | I42: =I39+I40 -> 0
A44: =IF(B1="請求書","【 振込口座 】","")
A47: =IF(B1="請求書","お振込手数料のご負担をお願い申し上げます。","※ 本発注書記載の金額にてご請求をお願いいたします。") -> ※ 本発注書記載の金額にてご請求をお願いいたします。

Sheet 領収書
A1: 領収書 | I1: ▼ 入力エリア
I2: 請求ID | K2: ←入力
G3: No. | H3: =IF(J2="","","R-"&MID(J2,5,3)) | I3: 案件ID | J3: =IF(J2="","",IFERROR(VLOOKUP(J2,請求管理!A:B,2,FALSE),""))
I4: 案件名 | J4: =IF(J2="","",IFERROR(VLOOKUP(J2,請求管理!A:C,3,FALSE),""))
B5: 領 収 書 | I5: 顧客名 | J5: =IF(J2="","",IFERROR(VLOOKUP(J2,請求管理!A:D,4,FALSE),""))
B7: =IF(J5="","",J5) | E7: 様
G8: 発行日 | H8: =IF(J2="","",TODAY())
B10: 金 額 | D10: =IF(J2="","",IFERROR(VLOOKUP(J2,請求管理!A:I,9,FALSE),0))
B12: 但し | D12: =IF(J2="","",IFERROR(VLOOKUP(J2,請求管理!A:C,3,FALSE),"")) | F12: の代金として
B14: 上記正に領収いたしました。
B16: 内訳
B17: 請求種別 | D17: =IF(J2="","",IFERROR(VLOOKUP(J2,請求管理!A:E,5,FALSE),""))
B18: 請求日 | D18: =IF(J2="","",IFERROR(VLOOKUP(J2,請求管理!A:F,6,FALSE),""))
B19: 請求額 | D19: =IF(J2="","",IFERROR(VLOOKUP(J2,請求管理!A:G,7,FALSE),0))
B20: 入金日 | D20: =IF(J2="","",IFERROR(VLOOKUP(J2,請求管理!A:H,8,FALSE),""))
B21: 入金額 | D21: =IF(J2="","",IFERROR(VLOOKUP(J2,請求管理!A:I,9,FALSE),0))
G23: 株式会社 LinK
G24: 〔社印〕

Sheet 請求管理
A1: 請求管理
A2: 株式会社LinK - 請求・入金管理
A3: ※ 案件ごとの請求・入金を行単位で追跡。分割請求（着手金/完工金）に対応。
A4: 請求ID | B4: 案件ID | C4: 案件名 | D4: 顧客名 | E4: 請求種別 | F4: 請求日 | G4: 請求額 | H4: 入金日 | I4: 入金額 | J4: 残額 | K4: ステータス | L4: 備考
A5: =IF(B5="","","INV-"&TEXT(ROW()-4,"000")) -> INV-001 | B5: P-001 | C5: =IF(B5="","",IFERROR(VLOOKUP(B5,案件管理!A:D,4,FALSE),"")) -> 吉野様邸 リフォーム工事 | D5: =IF(B5="","",IFERROR(VLOOKUP(B5,案件管理!A:C,3,FALSE),"")) -> 矢島不動産管理株式会社 | E5: 一括 | F5: 45735 | G5: 3500000 | H5: 45760 | I5: 3500000 | J5: =IF(B5="","",IF(G5="","",G5-IF(I5="",0,I5))) -> 0 | K5: =IF(B5="","",IF(G5="","",IF(J5<=0,"✅入金済",IF(I5<>"","⚠一部入金",IF(F5<>"","❌未入金",""))))) -> ✅入金済
A6: =IF(B6="","","INV-"&TEXT(ROW()-4,"000")) -> INV-002 | B6: P-003 | C6: =IF(B6="","",IFERROR(VLOOKUP(B6,案件管理!A:D,4,FALSE),"")) -> 吉野様邸 キッチンリフォーム | D6: =IF(B6="","",IFERROR(VLOOKUP(B6,案件管理!A:C,3,FALSE),"")) -> 矢島不動産管理株式会社 | E6: 着手金 | F6: 46034 | G6: 627220 | H6: 46040 | I6: 627220 | J6: =IF(B6="","",IF(G6="","",G6-IF(I6="",0,I6))) -> 0 | K6: =IF(B6="","",IF(G6="","",IF(J6<=0,"✅入金済",IF(I6<>"","⚠一部入金",IF(F6<>"","❌未入金",""))))) -> ✅入金済
A7: =IF(B7="","","INV-"&TEXT(ROW()-4,"000")) -> INV-003 | B7: P-003 | C7: =IF(B7="","",IFERROR(VLOOKUP(B7,案件管理!A:D,4,FALSE),"")) -> 吉野様邸 キッチンリフォーム | D7: =IF(B7="","",IFERROR(VLOOKUP(B7,案件管理!A:C,3,FALSE),"")) -> 矢島不動産管理株式会社 | E7: 完工金 | F7: 46064 | G7: 627220 | J7: =IF(B7="","",IF(G7="","",G7-IF(I7="",0,I7))) -> 627220 | K7: =IF(B7="","",IF(G7="","",IF(J7<=0,"✅入金済",IF(I7<>"","⚠一部入金",IF(F7<>"","❌未入金",""))))) -> ❌未入金
A8: =IF(B8="","","INV-"&TEXT(ROW()-4,"000")) | C8: =IF(B8="","",IFERROR(VLOOKUP(B8,案件管理!A:D,4,FALSE),"")) | D8: =IF(B8="","",IFERROR(VLOOKUP(B8,案件管理!A:C,3,FALSE),"")) | J8: =IF(B8="","",IF(G8="","",G8-IF(I8="",0,I8))) | K8: =IF(B8="","",IF(G8="","",IF(J8<=0,"✅入金済",IF(I8<>"","⚠一部入金",IF(F8<>"","❌未入金","")))))
A9: =IF(B9="","","INV-"&TEXT(ROW()-4,"000")) | C9: =IF(B9="","",IFERROR(VLOOKUP(B9,案件管理!A:D,4,FALSE),"")) | D9: =IF(B9="","",IFERROR(VLOOKUP(B9,案件管理!A:C,3,FALSE),"")) | J9: =IF(B9="","",IF(G9="","",G9-IF(I9="",0,I9))) | K9: =IF(B9="","",IF(G9="","",IF(J9<=0,"✅入金済",IF(I9<>"","⚠一部入金",IF(F9<>"","❌未入金","")))))
A10: =IF(B10="","","INV-"&TEXT(ROW()-4,"000")) | C10: =IF(B10="","",IFERROR(VLOOKUP(B10,案件管理!A:D,4,FALSE),"")) | D10: =IF(B10="","",IFERROR(VLOOKUP(B10,案件管理!A:C,3,FALSE),"")) | J10: =IF(B10="","",IF(G10="","",G10-IF(I10="",0,I10))) | K10: =IF(B10="","",IF(G10="","",IF(J10<=0,"✅入金済",IF(I10<>"","⚠一部入金",IF(F10<>"","❌未入金","")))))
A11: =IF(B11="","","INV-"&TEXT(ROW()-4,"000")) | C11: =IF(B11="","",IFERROR(VLOOKUP(B11,案件管理!A:D,4,FALSE),"")) | D11: =IF(B11="","",IFERROR(VLOOKUP(B11,案件管理!A:C,3,FALSE),"")) | J11: =IF(B11="","",IF(G11="","",G11-IF(I11="",0,I11))) | K11: =IF(B11="","",IF(G11="","",IF(J11<=0,"✅入金済",IF(I11<>"","⚠一部入金",IF(F11<>"","❌未入金","")))))
A12: =IF(B12="","","INV-"&TEXT(ROW()-4,"000")) | C12: =IF(B12="","",IFERROR(VLOOKUP(B12,案件管理!A:D,4,FALSE),"")) | D12: =IF(B12="","",IFERROR(VLOOKUP(B12,案件管理!A:C,3,FALSE),"")) | J12: =IF(B12="","",IF(G12="","",G12-IF(I12="",0,I12))) | K12: =IF(B12="","",IF(G12="","",IF(J12<=0,"✅入金済",IF(I12<>"","⚠一部入金",IF(F12<>"","❌未入金","")))))
A13: =IF(B13="","","INV-"&TEXT(ROW()-4,"000")) | C13: =IF(B13="","",IFERROR(VLOOKUP(B13,案件管理!A:D,4,FALSE),"")) | D13: =IF(B13="","",IFERROR(VLOOKUP(B13,案件管理!A:C,3,FALSE),"")) | J13: =IF(B13="","",IF(G13="","",G13-IF(I13="",0,I13))) | K13: =IF(B13="","",IF(G13="","",IF(J13<=0,"✅入金済",IF(I13<>"","⚠一部入金",IF(F13<>"","❌未入金","")))))
A14: =IF(B14="","","INV-"&TEXT(ROW()-4,"000")) | C14: =IF(B14="","",IFERROR(VLOOKUP(B14,案件管理!A:D,4,FALSE),"")) | D14: =IF(B14="","",IFERROR(VLOOKUP(B14,案件管理!A:C,3,FALSE),"")) | J14: =IF(B14="","",IF(G14="","",G14-IF(I14="",0,I14))) | K14: =IF(B14="","",IF(G14="","",IF(J14<=0,"✅入金済",IF(I14<>"","⚠一部入金",IF(F14<>"","❌未入金","")))))
A15: =IF(B15="","","INV-"&TEXT(ROW()-4,"000")) | C15: =IF(B15="","",IFERROR(VLOOKUP(B15,案件管理!A:D,4,FALSE),"")) | D15: =IF(B15="","",IFERROR(VLOOKUP(B15,案件管理!A:C,3,FALSE),"")) | J15: =IF(B15="","",IF(G15="","",G15-IF(I15="",0,I15))) | K15: =IF(B15="","",IF(G15="","",IF(J15<=0,"✅入金済",IF(I15<>"","⚠一部入金",IF(F15<>"","❌未入金","")))))
A16: =IF(B16="","","INV-"&TEXT(ROW()-4,"000")) | C16: =IF(B16="","",IFERROR(VLOOKUP(B16,案件管理!A:D,4,FALSE),"")) | D16: =IF(B16="","",IFERROR(VLOOKUP(B16,案件管理!A:C,3,FALSE),"")) | J16: =IF(B16="","",IF(G16="","",G16-IF(I16="",0,I16))) | K16: =IF(B16="","",IF(G16="","",IF(J16<=0,"✅入金済",IF(I16<>"","⚠一部入金",IF(F16<>"","❌未入金","")))))
A17: =IF(B17="","","INV-"&TEXT(ROW()-4,"000")) | C17: =IF(B17="","",IFERROR(VLOOKUP(B17,案件管理!A:D,4,FALSE),"")) | D17: =IF(B17="","",IFERROR(VLOOKUP(B17,案件管理!A:C,3,FALSE),"")) | J17: =IF(B17="","",IF(G17="","",G17-IF(I17="",0,I17))) | K17: =IF(B17="","",IF(G17="","",IF(J17<=0,"✅入金済",IF(I17<>"","⚠一部入金",IF(F17<>"","❌未入金","")))))
A18: =IF(B18="","","INV-"&TEXT(ROW()-4,"000")) | C18: =IF(B18="","",IFERROR(VLOOKUP(B18,案件管理!A:D,4,FALSE),"")) | D18: =IF(B18="","",IFERROR(VLOOKUP(B18,案件管理!A:C,3,FALSE),"")) | J18: =IF(B18="","",IF(G18="","",G18-IF(I18="",0,I18))) | K18: =IF(B18="","",IF(G18="","",IF(J18<=0,"✅入金済",IF(I18<>"","⚠一部入金",IF(F18<>"","❌未入金","")))))
A19: =IF(B19="","","INV-"&TEXT(ROW()-4,"000")) | C19: =IF(B19="","",IFERROR(VLOOKUP(B19,案件管理!A:D,4,FALSE),"")) | D19: =IF(B19="","",IFERROR(VLOOKUP(B19,案件管理!A:C,3,FALSE),"")) | J19: =IF(B19="","",IF(G19="","",G19-IF(I19="",0,I19))) | K19: =IF(B19="","",IF(G19="","",IF(J19<=0,"✅入金済",IF(I19<>"","⚠一部入金",IF(F19<>"","❌未入金","")))))
... A104: =IF(B104="","","INV-"&TEXT(ROW()-4,"000")) | C104: =IF(B104="","",IFERROR(VLOOKUP(B104,案件管理!A:D,4,FALSE),"")) | D104: =IF(B104="","",IFERROR(VLOOKUP(B104,案件管理!A:C,3,FALSE),"")) | J104: =IF(B104="","",IF(G104="","",G104-IF(I104="",0,I104))) | K104: =IF(B104="","",IF(G104="","",IF(J104<=0,"✅入金済",IF(I104<>"","⚠一部入金",IF(F104<>"","❌未入金","")))))

Sheet 支払管理
A1: 支払管理
A2: 株式会社LinK - 業者発注・支払管理
A3: ※ 業者への発注・支払を行単位で追跡。業者DBと自動連携。
A4: 支払ID | B4: 案件ID | C4: 業者ID | D4: 業者名 | E4: 工事内容 | F4: 発注日 | G4: 発注額 | H4: 支払日 | I4: 支払額 | J4: 残額 | K4: ステータス | L4: 支払条件 | M4: 備考
A5: =IF(B5="","","PAY-"&TEXT(ROW()-4,"000")) -> PAY-001 | B5: P-003 | C5: 1 | D5: =IF(C5="","",IFERROR(VLOOKUP(C5,業者DB!A:B,2,FALSE),"")) -> 株式会社M-Pros | E5: 解体工事（既存キッチン解体・撤去） | F5: 46030 | G5: 85000 | H5: 46060 | I5: 85000 | J5: =IF(B5="","",IF(G5="","",G5-IF(I5="",0,I5))) -> 0 | K5: =IF(B5="","",IF(G5="","",IF(J5<=0,"✅支払済",IF(I5<>"","⚠一部支払",IF(F5<>"","❌未支払",""))))) -> ✅支払済 | L5: =IF(C5="","",IFERROR(VLOOKUP(C5,業者DB!A:I,9,FALSE),"")) -> 0
A6: =IF(B6="","","PAY-"&TEXT(ROW()-4,"000")) -> PAY-002 | B6: P-003 | C6: 2 | D6: =IF(C6="","",IFERROR(VLOOKUP(C6,業者DB!A:B,2,FALSE),"")) -> 清水建装 | E6: 給排水配管工事 | F6: 46030 | G6: 120000 | H6: 46060 | I6: 120000 | J6: =IF(B6="","",IF(G6="","",G6-IF(I6="",0,I6))) -> 0 | K6: =IF(B6="","",IF(G6="","",IF(J6<=0,"✅支払済",IF(I6<>"","⚠一部支払",IF(F6<>"","❌未支払",""))))) -> ✅支払済 | L6: =IF(C6="","",IFERROR(VLOOKUP(C6,業者DB!A:I,9,FALSE),"")) -> 0
A7: =IF(B7="","","PAY-"&TEXT(ROW()-4,"000")) -> PAY-003 | B7: P-003 | C7: 4 | D7: =IF(C7="","",IFERROR(VLOOKUP(C7,業者DB!A:B,2,FALSE),"")) -> chic工房 | E7: クロス張替え・CFシート | F7: 46040 | G7: 45500 | J7: =IF(B7="","",IF(G7="","",G7-IF(I7="",0,I7))) -> 45500 | K7: =IF(B7="","",IF(G7="","",IF(J7<=0,"✅支払済",IF(I7<>"","⚠一部支払",IF(F7<>"","❌未支払",""))))) -> ❌未支払 | L7: =IF(C7="","",IFERROR(VLOOKUP(C7,業者DB!A:I,9,FALSE),"")) -> 0
A8: =IF(B8="","","PAY-"&TEXT(ROW()-4,"000")) | D8: =IF(C8="","",IFERROR(VLOOKUP(C8,業者DB!A:B,2,FALSE),"")) | J8: =IF(B8="","",IF(G8="","",G8-IF(I8="",0,I8))) | K8: =IF(B8="","",IF(G8="","",IF(J8<=0,"✅支払済",IF(I8<>"","⚠一部支払",IF(F8<>"","❌未支払",""))))) | L8: =IF(C8="","",IFERROR(VLOOKUP(C8,業者DB!A:I,9,FALSE),""))
A9: =IF(B9="","","PAY-"&TEXT(ROW()-4,"000")) | D9: =IF(C9="","",IFERROR(VLOOKUP(C9,業者DB!A:B,2,FALSE),"")) | J9: =IF(B9="","",IF(G9="","",G9-IF(I9="",0,I9))) | K9: =IF(B9="","",IF(G9="","",IF(J9<=0,"✅支払済",IF(I9<>"","⚠一部支払",IF(F9<>"","❌未支払",""))))) | L9: =IF(C9="","",IFERROR(VLOOKUP(C9,業者DB!A:I,9,FALSE),""))
A10: =IF(B10="","","PAY-"&TEXT(ROW()-4,"000")) | D10: =IF(C10="","",IFERROR(VLOOKUP(C10,業者DB!A:B,2,FALSE),"")) | J10: =IF(B10="","",IF(G10="","",G10-IF(I10="",0,I10))) | K10: =IF(B10="","",IF(G10="","",IF(J10<=0,"✅支払済",IF(I10<>"","⚠一部支払",IF(F10<>"","❌未支払",""))))) | L10: =IF(C10="","",IFERROR(VLOOKUP(C10,業者DB!A:I,9,FALSE),""))
A11: =IF(B11="","","PAY-"&TEXT(ROW()-4,"000")) | D11: =IF(C11="","",IFERROR(VLOOKUP(C11,業者DB!A:B,2,FALSE),"")) | J11: =IF(B11="","",IF(G11="","",G11-IF(I11="",0,I11))) | K11: =IF(B11="","",IF(G11="","",IF(J11<=0,"✅支払済",IF(I11<>"","⚠一部支払",IF(F11<>"","❌未支払",""))))) | L11: =IF(C11="","",IFERROR(VLOOKUP(C11,業者DB!A:I,9,FALSE),""))
A12: =IF(B12="","","PAY-"&TEXT(ROW()-4,"000")) | D12: =IF(C12="","",IFERROR(VLOOKUP(C12,業者DB!A:B,2,FALSE),"")) | J12: =IF(B12="","",IF(G12="","",G12-IF(I12="",0,I12))) | K12: =IF(B12="","",IF(G12="","",IF(J12<=0,"✅支払済",IF(I12<>"","⚠一部支払",IF(F12<>"","❌未支払",""))))) | L12: =IF(C12="","",IFERROR(VLOOKUP(C12,業者DB!A:I,9,FALSE),""))
A13: =IF(B13="","","PAY-"&TEXT(ROW()-4,"000")) | D13: =IF(C13="","",IFERROR(VLOOKUP(C13,業者DB!A:B,2,FALSE),"")) | J13: =IF(B13="","",IF(G13="","",G13-IF(I13="",0,I13))) | K13: =IF(B13="","",IF(G13="","",IF(J13<=0,"✅支払済",IF(I13<>"","⚠一部支払",IF(F13<>"","❌未支払",""))))) | L13: =IF(C13="","",IFERROR(VLOOKUP(C13,業者DB!A:I,9,FALSE),""))
A14: =IF(B14="","","PAY-"&TEXT(ROW()-4,"000")) | D14: =IF(C14="","",IFERROR(VLOOKUP(C14,業者DB!A:B,2,FALSE),"")) | J14: =IF(B14="","",IF(G14="","",G14-IF(I14="",0,I14))) | K14: =IF(B14="","",IF(G14="","",IF(J14<=0,"✅支払済",IF(I14<>"","⚠一部支払",IF(F14<>"","❌未支払",""))))) | L14: =IF(C14="","",IFERROR(VLOOKUP(C14,業者DB!A:I,9,FALSE),""))
A15: =IF(B15="","","PAY-"&TEXT(ROW()-4,"000")) | D15: =IF(C15="","",IFERROR(VLOOKUP(C15,業者DB!A:B,2,FALSE),"")) | J15: =IF(B15="","",IF(G15="","",G15-IF(I15="",0,I15))) | K15: =IF(B15="","",IF(G15="","",IF(J15<=0,"✅支払済",IF(I15<>"","⚠一部支払",IF(F15<>"","❌未支払",""))))) | L15: =IF(C15="","",IFERROR(VLOOKUP(C15,業者DB!A:I,9,FALSE),""))
A16: =IF(B16="","","PAY-"&TEXT(ROW()-4,"000")) | D16: =IF(C16="","",IFERROR(VLOOKUP(C16,業者DB!A:B,2,FALSE),"")) | J16: =IF(B16="","",IF(G16="","",G16-IF(I16="",0,I16))) | K16: =IF(B16="","",IF(G16="","",IF(J16<=0,"✅支払済",IF(I16<>"","⚠一部支払",IF(F16<>"","❌未支払",""))))) | L16: =IF(C16="","",IFERROR(VLOOKUP(C16,業者DB!A:I,9,FALSE),""))
A17: =IF(B17="","","PAY-"&TEXT(ROW()-4,"000")) | D17: =IF(C17="","",IFERROR(VLOOKUP(C17,業者DB!A:B,2,FALSE),"")) | J17: =IF(B17="","",IF(G17="","",G17-IF(I17="",0,I17))) | K17: =IF(B17="","",IF(G17="","",IF(J17<=0,"✅支払済",IF(I17<>"","⚠一部支払",IF(F17<>"","❌未支払",""))))) | L17: =IF(C17="","",IFERROR(VLOOKUP(C17,業者DB!A:I,9,FALSE),""))
A18: =IF(B18="","","PAY-"&TEXT(ROW()-4,"000")) | D18: =IF(C18="","",IFERROR(VLOOKUP(C18,業者DB!A:B,2,FALSE),"")) | J18: =IF(B18="","",IF(G18="","",G18-IF(I18="",0,I18))) | K18: =IF(B18="","",IF(G18="","",IF(J18<=0,"✅支払済",IF(I18<>"","⚠一部支払",IF(F18<>"","❌未支払",""))))) | L18: =IF(C18="","",IFERROR(VLOOKUP(C18,業者DB!A:I,9,FALSE),""))
A19: =IF(B19="","","PAY-"&TEXT(ROW()-4,"000")) | D19: =IF(C19="","",IFERROR(VLOOKUP(C19,業者DB!A:B,2,FALSE),"")) | J19: =IF(B19="","",IF(G19="","",G19-IF(I19="",0,I19))) | K19: =IF(B19="","",IF(G19="","",IF(J19<=0,"✅支払済",IF(I19<>"","⚠一部支払",IF(F19<>"","❌未支払",""))))) | L19: =IF(C19="","",IFERROR(VLOOKUP(C19,業者DB!A:I,9,FALSE),""))
... A104: =IF(B104="","","PAY-"&TEXT(ROW()-4,"000")) | D104: =IF(C104="","",IFERROR(VLOOKUP(C104,業者DB!A:B,2,FALSE),"")) | J104: =IF(B104="","",IF(G104="","",G104-IF(I104="",0,I104))) | K104: =IF(B104="","",IF(G104="","",IF(J104<=0,"✅支払済",IF(I104<>"","⚠一部支払",IF(F104<>"","❌未支払",""))))) | L104: =IF(C104="","",IFERROR(VLOOKUP(C104,業者DB!A:I,9,FALSE),""))

Sheet 工程表
A1: 工 程 表 | F1: 株式会社LinK
A2: 案件ID▶ | B2: P-003 | D2: 着工日▶ | E2: 46068 | F2: ← 着工日を入力すると日付軸が自動生成
A3: 工事名 | B3: =IFERROR(VLOOKUP(B2,案件管理!A:D,4,FALSE),"") -> 吉野様邸 キッチンリフォーム | D3: 完工予定日▶ | E3: =E2+83 -> 46151
A4: 顧客名 | B4: =IFERROR(VLOOKUP(B2,案件管理!A:D,3,FALSE),"")&" "&IFERROR(VLOOKUP(VLOOKUP(B2,案件管理!A:B,2,FALSE),顧客マスタ!A:D,4,FALSE),"様") -> 矢島不動産管理株式会社 御中 | D4: 施工場所 | E4: =操作パネル!F8 -> 東京都港区南麻布
A5: No. | B5: 工種 | C5: 施工内容 | D5: 開始日 | E5: 終了日 | F5: 日数 | G5: 第1週 | I5: 第2週 | K5: 第3週 | M5: 第4週 | O5: 第5週 | Q5: 第6週 | S5: 第7週 | U5: 第8週 | W5: 第9週 | Y5: 第10週 | AA5: 第11週 | AC5: 第12週 | AE5: 第13週 | AG5: 第14週
G6: =$E$2+0 -> 46068 | H6: =$E$2+3 -> 46071 | I6: =$E$2+6 -> 46074 | J6: =$E$2+9 -> 46077 | K6: =$E$2+12 -> 46080 | L6: =$E$2+15 -> 46083 | M6: =$E$2+18 -> 46086 | N6: =$E$2+21 -> 46089 | O6: =$E$2+24 -> 46092 | P6: =$E$2+27 -> 46095 | Q6: =$E$2+30 -> 46098 | R6: =$E$2+33 -> 46101 | S6: =$E$2+36 -> 46104 | T6: =$E$2+39 -> 46107 | U6: =$E$2+42 -> 46110 | V6: =$E$2+45 -> 46113 | W6: =$E$2+48 -> 46116 | X6: =$E$2+51 -> 46119 | Y6: =$E$2+54 -> 46122 | Z6: =$E$2+57 -> 46125 | AA6: =$E$2+60 -> 46128 | AB6: =$E$2+63 -> 46131 | AC6: =$E$2+66 -> 46134 | AD6: =$E$2+69 -> 46137 | AE6: =$E$2+72 -> 46140 | AF6: =$E$2+75 -> 46143 | AG6: =$E$2+78 -> 46146 | AH6: =$E$2+81 -> 46149
A7: =IF(B7<>"",ROW()-6,"") -> 1 | B7: 養生・仮設 | C7: 養生・仮設足場設置 | D7: 46068 | E7: 46069 | F7: =IF(AND(D7<>"",E7<>""),E7-D7+1,"") -> 2 | G7: =IF(AND($D7<>"",$E7<>""),IF(AND($E7>=G$6,$D7<=G$6+2),"■",""),"") -> ■ | H7: =IF(AND($D7<>"",$E7<>""),IF(AND($E7>=H$6,$D7<=H$6+2),"■",""),"") | I7: =IF(AND($D7<>"",$E7<>""),IF(AND($E7>=I$6,$D7<=I$6+2),"■",""),"") | J7: =IF(AND($D7<>"",$E7<>""),IF(AND($E7>=J$6,$D7<=J$6+2),"■",""),"") | K7: =IF(AND($D7<>"",$E7<>""),IF(AND($E7>=K$6,$D7<=K$6+2),"■",""),"") | L7: =IF(AND($D7<>"",$E7<>""),IF(AND($E7>=L$6,$D7<=L$6+2),"■",""),"") | M7: =IF(AND($D7<>"",$E7<>""),IF(AND($E7>=M$6,$D7<=M$6+2),"■",""),"") | N7: =IF(AND($D7<>"",$E7<>""),IF(AND($E7>=N$6,$D7<=N$6+2),"■",""),"") | ... AH7: =IF(AND($D7<>"",$E7<>""),IF(AND($E7>=AH$6,$D7<=AH$6+2),"■",""),"")
A8: =IF(B8<>"",ROW()-6,"") -> 2 | B8: 既存キッチン解体 | C8: 既存キッチン・壁面解体撤去 | D8: 46070 | E8: 46074 | F8: =IF(AND(D8<>"",E8<>""),E8-D8+1,"") -> 5 | G8: =IF(AND($D8<>"",$E8<>""),IF(AND($E8>=G$6,$D8<=G$6+2),"■",""),"") -> ■ | H8: =IF(AND($D8<>"",$E8<>""),IF(AND($E8>=H$6,$D8<=H$6+2),"■",""),"") -> ■ | I8: =IF(AND($D8<>"",$E8<>""),IF(AND($E8>=I$6,$D8<=I$6+2),"■",""),"") -> ■ | J8: =IF(AND($D8<>"",$E8<>""),IF(AND($E8>=J$6,$D8<=J$6+2),"■",""),"") | K8: =IF(AND($D8<>"",$E8<>""),IF(AND($E8>=K$6,$D8<=K$6+2),"■",""),"") | L8: =IF(AND($D8<>"",$E8<>""),IF(AND($E8>=L$6,$D8<=L$6+2),"■",""),"") | M8: =IF(AND($D8<>"",$E8<>""),IF(AND($E8>=M$6,$D8<=M$6+2),"■",""),"") | N8: =IF(AND($D8<>"",$E8<>""),IF(AND($E8>=N$6,$D8<=N$6+2),"■",""),"") | ... AH8: =IF(AND($D8<>"",$E8<>""),IF(AND($E8>=AH$6,$D8<=AH$6+2),"■",""),"")
A9: =IF(B9<>"",ROW()-6,"") -> 3 | B9: 電気配線工事 | C9: 電気配線・コンセント移設 | D9: 46075 | E9: 46081 | F9: =IF(AND(D9<>"",E9<>""),E9-D9+1,"") -> 7 | G9: =IF(AND($D9<>"",$E9<>""),IF(AND($E9>=G$6,$D9<=G$6+2),"■",""),"") | H9: =IF(AND($D9<>"",$E9<>""),IF(AND($E9>=H$6,$D9<=H$6+2),"■",""),"") | I9: =IF(AND($D9<>"",$E9<>""),IF(AND($E9>=I$6,$D9<=I$6+2),"■",""),"") -> ■ | J9: =IF(AND($D9<>"",$E9<>""),IF(AND($E9>=J$6,$D9<=J$6+2),"■",""),"") -> ■ | K9: =IF(AND($D9<>"",$E9<>""),IF(AND($E9>=K$6,$D9<=K$6+2),"■",""),"") -> ■ | L9: =IF(AND($D9<>"",$E9<>""),IF(AND($E9>=L$6,$D9<=L$6+2),"■",""),"") | M9: =IF(AND($D9<>"",$E9<>""),IF(AND($E9>=M$6,$D9<=M$6+2),"■",""),"") | N9: =IF(AND($D9<>"",$E9<>""),IF(AND($E9>=N$6,$D9<=N$6+2),"■",""),"") | ... AH9: =IF(AND($D9<>"",$E9<>""),IF(AND($E9>=AH$6,$D9<=AH$6+2),"■",""),"")
A10: =IF(B10<>"",ROW()-6,"") -> 4 | B10: 給排水配管工事 | C10: 給排水配管・接続工事 | D10: 46075 | E10: 46086 | F10: =IF(AND(D10<>"",E10<>""),E10-D10+1,"") -> 12 | G10: =IF(AND($D10<>"",$E10<>""),IF(AND($E10>=G$6,$D10<=G$6+2),"■",""),"") | H10: =IF(AND($D10<>"",$E10<>""),IF(AND($E10>=H$6,$D10<=H$6+2),"■",""),"") | I10: =IF(AND($D10<>"",$E10<>""),IF(AND($E10>=I$6,$D10<=I$6+2),"■",""),"") -> ■ | J10: =IF(AND($D10<>"",$E10<>""),IF(AND($E10>=J$6,$D10<=J$6+2),"■",""),"") -> ■ | K10: =IF(AND($D10<>"",$E10<>""),IF(AND($E10>=K$6,$D10<=K$6+2),"■",""),"") -> ■ | L10: =IF(AND($D10<>"",$E10<>""),IF(AND($E10>=L$6,$D10<=L$6+2),"■",""),"") -> ■ | M10: =IF(AND($D10<>"",$E10<>""),IF(AND($E10>=M$6,$D10<=M$6+2),"■",""),"") -> ■ | N10: =IF(AND($D10<>"",$E10<>""),IF(AND($E10>=N$6,$D10<=N$6+2),"■",""),"") | ... AH10: =IF(AND($D10<>"",$E10<>""),IF(AND($E10>=AH$6,$D10<=AH$6+2),"■",""),"")
A11: =IF(B11<>"",ROW()-6,"") -> 5 | B11: 衛生器具取付 | C11: 衛生器具仮設・本設 | D11: 46087 | E11: 46090 | F11: =IF(AND(D11<>"",E11<>""),E11-D11+1,"") -> 4 | G11: =IF(AND($D11<>"",$E11<>""),IF(AND($E11>=G$6,$D11<=G$6+2),"■",""),"") | H11: =IF(AND($D11<>"",$E11<>""),IF(AND($E11>=H$6,$D11<=H$6+2),"■",""),"") | I11: =IF(AND($D11<>"",$E11<>""),IF(AND($E11>=I$6,$D11<=I$6+2),"■",""),"") | J11: =IF(AND($D11<>"",$E11<>""),IF(AND($E11>=J$6,$D11<=J$6+2),"■",""),"") | K11: =IF(AND($D11<>"",$E11<>""),IF(AND($E11>=K$6,$D11<=K$6+2),"■",""),"") | L11: =IF(AND($D11<>"",$E11<>""),IF(AND($E11>=L$6,$D11<=L$6+2),"■",""),"") | M11: =IF(AND($D11<>"",$E11<>""),IF(AND($E11>=M$6,$D11<=M$6+2),"■",""),"") -> ■ | N11: =IF(AND($D11<>"",$E11<>""),IF(AND($E11>=N$6,$D11<=N$6+2),"■",""),"") -> ■ | ... AH11: =IF(AND($D11<>"",$E11<>""),IF(AND($E11>=AH$6,$D11<=AH$6+2),"■",""),"")
A12: =IF(B12<>"",ROW()-6,"") -> 6 | B12: キッチン搬入・設置 | C12: システムキッチン搬入・据付 | D12: 46091 | E12: 46101 | F12: =IF(AND(D12<>"",E12<>""),E12-D12+1,"") -> 11 | G12: =IF(AND($D12<>"",$E12<>""),IF(AND($E12>=G$6,$D12<=G$6+2),"■",""),"") | H12: =IF(AND($D12<>"",$E12<>""),IF(AND($E12>=H$6,$D12<=H$6+2),"■",""),"") | I12: =IF(AND($D12<>"",$E12<>""),IF(AND($E12>=I$6,$D12<=I$6+2),"■",""),"") | J12: =IF(AND($D12<>"",$E12<>""),IF(AND($E12>=J$6,$D12<=J$6+2),"■",""),"") | K12: =IF(AND($D12<>"",$E12<>""),IF(AND($E12>=K$6,$D12<=K$6+2),"■",""),"") | L12: =IF(AND($D12<>"",$E12<>""),IF(AND($E12>=L$6,$D12<=L$6+2),"■",""),"") | M12: =IF(AND($D12<>"",$E12<>""),IF(AND($E12>=M$6,$D12<=M$6+2),"■",""),"") | N12: =IF(AND($D12<>"",$E12<>""),IF(AND($E12>=N$6,$D12<=N$6+2),"■",""),"") -> ■ | ... AH12: =IF(AND($D12<>"",$E12<>""),IF(AND($E12>=AH$6,$D12<=AH$6+2),"■",""),"")
A13: =IF(B13<>"",ROW()-6,"") -> 7 | B13: 内装仕上げ | C13: 壁紙・床材仕上げ | D13: 46102 | E13: 46112 | F13: =IF(AND(D13<>"",E13<>""),E13-D13+1,"") -> 11 | G13: =IF(AND($D13<>"",$E13<>""),IF(AND($E13>=G$6,$D13<=G$6+2),"■",""),"") | H13: =IF(AND($D13<>"",$E13<>""),IF(AND($E13>=H$6,$D13<=H$6+2),"■",""),"") | I13: =IF(AND($D13<>"",$E13<>""),IF(AND($E13>=I$6,$D13<=I$6+2),"■",""),"") | J13: =IF(AND($D13<>"",$E13<>""),IF(AND($E13>=J$6,$D13<=J$6+2),"■",""),"") | K13: =IF(AND($D13<>"",$E13<>""),IF(AND($E13>=K$6,$D13<=K$6+2),"■",""),"") | L13: =IF(AND($D13<>"",$E13<>""),IF(AND($E13>=L$6,$D13<=L$6+2),"■",""),"") | M13: =IF(AND($D13<>"",$E13<>""),IF(AND($E13>=M$6,$D13<=M$6+2),"■",""),"") | N13: =IF(AND($D13<>"",$E13<>""),IF(AND($E13>=N$6,$D13<=N$6+2),"■",""),"") | ... AH13: =IF(AND($D13<>"",$E13<>""),IF(AND($E13>=AH$6,$D13<=AH$6+2),"■",""),"")
A14: =IF(B14<>"",ROW()-6,"") -> 8 | B14: 最終クリーニング | C14: 最終仕上・美装クリーニング | D14: 46113 | E14: 46117 | F14: =IF(AND(D14<>"",E14<>""),E14-D14+1,"") -> 5 | G14: =IF(AND($D14<>"",$E14<>""),IF(AND($E14>=G$6,$D14<=G$6+2),"■",""),"") | H14: =IF(AND($D14<>"",$E14<>""),IF(AND($E14>=H$6,$D14<=H$6+2),"■",""),"") | I14: =IF(AND($D14<>"",$E14<>""),IF(AND($E14>=I$6,$D14<=I$6+2),"■",""),"") | J14: =IF(AND($D14<>"",$E14<>""),IF(AND($E14>=J$6,$D14<=J$6+2),"■",""),"") | K14: =IF(AND($D14<>"",$E14<>""),IF(AND($E14>=K$6,$D14<=K$6+2),"■",""),"") | L14: =IF(AND($D14<>"",$E14<>""),IF(AND($E14>=L$6,$D14<=L$6+2),"■",""),"") | M14: =IF(AND($D14<>"",$E14<>""),IF(AND($E14>=M$6,$D14<=M$6+2),"■",""),"") | N14: =IF(AND($D14<>"",$E14<>""),IF(AND($E14>=N$6,$D14<=N$6+2),"■",""),"") | ... AH14: =IF(AND($D14<>"",$E14<>""),IF(AND($E14>=AH$6,$D14<=AH$6+2),"■",""),"")
A15: 【備考】 | B15: 塗装 | F15: =IF(AND(D15<>"",E15<>""),E15-D15+1,"") | G15: =IF(AND($D15<>"",$E15<>""),IF(AND($E15>=G$6,$D15<=G$6+2),"■",""),"") | H15: =IF(AND($D15<>"",$E15<>""),IF(AND($E15>=H$6,$D15<=H$6+2),"■",""),"") | I15: =IF(AND($D15<>"",$E15<>""),IF(AND($E15>=I$6,$D15<=I$6+2),"■",""),"") | J15: =IF(AND($D15<>"",$E15<>""),IF(AND($E15>=J$6,$D15<=J$6+2),"■",""),"") | K15: =IF(AND($D15<>"",$E15<>""),IF(AND($E15>=K$6,$D15<=K$6+2),"■",""),"") | L15: =IF(AND($D15<>"",$E15<>""),IF(AND($E15>=L$6,$D15<=L$6+2),"■",""),"") | M15: =IF(AND($D15<>"",$E15<>""),IF(AND($E15>=M$6,$D15<=M$6+2),"■",""),"") | N15: =IF(AND($D15<>"",$E15<>""),IF(AND($E15>=N$6,$D15<=N$6+2),"■",""),"") | ... AH15: =IF(AND($D15<>"",$E15<>""),IF(AND($E15>=AH$6,$D15<=AH$6+2),"■",""),"")
A16: ※天候・資材納期等により工程が変更になる場合がございます。 | B16: 内装 | F16: =IF(AND(D16<>"",E16<>""),E16-D16+1,"") | G16: =IF(AND($D16<>"",$E16<>""),IF(AND($E16>=G$6,$D16<=G$6+2),"■",""),"") | H16: =IF(AND($D16<>"",$E16<>""),IF(AND($E16>=H$6,$D16<=H$6+2),"■",""),"") | I16: =IF(AND($D16<>"",$E16<>""),IF(AND($E16>=I$6,$D16<=I$6+2),"■",""),"") | J16: =IF(AND($D16<>"",$E16<>""),IF(AND($E16>=J$6,$D16<=J$6+2),"■",""),"") | K16: =IF(AND($D16<>"",$E16<>""),IF(AND($E16>=K$6,$D16<=K$6+2),"■",""),"") | L16: =IF(AND($D16<>"",$E16<>""),IF(AND($E16>=L$6,$D16<=L$6+2),"■",""),"") | M16: =IF(AND($D16<>"",$E16<>""),IF(AND($E16>=M$6,$D16<=M$6+2),"■",""),"") | N16: =IF(AND($D16<>"",$E16<>""),IF(AND($E16>=N$6,$D16<=N$6+2),"■",""),"") | ... AH16: =IF(AND($D16<>"",$E16<>""),IF(AND($E16>=AH$6,$D16<=AH$6+2),"■",""),"")
A17: =IF(B17<>"",ROW()-6,"") -> 11 | B17: 家具 | F17: =IF(AND(D17<>"",E17<>""),E17-D17+1,"") | G17: =IF(AND($D17<>"",$E17<>""),IF(AND($E17>=G$6,$D17<=G$6+2),"■",""),"") | H17: =IF(AND($D17<>"",$E17<>""),IF(AND($E17>=H$6,$D17<=H$6+2),"■",""),"") | I17: =IF(AND($D17<>"",$E17<>""),IF(AND($E17>=I$6,$D17<=I$6+2),"■",""),"") | J17: =IF(AND($D17<>"",$E17<>""),IF(AND($E17>=J$6,$D17<=J$6+2),"■",""),"") | K17: =IF(AND($D17<>"",$E17<>""),IF(AND($E17>=K$6,$D17<=K$6+2),"■",""),"") | L17: =IF(AND($D17<>"",$E17<>""),IF(AND($E17>=L$6,$D17<=L$6+2),"■",""),"") | M17: =IF(AND($D17<>"",$E17<>""),IF(AND($E17>=M$6,$D17<=M$6+2),"■",""),"") | N17: =IF(AND($D17<>"",$E17<>""),IF(AND($E17>=N$6,$D17<=N$6+2),"■",""),"") | ... AH17: =IF(AND($D17<>"",$E17<>""),IF(AND($E17>=AH$6,$D17<=AH$6+2),"■",""),"")
A18: =IF(B18<>"",ROW()-6,"") -> 12 | B18: 建具 | F18: =IF(AND(D18<>"",E18<>""),E18-D18+1,"") | G18: =IF(AND($D18<>"",$E18<>""),IF(AND($E18>=G$6,$D18<=G$6+2),"■",""),"") | H18: =IF(AND($D18<>"",$E18<>""),IF(AND($E18>=H$6,$D18<=H$6+2),"■",""),"") | I18: =IF(AND($D18<>"",$E18<>""),IF(AND($E18>=I$6,$D18<=I$6+2),"■",""),"") | J18: =IF(AND($D18<>"",$E18<>""),IF(AND($E18>=J$6,$D18<=J$6+2),"■",""),"") | K18: =IF(AND($D18<>"",$E18<>""),IF(AND($E18>=K$6,$D18<=K$6+2),"■",""),"") | L18: =IF(AND($D18<>"",$E18<>""),IF(AND($E18>=L$6,$D18<=L$6+2),"■",""),"") | M18: =IF(AND($D18<>"",$E18<>""),IF(AND($E18>=M$6,$D18<=M$6+2),"■",""),"") | N18: =IF(AND($D18<>"",$E18<>""),IF(AND($E18>=N$6,$D18<=N$6+2),"■",""),"") | ... AH18: =IF(AND($D18<>"",$E18<>""),IF(AND($E18>=AH$6,$D18<=AH$6+2),"■",""),"")
A19: =IF(B19<>"",ROW()-6,"") -> 13 | B19: 金物 | F19: =IF(AND(D19<>"",E19<>""),E19-D19+1,"") | G19: =IF(AND($D19<>"",$E19<>""),IF(AND($E19>=G$6,$D19<=G$6+2),"■",""),"") | H19: =IF(AND($D19<>"",$E19<>""),IF(AND($E19>=H$6,$D19<=H$6+2),"■",""),"") | I19: =IF(AND($D19<>"",$E19<>""),IF(AND($E19>=I$6,$D19<=I$6+2),"■",""),"") | J19: =IF(AND($D19<>"",$E19<>""),IF(AND($E19>=J$6,$D19<=J$6+2),"■",""),"") | K19: =IF(AND($D19<>"",$E19<>""),IF(AND($E19>=K$6,$D19<=K$6+2),"■",""),"") | L19: =IF(AND($D19<>"",$E19<>""),IF(AND($E19>=L$6,$D19<=L$6+2),"■",""),"") | M19: =IF(AND($D19<>"",$E19<>""),IF(AND($E19>=M$6,$D19<=M$6+2),"■",""),"") | N19: =IF(AND($D19<>"",$E19<>""),IF(AND($E19>=N$6,$D19<=N$6+2),"■",""),"") | ... AH19: =IF(AND($D19<>"",$E19<>""),IF(AND($E19>=AH$6,$D19<=AH$6+2),"■",""),"")
A20: =IF(B20<>"",ROW()-6,"") -> 14 | B20: 電気 | F20: =IF(AND(D20<>"",E20<>""),E20-D20+1,"") | G20: =IF(AND($D20<>"",$E20<>""),IF(AND($E20>=G$6,$D20<=G$6+2),"■",""),"") | H20: =IF(AND($D20<>"",$E20<>""),IF(AND($E20>=H$6,$D20<=H$6+2),"■",""),"") | I20: =IF(AND($D20<>"",$E20<>""),IF(AND($E20>=I$6,$D20<=I$6+2),"■",""),"") | J20: =IF(AND($D20<>"",$E20<>""),IF(AND($E20>=J$6,$D20<=J$6+2),"■",""),"") | K20: =IF(AND($D20<>"",$E20<>""),IF(AND($E20>=K$6,$D20<=K$6+2),"■",""),"") | L20: =IF(AND($D20<>"",$E20<>""),IF(AND($E20>=L$6,$D20<=L$6+2),"■",""),"") | M20: =IF(AND($D20<>"",$E20<>""),IF(AND($E20>=M$6,$D20<=M$6+2),"■",""),"") | N20: =IF(AND($D20<>"",$E20<>""),IF(AND($E20>=N$6,$D20<=N$6+2),"■",""),"") | ... AH20: =IF(AND($D20<>"",$E20<>""),IF(AND($E20>=AH$6,$D20<=AH$6+2),"■",""),"")
A21: =IF(B21<>"",ROW()-6,"") -> 15 | B21: 給排水 | F21: =IF(AND(D21<>"",E21<>""),E21-D21+1,"") | G21: =IF(AND($D21<>"",$E21<>""),IF(AND($E21>=G$6,$D21<=G$6+2),"■",""),"") | H21: =IF(AND($D21<>"",$E21<>""),IF(AND($E21>=H$6,$D21<=H$6+2),"■",""),"") | I21: =IF(AND($D21<>"",$E21<>""),IF(AND($E21>=I$6,$D21<=I$6+2),"■",""),"") | J21: =IF(AND($D21<>"",$E21<>""),IF(AND($E21>=J$6,$D21<=J$6+2),"■",""),"") | K21: =IF(AND($D21<>"",$E21<>""),IF(AND($E21>=K$6,$D21<=K$6+2),"■",""),"") | L21: =IF(AND($D21<>"",$E21<>""),IF(AND($E21>=L$6,$D21<=L$6+2),"■",""),"") | M21: =IF(AND($D21<>"",$E21<>""),IF(AND($E21>=M$6,$D21<=M$6+2),"■",""),"") | N21: =IF(AND($D21<>"",$E21<>""),IF(AND($E21>=N$6,$D21<=N$6+2),"■",""),"") | ... AH21: =IF(AND($D21<>"",$E21<>""),IF(AND($E21>=AH$6,$D21<=AH$6+2),"■",""),"")
A22: =IF(B22<>"",ROW()-6,"") -> 16 | B22: 空調 | F22: =IF(AND(D22<>"",E22<>""),E22-D22+1,"") | G22: =IF(AND($D22<>"",$E22<>""),IF(AND($E22>=G$6,$D22<=G$6+2),"■",""),"") | H22: =IF(AND($D22<>"",$E22<>""),IF(AND($E22>=H$6,$D22<=H$6+2),"■",""),"") | I22: =IF(AND($D22<>"",$E22<>""),IF(AND($E22>=I$6,$D22<=I$6+2),"■",""),"") | J22: =IF(AND($D22<>"",$E22<>""),IF(AND($E22>=J$6,$D22<=J$6+2),"■",""),"") | K22: =IF(AND($D22<>"",$E22<>""),IF(AND($E22>=K$6,$D22<=K$6+2),"■",""),"") | L22: =IF(AND($D22<>"",$E22<>""),IF(AND($E22>=L$6,$D22<=L$6+2),"■",""),"") | M22: =IF(AND($D22<>"",$E22<>""),IF(AND($E22>=M$6,$D22<=M$6+2),"■",""),"") | N22: =IF(AND($D22<>"",$E22<>""),IF(AND($E22>=N$6,$D22<=N$6+2),"■",""),"") | ... AH22: =IF(AND($D22<>"",$E22<>""),IF(AND($E22>=AH$6,$D22<=AH$6+2),"■",""),"")
A23: =IF(B23<>"",ROW()-6,"") -> 17 | B23: 仕上 | F23: =IF(AND(D23<>"",E23<>""),E23-D23+1,"") | G23: =IF(AND($D23<>"",$E23<>""),IF(AND($E23>=G$6,$D23<=G$6+2),"■",""),"") | H23: =IF(AND($D23<>"",$E23<>""),IF(AND($E23>=H$6,$D23<=H$6+2),"■",""),"") | I23: =IF(AND($D23<>"",$E23<>""),IF(AND($E23>=I$6,$D23<=I$6+2),"■",""),"") | J23: =IF(AND($D23<>"",$E23<>""),IF(AND($E23>=J$6,$D23<=J$6+2),"■",""),"") | K23: =IF(AND($D23<>"",$E23<>""),IF(AND($E23>=K$6,$D23<=K$6+2),"■",""),"") | L23: =IF(AND($D23<>"",$E23<>""),IF(AND($E23>=L$6,$D23<=L$6+2),"■",""),"") | M23: =IF(AND($D23<>"",$E23<>""),IF(AND($E23>=M$6,$D23<=M$6+2),"■",""),"") | N23: =IF(AND($D23<>"",$E23<>""),IF(AND($E23>=N$6,$D23<=N$6+2),"■",""),"") | ... AH23: =IF(AND($D23<>"",$E23<>""),IF(AND($E23>=AH$6,$D23<=AH$6+2),"■",""),"")
A24: =IF(B24<>"",ROW()-6,"") -> 18 | B24: 衛生 | F24: =IF(AND(D24<>"",E24<>""),E24-D24+1,"") | G24: =IF(AND($D24<>"",$E24<>""),IF(AND($E24>=G$6,$D24<=G$6+2),"■",""),"") | H24: =IF(AND($D24<>"",$E24<>""),IF(AND($E24>=H$6,$D24<=H$6+2),"■",""),"") | I24: =IF(AND($D24<>"",$E24<>""),IF(AND($E24>=I$6,$D24<=I$6+2),"■",""),"") | J24: =IF(AND($D24<>"",$E24<>""),IF(AND($E24>=J$6,$D24<=J$6+2),"■",""),"") | K24: =IF(AND($D24<>"",$E24<>""),IF(AND($E24>=K$6,$D24<=K$6+2),"■",""),"") | L24: =IF(AND($D24<>"",$E24<>""),IF(AND($E24>=L$6,$D24<=L$6+2),"■",""),"") | M24: =IF(AND($D24<>"",$E24<>""),IF(AND($E24>=M$6,$D24<=M$6+2),"■",""),"") | N24: =IF(AND($D24<>"",$E24<>""),IF(AND($E24>=N$6,$D24<=N$6+2),"■",""),"") | ... AH24: =IF(AND($D24<>"",$E24<>""),IF(AND($E24>=AH$6,$D24<=AH$6+2),"■",""),"")
A25: =IF(B25<>"",ROW()-6,"") -> 19 | B25: ガス | F25: =IF(AND(D25<>"",E25<>""),E25-D25+1,"") | G25: =IF(AND($D25<>"",$E25<>""),IF(AND($E25>=G$6,$D25<=G$6+2),"■",""),"") | H25: =IF(AND($D25<>"",$E25<>""),IF(AND($E25>=H$6,$D25<=H$6+2),"■",""),"") | I25: =IF(AND($D25<>"",$E25<>""),IF(AND($E25>=I$6,$D25<=I$6+2),"■",""),"") | J25: =IF(AND($D25<>"",$E25<>""),IF(AND($E25>=J$6,$D25<=J$6+2),"■",""),"") | K25: =IF(AND($D25<>"",$E25<>""),IF(AND($E25>=K$6,$D25<=K$6+2),"■",""),"") | L25: =IF(AND($D25<>"",$E25<>""),IF(AND($E25>=L$6,$D25<=L$6+2),"■",""),"") | M25: =IF(AND($D25<>"",$E25<>""),IF(AND($E25>=M$6,$D25<=M$6+2),"■",""),"") | N25: =IF(AND($D25<>"",$E25<>""),IF(AND($E25>=N$6,$D25<=N$6+2),"■",""),"") | ... AH25: =IF(AND($D25<>"",$E25<>""),IF(AND($E25>=AH$6,$D25<=AH$6+2),"■",""),"")
A26: =IF(B26<>"",ROW()-6,"") -> 20 | B26: 共通 | F26: =IF(AND(D26<>"",E26<>""),E26-D26+1,"") | G26: =IF(AND($D26<>"",$E26<>""),IF(AND($E26>=G$6,$D26<=G$6+2),"■",""),"") | H26: =IF(AND($D26<>"",$E26<>""),IF(AND($E26>=H$6,$D26<=H$6+2),"■",""),"") | I26: =IF(AND($D26<>"",$E26<>""),IF(AND($E26>=I$6,$D26<=I$6+2),"■",""),"") | J26: =IF(AND($D26<>"",$E26<>""),IF(AND($E26>=J$6,$D26<=J$6+2),"■",""),"") | K26: =IF(AND($D26<>"",$E26<>""),IF(AND($E26>=K$6,$D26<=K$6+2),"■",""),"") | L26: =IF(AND($D26<>"",$E26<>""),IF(AND($E26>=L$6,$D26<=L$6+2),"■",""),"") | M26: =IF(AND($D26<>"",$E26<>""),IF(AND($E26>=M$6,$D26<=M$6+2),"■",""),"") | N26: =IF(AND($D26<>"",$E26<>""),IF(AND($E26>=N$6,$D26<=N$6+2),"■",""),"") | ... AH26: =IF(AND($D26<>"",$E26<>""),IF(AND($E26>=AH$6,$D26<=AH$6+2),"■",""),"")

Sheet 顧客マスタ
B1: 顧客マスタ
B2: 全顧客情報を一元管理。案件管理・見積書・帳票の顧客情報はここから自動取得されます。
A4: 顧客ID | B4: 区分 | C4: 会社名 / 氏名 | D4: 敷称 | E4: 担当者名 | F4: 郵便番号 | G4: 住所 | H4: 電話番号 | I4: メール | J4: 紹介元 | K4: 紹介元詳細 | L4: 累計案件数 | M4: 累計受注額 | N4: 最終取引日 | O4: ランク | P4: 登録日 | Q4: 更新日 | R4: ステータス | S4: 備考 | T4: 特記事項
A5: C-001 | B5: 法人 | C5: 矢島不動産管理株式会社 | D5: 御中 | E5: 山本店長 | G5: 東京都練馬区 | L5: 3 | M5: 4754440 | O5: A | R5: アクティブ | S5: 主力取引先。賃貸原状回復・フルリフォーム・耐震工事。末締め翌月末払い | T5: 担当: 山本店長/原田/葛原/南(経理)。2021年頃取引開始。100万円以上の大型案件多い
A6: C-002 | B6: 法人 | C6: 一建設 | D6: 御中 | L6: 0 | M6: 0 | R6: アクティブ | S6: 2025年11月取引開始。リフォーム・リノベーション。月500万円規模 | T6: 今後の主力取引先
A7: C-003 | B7: 法人 | C7: フィガロ | D7: 御中 | E7: 内堀 | L7: 0 | M7: 0 | R7: アクティブ | S7: 備品発注（リクシルGROHE、サイレントグリス等）
A8: C-004 | B8: 個人 | C8: 石澤クリーニング | D8: 様 | E8: 石澤操子 | L8: 0 | M8: 0 | R8: アクティブ | S8: 紹介案件。耐震工事+リフォーム（総額約1,500万円）
A9: C-005 | L9: =COUNTIF(案件管理!B:B,A9) -> 0 | M9: =SUMIFS(案件管理!F:F,案件管理!B:B,A9,案件管理!I:I,"⑤受注")+SUMIFS(案件管理!F:F,案件管理!B:B,A9,案件管理!I:I,"⑦完工") -> 0
A10: C-006 | L10: =COUNTIF(案件管理!B:B,A10) -> 0 | M10: =SUMIFS(案件管理!F:F,案件管理!B:B,A10,案件管理!I:I,"⑤受注")+SUMIFS(案件管理!F:F,案件管理!B:B,A10,案件管理!I:I,"⑦完工") -> 0
A11: C-007 | L11: =COUNTIF(案件管理!B:B,A11) -> 0 | M11: =SUMIFS(案件管理!F:F,案件管理!B:B,A11,案件管理!I:I,"⑤受注")+SUMIFS(案件管理!F:F,案件管理!B:B,A11,案件管理!I:I,"⑦完工") -> 0
A12: C-008 | L12: =COUNTIF(案件管理!B:B,A12) -> 0 | M12: =SUMIFS(案件管理!F:F,案件管理!B:B,A12,案件管理!I:I,"⑤受注")+SUMIFS(案件管理!F:F,案件管理!B:B,A12,案件管理!I:I,"⑦完工") -> 0
A13: C-009 | L13: =COUNTIF(案件管理!B:B,A13) -> 0 | M13: =SUMIFS(案件管理!F:F,案件管理!B:B,A13,案件管理!I:I,"⑤受注")+SUMIFS(案件管理!F:F,案件管理!B:B,A13,案件管理!I:I,"⑦完工") -> 0
A14: C-010 | L14: =COUNTIF(案件管理!B:B,A14) -> 0 | M14: =SUMIFS(案件管理!F:F,案件管理!B:B,A14,案件管理!I:I,"⑤受注")+SUMIFS(案件管理!F:F,案件管理!B:B,A14,案件管理!I:I,"⑦完工") -> 0
L15: =COUNTIF(案件管理!B:B,A15) -> 0 | M15: =SUMIFS(案件管理!F:F,案件管理!B:B,A15,案件管理!I:I,"⑤受注")+SUMIFS(案件管理!F:F,案件管理!B:B,A15,案件管理!I:I,"⑦完工") -> 0
L16: =COUNTIF(案件管理!B:B,A16) -> 0 | M16: =SUMIFS(案件管理!F:F,案件管理!B:B,A16,案件管理!I:I,"⑤受注")+SUMIFS(案件管理!F:F,案件管理!B:B,A16,案件管理!I:I,"⑦完工") -> 0
L17: =COUNTIF(案件管理!B:B,A17) -> 0 | M17: =SUMIFS(案件管理!F:F,案件管理!B:B,A17,案件管理!I:I,"⑤受注")+SUMIFS(案件管理!F:F,案件管理!B:B,A17,案件管理!I:I,"⑦完工") -> 0
L18: =COUNTIF(案件管理!B:B,A18) -> 0 | M18: =SUMIFS(案件管理!F:F,案件管理!B:B,A18,案件管理!I:I,"⑤受注")+SUMIFS(案件管理!F:F,案件管理!B:B,A18,案件管理!I:I,"⑦完工") -> 0
L19: =COUNTIF(案件管理!B:B,A19) -> 0 | M19: =SUMIFS(案件管理!F:F,案件管理!B:B,A19,案件管理!I:I,"⑤受注")+SUMIFS(案件管理!F:F,案件管理!B:B,A19,案件管理!I:I,"⑦完工") -> 0
L20: =COUNTIF(案件管理!B:B,A20) -> 0 | M20: =SUMIFS(案件管理!F:F,案件管理!B:B,A20,案件管理!I:I,"⑤受注")+SUMIFS(案件管理!F:F,案件管理!B:B,A20,案件管理!I:I,"⑦完工") -> 0
L21: =COUNTIF(案件管理!B:B,A21) -> 0 | M21: =SUMIFS(案件管理!F:F,案件管理!B:B,A21,案件管理!I:I,"⑤受注")+SUMIFS(案件管理!F:F,案件管理!B:B,A21,案件管理!I:I,"⑦完工") -> 0
L22: =COUNTIF(案件管理!B:B,A22) -> 0 | M22: =SUMIFS(案件管理!F:F,案件管理!B:B,A22,案件管理!I:I,"⑤受注")+SUMIFS(案件管理!F:F,案件管理!B:B,A22,案件管理!I:I,"⑦完工") -> 0
L23: =COUNTIF(案件管理!B:B,A23) -> 0 | M23: =SUMIFS(案件管理!F:F,案件管理!B:B,A23,案件管理!I:I,"⑤受注")+SUMIFS(案件管理!F:F,案件管理!B:B,A23,案件管理!I:I,"⑦完工") -> 0
L24: =COUNTIF(案件管理!B:B,A24) -> 0 | M24: =SUMIFS(案件管理!F:F,案件管理!B:B,A24,案件管理!I:I,"⑤受注")+SUMIFS(案件管理!F:F,案件管理!B:B,A24,案件管理!I:I,"⑦完工") -> 0
L25: =COUNTIF(案件管理!B:B,A25) -> 0 | M25: =SUMIFS(案件管理!F:F,案件管理!B:B,A25,案件管理!I:I,"⑤受注")+SUMIFS(案件管理!F:F,案件管理!B:B,A25,案件管理!I:I,"⑦完工") -> 0
L26: =COUNTIF(案件管理!B:B,A26) -> 0 | M26: =SUMIFS(案件管理!F:F,案件管理!B:B,A26,案件管理!I:I,"⑤受注")+SUMIFS(案件管理!F:F,案件管理!B:B,A26,案件管理!I:I,"⑦完工") -> 0
... L104: =COUNTIF(案件管理!B:B,A104) -> 0 | M104: =SUMIFS(案件管理!F:F,案件管理!B:B,A104,案件管理!I:I,"⑤受注")+SUMIFS(案件管理!F:F,案件管理!B:B,A104,案件管理!I:I,"⑦完工") -> 0

Sheet マスター設定
B2: マスター設定 | H2: 【ロゴ配置エリア】
B3: 見積作成ソフト ver.1.0
B6: ■ 会社情報（固定） | J6: ■ 担当者リスト
B7: 会社名 | C7: 株式会社ＬｉｎＫ | I7: No. | J7: 担当者名 | K7: メールアドレス | L7: 電話番号 | M7: 役職 | N7: 備考
B8: 郵便番号 | C8: 134-0081 | I8: 1 | J8: 吉野博 | K8: info@link-8.jp | L8: 03-6825-2464
B9: 住所 | C9: 東京都江戸川区北葛西1-2-22 | I9: 2
B10: 電話番号 | C10: 03-6825-2464 | I10: 3
B11: メール | C11: info@link-8.jp | I11: 4
B12: 代表者名 | C12: 吉野博 | I12: 5
I13: 6
I14: 7
I15: 8
I16: 9
I17: 10
B19: ■ 案件情報（案件ごとに入力） | J19: ■ 経費・税設定（デフォルト値変更可）
B20: 案件名（工事名） | J20: 会社経費率 | K20: 0.1 | L20: ← 変更可
B21: 顧客名 | E21: 様 | J21: 現場経費率 | K21: 0.05 | L21: ← 変更可
B22: 施工場所 | J22: 現場管理費単価 | K22: 25000 | L22: /人工
B23: 施工住所 | J23: 現場管理人工数 | K23: 5 | L23: 人工
B24: 担当者 | E24: ◀ セレクト | J24: 消費税率 | K24: 0.1
B25: メール | C25: =IFERROR(VLOOKUP(C24,I8:K17,2,FALSE),"") | E25: ◀ 担当者連動
B26: 見積日 | J26: ■ 自動採番
B27: 有効期間 | C27: 30日間 | J27: 現在の案件数 | K27: =COUNTA(案件管理!I5:I96) -> 3
B28: 別途工事 | C28: 見積記載無き項目 | J28: 次の案件ID | K28: ="P-"&TEXT(COUNTA(案件管理!I5:I96)+1,"000") -> P-004
B29: 工事期間 | D29: ～
B30: 備考
B33: ■ 工事カテゴリ選択（使用する工事に☑を入力）
B34: No. | C34: 選択 | D34: 工事カテゴリ名 | E34: シート名 | F34: 小計金額 | G34: 状態
B35: 1 | C35: ☑ | D35: 解体工事 | E35: （旧）解体工事 | F35: 98000 | G35: ✔使用中
B36: 2 | C36: ☐ | D36: 造作工事 | E36: （旧）産廃費 | F36: 0
B37: 3 | C37: ☐ | D37: 建具工事 | E37: （旧）仮設 | F37: 0
B38: 4 | C38: ☐ | D38: 家具工事 | E38: （旧）解体後補修箇所 | F38: 0
B39: 5 | C39: ☐ | D39: 電気設備 | E39: （旧）新規壁工事 | F39: 0
B40: 6 | C40: ☑ | D40: タイル左官工事 | E40: （旧）造作工事 | F40: 188000 | G40: ✔使用中
B41: 7 | C41: ☐ | D41: 仕上げ工事 | E41: （旧）下地工事 | F41: 0
B42: 8 | C42: ☑ | D42: 衛生設備 | E42: （旧）建具工事 | F42: 1264120 | G42: ✔使用中
B43: 9 | C43: ☑ | D43: 共通 | E43: （旧）家具 | F43: 3013690 | G43: ✔使用中
B44: 10 | C44: ☐ | D44: 下地工事 | E44: （旧）床 | F44: 0
B45: 11 | C45: ☑ | D45: 新規壁工事 | E45: （旧）電気設備' | F45: 243500 | G45: ✔使用中
B46: 12 | C46: ☐ | D46: 床 | E46: （旧）空調 | F46: 0
B47: 13 | C47: ☑ | D47: 空調 | E47: （旧）タイル左官工事 | F47: 423500 | G47: ✔使用中
B48: 14 | C48: ☐ | D48: シート工事 | E48: （旧）雑工事 | F48: 0
B49: 15 | C49: ☐ | D49: 塗装工事 | E49: （旧）シート工事 | F49: 0
B50: 16 | C50: ☑ | D50: 雑工事 | E50: （旧）仕上げ工事 | F50: 65000 | G50: ✔使用中
B51: 17 | C51: ☐ | D51: 防災工事 | E51: （旧）衛生設備 | F51: 0
B52: 18 | C52: ☐ | D52: ガス工事 | E52: （旧）塗装工事 | F52: 0
B53: 19 | C53: ☐ | D53: 産廃費 | E53: （旧）防災工事 | F53: 0
B54: 20 | C54: ☐ | D54: 仮設工事 | E54: （旧）ガス工事 | F54: 0

Sheet 工事項目DB
B1: 工事項目データベース
B2: 過去の工事項目・単価・仕様を蓄積し、次回見積で再利用できます。
A4: ID | B4: 工事カテゴリ | C4: 品名（小項目） | D4: 仕様・形状 | E4: 単位 | F4: 標準単価 | G4: 業者名 | H4: 最終使用日 | I4: 利益率 | J4: 使用回数 | K4: 案件名 | L4: 検索キー（自動） | M4: 登録日
A5: 1 | B5: 解体工事 | C5: 発生材処理費 | D5: 混載 | E5: ㎥ | F5: 20000 | H5: 45759 | J5: 1 | K5: 南麻布レジデンス | L5: =IF(A5<>"",B5&"|"&C5,"") -> 解体工事|発生材処理費 | M5: 45759
A6: 2 | B6: 解体工事 | C6: トラック | E6: 台 | F6: 18000 | H6: 45759 | J6: 1 | K6: 南麻布レジデンス | L6: =IF(A6<>"",B6&"|"&C6,"") -> 解体工事|トラック | M6: 45759
A7: 3 | B7: 解体工事 | C7: 運搬費 | E7: 人工 | F7: 20000 | H7: 45759 | J7: 1 | K7: 南麻布レジデンス | L7: =IF(A7<>"",B7&"|"&C7,"") -> 解体工事|運搬費 | M7: 45759
A8: 4 | B8: 造作工事 | C8: 階段室下 シナベニヤ t12 材料費 | E8: 枚 | F8: 11000 | H8: 45759 | J8: 1 | K8: 南麻布レジデンス | L8: =IF(A8<>"",B8&"|"&C8,"") -> 造作工事|階段室下 シナベニヤ t12 材料費 | M8: 45759
A9: 5 | B9: 造作工事 | C9: 階段室下 間接照明隠蔽用 モクヒモ材 | E9: 本 | F9: 15000 | H9: 45759 | J9: 1 | K9: 南麻布レジデンス | L9: =IF(A9<>"",B9&"|"&C9,"") -> 造作工事|階段室下 間接照明隠蔽用 モクヒモ材 | M9: 45759
A10: 6 | B10: 造作工事 | C10: シナベニヤ ダボ掘り込み 取付 | E10: 式 | F10: 25000 | H10: 45759 | J10: 1 | K10: 南麻布レジデンス | L10: =IF(A10<>"",B10&"|"&C10,"") -> 造作工事|シナベニヤ ダボ掘り込み 取付 | M10: 45759
A11: 7 | B11: 造作工事 | C11: 折り上げ天井部 ナラ突板 | D11: 2m | E11: 本 | F11: 18500 | H11: 45759 | J11: 1 | K11: 南麻布レジデンス | L11: =IF(A11<>"",B11&"|"&C11,"") -> 造作工事|折り上げ天井部 ナラ突板 | M11: 45759
A12: 8 | B12: 造作工事 | C12: 労務費 | E12: 人工 | F12: 30000 | H12: 45759 | J12: 1 | K12: 南麻布レジデンス | L12: =IF(A12<>"",B12&"|"&C12,"") -> 造作工事|労務費 | M12: 45759
A13: 9 | B13: 建具工事 | C13: 1F-2F踊り場 障子 | D13: 797*474 金物含む | E13: 枚 | F13: 96520 | H13: 45759 | J13: 1 | K13: 南麻布レジデンス | L13: =IF(A13<>"",B13&"|"&C13,"") -> 建具工事|1F-2F踊り場 障子 | M13: 45759
A14: 10 | B14: 建具工事 | C14: 2F廊下 障子 | D14: 500*572 金物含む | E14: 枚 | F14: 94500 | H14: 45759 | J14: 1 | K14: 南麻布レジデンス | L14: =IF(A14<>"",B14&"|"&C14,"") -> 建具工事|2F廊下 障子 | M14: 45759
A15: 11 | B15: 建具工事 | C15: 2F廊下+2Fキッチン部分 障子 | D15: 2064*575 金物含む | E15: 枚 | F15: 166500 | H15: 45759 | J15: 1 | K15: 南麻布レジデンス | L15: =IF(A15<>"",B15&"|"&C15,"") -> 建具工事|2F廊下+2Fキッチン部分 障子 | M15: 45759
A16: 12 | B16: 建具工事 | C16: WD2 新規建具 ナラ突板 | D16: 2121*667*36 金物取手枠込 | E16: 組 | F16: 200000 | H16: 45759 | J16: 1 | K16: 南麻布レジデンス | L16: =IF(A16<>"",B16&"|"&C16,"") -> 建具工事|WD2 新規建具 ナラ突板 | M16: 45759
A17: 13 | B17: 建具工事 | C17: WD3 新規引き戸 塗装仕上げ | D17: 2178*650*36 金物取手含む | E17: 組 | F17: 180000 | H17: 45759 | J17: 1 | K17: 南麻布レジデンス | L17: =IF(A17<>"",B17&"|"&C17,"") -> 建具工事|WD3 新規引き戸 塗装仕上げ | M17: 45759
A18: 14 | B18: 建具工事 | C18: 運搬費 | D18: 新規建具３回 | E18: 式 | F18: 85000 | H18: 45759 | J18: 1 | K18: 南麻布レジデンス | L18: =IF(A18<>"",B18&"|"&C18,"") -> 建具工事|運搬費 | M18: 45759
A19: 15 | B19: 建具工事 | C19: 副資材 | E19: 式 | F19: 15200 | H19: 45759 | J19: 1 | K19: 南麻布レジデンス | L19: =IF(A19<>"",B19&"|"&C19,"") -> 建具工事|副資材 | M19: 45759
A20: 16 | B20: 家具工事 | C20: 収納内部 引き出し付き什器 | D20: スライドレール取手金物込 | E20: 台 | F20: 248500 | H20: 45759 | J20: 1 | K20: 南麻布レジデンス | L20: =IF(A20<>"",B20&"|"&C20,"") -> 家具工事|収納内部 引き出し付き什器 | M20: 45759
A21: 17 | B21: 家具工事 | C21: ドロワー 本体代 | E21: 台 | F21: 224850 | H21: 45759 | J21: 1 | K21: 南麻布レジデンス | L21: =IF(A21<>"",B21&"|"&C21,"") -> 家具工事|ドロワー 本体代 | M21: 45759
A22: 18 | B22: 家具工事 | C22: 大型障子 本体代 ワーロン | D22: 1800*1500x2 金物込 | E22: 組 | F22: 466500 | H22: 45759 | J22: 1 | K22: 南麻布レジデンス | L22: =IF(A22<>"",B22&"|"&C22,"") -> 家具工事|大型障子 本体代 ワーロン | M22: 45759
A23: 19 | B23: 家具工事 | C23: ベッド土台 ヘッドパネル | D23: ナラ突板 マットレス下脱着式 | E23: 組 | F23: 178560 | H23: 45759 | J23: 1 | K23: 南麻布レジデンス | L23: =IF(A23<>"",B23&"|"&C23,"") -> 家具工事|ベッド土台 ヘッドパネル | M23: 45759
A24: 20 | B24: 家具工事 | C24: サイドボード ナラ突板 | D24: 照明コンセントスイッチ支給 | E24: 台 | F24: 78660 | H24: 45759 | J24: 1 | K24: 南麻布レジデンス | L24: =IF(A24<>"",B24&"|"&C24,"") -> 家具工事|サイドボード ナラ突板 | M24: 45759
A25: 21 | B25: 家具工事 | C25: 洗面台 ドレッサー コーリアン | E25: 枚 | F25: 56000 | H25: 45759 | J25: 1 | K25: 南麻布レジデンス | L25: =IF(A25<>"",B25&"|"&C25,"") -> 家具工事|洗面台 ドレッサー コーリアン | M25: 45759
A26: 22 | B26: タイル左官工事 | C26: 浴槽タイルまし張り 壁床 | D26: 大判タイル 材料支給 | E26: 人工 | F26: 30000 | H26: 45759 | J26: 1 | K26: 南麻布レジデンス | L26: =IF(A26<>"",B26&"|"&C26,"") -> タイル左官工事|浴槽タイルまし張り 壁床 | M26: 45759
A27: 23 | B27: タイル左官工事 | C27: 目地 材工共 | E27: 式 | F27: 65000 | H27: 45759 | J27: 1 | K27: 南麻布レジデンス | L27: =IF(A27<>"",B27&"|"&C27,"") -> タイル左官工事|目地 材工共 | M27: 45759
A28: 24 | B28: タイル左官工事 | C28: 水回り コーキング | D28: 材工共 | E28: 式 | F28: 55000 | H28: 45759 | J28: 1 | K28: 南麻布レジデンス | L28: =IF(A28<>"",B28&"|"&C28,"") -> タイル左官工事|水回り コーキング | M28: 45759
A29: 25 | B29: タイル左官工事 | C29: 既存ブロック塀 左官材工共 | D29: Magic coat flex クラウド仕上色 | E29: 式 | F29: 100000 | H29: 45759 | J29: 1 | K29: 南麻布レジデンス | L29: =IF(A29<>"",B29&"|"&C29,"") -> タイル左官工事|既存ブロック塀 左官材工共 | M29: 45759
A30: 26 | B30: 仕上げ工事 | C30: 階段下 新規ベニヤ貼り後 塗装 | D30: 材工共 | E30: 式 | F30: 65000 | H30: 45759 | J30: 1 | K30: 南麻布レジデンス | L30: =IF(A30<>"",B30&"|"&C30,"") -> 仕上げ工事|階段下 新規ベニヤ貼り後 塗装 | M30: 45759
A31: 27 | B31: 共通 | C31: 搬入費 | E31: 式 | F31: 25000 | H31: 45759 | J31: 1 | K31: 南麻布レジデンス | L31: =IF(A31<>"",B31&"|"&C31,"") -> 共通|搬入費 | M31: 45759
A32: 28 | B32: 共通 | C32: 副資材 | E32: 式 | F32: 15200 | H32: 45759 | J32: 1 | K32: 南麻布レジデンス | L32: =IF(A32<>"",B32&"|"&C32,"") -> 共通|副資材 | M32: 45759
A33: 29 | B33: 共通 | C33: 発生材処理費 | E33: 式 | F33: 6850 | H33: 45759 | J33: 1 | K33: 南麻布レジデンス | L33: =IF(A33<>"",B33&"|"&C33,"") -> 共通|発生材処理費 | M33: 45759
A34: 30 | B34: 共通 | C34: 運搬費 | D34: 4t 2回分 | E34: 式 | F34: 100000 | H34: 45759 | J34: 1 | K34: 南麻布レジデンス | L34: =IF(A34<>"",B34&"|"&C34,"") -> 共通|運搬費 | M34: 45759
A35: 31 | B35: 共通 | C35: 労務費（取付・現場加工） | E35: 人工 | F35: 30000 | H35: 45759 | J35: 1 | K35: 南麻布レジデンス | L35: =IF(A35<>"",B35&"|"&C35,"") -> 共通|労務費（取付・現場加工） | M35: 45759
A36: 32 | B36: 共通 | C36: 資材運搬搬入費 | E36: 式 | F36: 18000 | H36: 45759 | J36: 1 | K36: 南麻布レジデンス | L36: =IF(A36<>"",B36&"|"&C36,"") -> 共通|資材運搬搬入費 | M36: 45759
A37: 33 | B37: 解体工事 | C37: 既存キッチン解体・撤去 | D37: 材工共 | E37: 式 | F37: 85000 | H37: =TODAY() -> 46070 | J37: 1 | K37: P-003 吉野様邸 キッチンリフォーム | L37: =IF(A37<>"",B37&"|"&C37,"") -> 解体工事|既存キッチン解体・撤去 | M37: =TODAY() -> 46070
A38: 34 | B38: 衛生設備 | C38: 給排水配管工事 | D38: 材工共 | E38: 式 | F38: 120000 | H38: =TODAY() -> 46070 | I38: 0.25 | J38: 1 | K38: P-003 吉野様邸 キッチンリフォーム | L38: =IF(A38<>"",B38&"|"&C38,"") -> 衛生設備|給排水配管工事 | M38: =TODAY() -> 46070
A39: 35 | B39: 家具工事 | C39: LIXIL システムキッチン シエラS | D39: W2550 IH・食洗機付 | E39: 台 | F39: 420000 | H39: =TODAY() -> 46070 | I39: 0.25 | J39: 1 | K39: P-003 吉野様邸 キッチンリフォーム | L39: =IF(A39<>"",B39&"|"&C39,"") -> 家具工事|LIXIL システムキッチン シエラS | M39: =TODAY() -> 46070
A40: 36 | B40: 仕上げ工事 | C40: クロス張替え | D40: 量産クロス SP級 | E40: ㎡ | F40: 650 | H40: =TODAY() -> 46070 | I40: 0.38235294 | J40: 1 | K40: P-003 吉野様邸 キッチンリフォーム | L40: =IF(A40<>"",B40&"|"&C40,"") -> 仕上げ工事|クロス張替え | M40: =TODAY() -> 46070
A41: 37 | B41: 仕上げ工事 | C41: CFシート張替え | D41: サンゲツ HM-10108 | E41: ㎡ | F41: 800 | H41: =TODAY() -> 46070 | I41: 0.40909091 | J41: 1 | K41: P-003 吉野様邸 キッチンリフォーム | L41: =IF(A41<>"",B41&"|"&C41,"") -> 仕上げ工事|CFシート張替え | M41: =TODAY() -> 46070
A42: 38 | B42: 電気設備 | C42: コンセント増設・照明移設 | D42: 材工共 | E42: 式 | F42: 65000 | H42: =TODAY() -> 46070 | I42: 0.55555556 | J42: 1 | K42: P-003 吉野様邸 キッチンリフォーム | L42: =IF(A42<>"",B42&"|"&C42,"") -> 電気設備|コンセント増設・照明移設 | M42: =TODAY() -> 46070
A43: 39 | B43: 共通 | C43: 産廃処理費 | D43: 混載 | E43: ㎥ | F43: 18000 | H43: =TODAY() -> 46070 | I43: 0.25 | J43: 1 | K43: P-003 吉野様邸 キッチンリフォーム | L43: =IF(A43<>"",B43&"|"&C43,"") -> 共通|産廃処理費 | M43: =TODAY() -> 46070
I44: 0.25 | L44: =IF(A44<>"",B44&"|"&C44,"")
L45: =IF(A45<>"",B45&"|"&C45,"")
L46: =IF(A46<>"",B46&"|"&C46,"")
L47: =IF(A47<>"",B47&"|"&C47,"")
L48: =IF(A48<>"",B48&"|"&C48,"")
L49: =IF(A49<>"",B49&"|"&C49,"")
L50: =IF(A50<>"",B50&"|"&C50,"")
A74: 70 | B74: 家具工事 | C74: 名称形状 | E74: 単位 | F74: 0 | H74: 45759 | J74: 1 | K74: 南麻布レジデンス | L74: 家具工事|名称形状 | M74: 45759
A75: 71 | B75: 家具工事 | C75: ベッドフレーム土台（6分割パネル下） | E75: 組 | F75: 65000 | H75: 45759 | J75: 1 | K75: 南麻布レジデンス | L75: 家具工事|ベッドフレーム土台（6分割パネル下） | M75: 45759
A76: 72 | B76: 家具工事 | C76: ベッドフレーム 幕板 ナラ突板 | D76: 150*2200*20 | E76: 本 | F76: 28500 | H76: 45759 | J76: 1 | K76: 南麻布レジデンス | L76: 家具工事|ベッドフレーム 幕板 ナラ突板 | M76: 45759
A77: 73 | B77: 家具工事 | C77: ヘッドボード ナラ突板 | D77: 1000*2375*100 | E77: 組 | F77: 76500 | H77: 45759 | J77: 1 | K77: 南麻布レジデンス | L77: 家具工事|ヘッドボード ナラ突板 | M77: 45759
A78: 74 | B78: 家具工事 | C78: アクリル板 | D78: 158*3*2375 | E78: 枚 | F78: 10000 | H78: 45759 | J78: 1 | K78: 南麻布レジデンス | L78: 家具工事|アクリル板 | M78: 45759
A79: 75 | B79: 家具工事 | C79: 洗面台 ドレッサー コーリアン | E79: 枚 | F79: 56000 | H79: 45759 | J79: 1 | K79: 南麻布レジデンス | L79: 家具工事|洗面台 ドレッサー コーリアン | M79: 45759
A80: 76 | B80: 家具工事 | C80: 洗面台 ドレッサー 本体代 | D80: 925*550*600 | E80: 台 | F80: 135000 | H80: 45759 | J80: 1 | K80: 南麻布レジデンス | L80: 家具工事|洗面台 ドレッサー 本体代 | M80: 45759
A81: 77 | B81: 家具工事 | C81: 洗面ボウル | E81: 台 | F81: 69000 | H81: 45759 | J81: 1 | K81: 南麻布レジデンス | L81: 家具工事|洗面ボウル | M81: 45759
A82: 78 | B82: 家具工事 | C82: 排水 給水 金物 | E82: 式 | F82: 20000 | H82: 45759 | J82: 1 | K82: 南麻布レジデンス | L82: 家具工事|排水 給水 金物 | M82: 45759
A83: 79 | B83: 家具工事 | C83: 水栓 | E83: 台 | F83: 46500 | H83: 45759 | J83: 1 | K83: 南麻布レジデンス | L83: 家具工事|水栓 | M83: 45759
A84: 80 | B84: 家具工事 | C84: 姿見収納 本体代 | D84: 600*800*137 | E84: 台 | F84: 150000 | H84: 45759 | J84: 1 | K84: 南麻布レジデンス | L84: 家具工事|姿見収納 本体代 | M84: 45759
A85: 81 | B85: 家具工事 | C85: 取付 現場加工費 | E85: 人工 | F85: 30000 | H85: 45759 | J85: 1 | K85: 南麻布レジデンス | L85: 家具工事|取付 現場加工費 | M85: 45759
A86: 82 | B86: 家具工事 | C86: 水回り繋ぎ込み 既存給排水管 切り回し タイル前脱着 | E86: 人工 | F86: 35000 | H86: 45759 | J86: 1 | K86: 南麻布レジデンス | L86: 家具工事|水回り繋ぎ込み 既存給排水管 切り回し タイル前脱着 | M86: 45759
A87: 83 | B87: 家具工事 | C87: 副資材 発生材処理費 | E87: 式 | F87: 11200 | H87: 45759 | J87: 1 | K87: 南麻布レジデンス | L87: 家具工事|副資材 発生材処理費 | M87: 45759
A88: 84 | B88: 家具工事 | C88: 搬入費 | E88: 人工 | F88: 24000 | H88: 45759 | J88: 1 | K88: 南麻布レジデンス | L88: 家具工事|搬入費 | M88: 45759
A89: 85 | B89: 家具工事 | C89: 運搬費 | D89: 4ｔ 2回分 | E89: 式 | F89: 100000 | H89: 45759 | J89: 1 | K89: 南麻布レジデンス | L89: 家具工事|運搬費 | M89: 45759
A90: 86 | B90: 電気設備 | C90: 階段下収納 間接照明 本体代 | E90: 本 | F90: 26500 | H90: 45759 | J90: 1 | K90: 南麻布レジデンス | L90: 電気設備|階段下収納 間接照明 本体代 | M90: 45759
A91: 87 | B91: 電気設備 | C91: ベッドヘッド 間接照明 本体代 | E91: 本 | F91: 26500 | H91: 45759 | J91: 1 | K91: 南麻布レジデンス | L91: 電気設備|ベッドヘッド 間接照明 本体代 | M91: 45759
A92: 88 | B92: 電気設備 | C92: 障子後ろ 間接照明 本体代 | E92: 本 | F92: 26500 | H92: 45759 | J92: 1 | K92: 南麻布レジデンス | L92: 電気設備|障子後ろ 間接照明 本体代 | M92: 45759
A93: 89 | B93: 電気設備 | C93: コンセント 本体代 | E93: 台 | F93: 2500 | H93: 45759 | J93: 1 | K93: 南麻布レジデンス | L93: 電気設備|コンセント 本体代 | M93: 45759
A94: 90 | B94: 電気設備 | C94: 折り上げ天井 間接照明 本体代 | E94: 本 | F94: 26500 | H94: 45759 | J94: 1 | K94: 南麻布レジデンス | L94: 電気設備|折り上げ天井 間接照明 本体代 | M94: 45759
A95: 91 | B95: タイル左官工事 | C95: 浴槽タイルまし張り 壁床 | D95: 大判タイル 材料支給 | E95: 人工 | F95: 30000 | H95: 45759 | J95: 1 | K95: 南麻布レジデンス | L95: タイル左官工事|浴槽タイルまし張り 壁床 | M95: 45759
A96: 92 | B96: タイル左官工事 | C96: 目地 材工共 | E96: 式 | F96: 65000 | H96: 45759 | J96: 1 | K96: 南麻布レジデンス | L96: タイル左官工事|目地 材工共 | M96: 45759
A97: 93 | B97: タイル左官工事 | C97: 糊 | E97: 式 | F97: 15000 | H97: 45759 | J97: 1 | K97: 南麻布レジデンス | L97: タイル左官工事|糊 | M97: 45759
A98: 94 | B98: タイル左官工事 | C98: 副資材 | E98: 式 | F98: 8500 | H98: 45759 | J98: 1 | K98: 南麻布レジデンス | L98: タイル左官工事|副資材 | M98: 45759
A99: 95 | B99: タイル左官工事 | C99: 水回り コーキング | D99: 材工共 | E99: 式 | F99: 55000 | H99: 45759 | J99: 1 | K99: 南麻布レジデンス | L99: タイル左官工事|水回り コーキング | M99: 45759
A100: 96 | B100: タイル左官工事 | C100: 既存ブロック塀 左官材工共 | D100: Magic coat flex クラウド仕上色 21-80B | E100: 式 | F100: 100000 | H100: 45759 | J100: 1 | K100: 南麻布レジデンス | L100: タイル左官工事|既存ブロック塀 左官材工共 | M100: 45759
A101: 97 | B101: 仕上げ工事 | C101: 階段下 新規ベニヤ貼り後 塗装 | D101: 材工共 | E101: 式 | F101: 65000 | H101: 45759 | J101: 1 | K101: 南麻布レジデンス | L101: 仕上げ工事|階段下 新規ベニヤ貼り後 塗装 | M101: 45759

Sheet 業者DB
B1: 業者データベース
B2: 協力業者の情報を管理し、注文書・請書の宛先自動入力に使用します。
A4: ID | B4: 業者名 | C4: 代表者名 | D4: 郵便番号 | E4: 住所 | F4: 電話番号 | G4: メール | H4: 得意工事 | I4: 支払条件 | J4: 備考
A5: 1 | B5: 株式会社M-Pros | J5: 発注実績: 7,180,531円/8件
A6: 2 | B6: 清水建装 | J6: 発注実績: 6,527,800円/28件
A7: 3 | B7: 株式会社 秀英 | J7: 発注実績: 5,308,181円/3件
A8: 4 | B8: chic工房 | H8: 内装（クロス・CF） | J8: 発注実績: 4,720,176円/58件
A9: 5 | B9: GROW UP 株式会社 | H9: 多能工系 | J9: 発注実績: 3,939,615円/75件
A10: 6 | B10: HLD株式会社 | J10: 発注実績: 3,584,637円/6件
A11: 7 | B11: 合同会社HK | J11: 発注実績: 3,085,559円/5件
A12: 8 | B12: 東京ライフワークス | H12: 内装系 | J12: 発注実績: 2,562,200円/43件
A13: 9 | B13: インテリアフジイ | H13: 内装 | J13: 発注実績: 2,371,413円/36件
A14: 10 | B14: 株式会社ワタナベ | H14: 外注（多業種） | J14: 外注。発注実績: 2,188,342円/30件
A15: 11 | B15: エムデン | J15: 発注実績: 1,724,908円/33件
A16: 12 | B16: 建辰工業 | J16: 発注実績: 1,379,060円/11件
A17: 13 | B17: 株式会社エヌ・アイ・シー | J17: 発注実績: 1,190,540円/10件
A18: 14 | B18: 株式会社Marshall | J18: 発注実績: 1,173,879円/3件
A19: 15 | B19: 有限会社菊池ガラス建材 | J19: 発注実績: 973,196円/17件
A20: 16 | B20: 株式会社ワタナベ（仕入） | H20: 建材問屋 | J20: 仕入先。発注実績: 5,580,202円/128件
A21: 17 | B21: 渡辺パイプ株式会社 | H21: 配管・住設資材 | J21: 仕入先。発注実績: 5,037,847円/58件
A22: 18 | B22: 株式会社角産 | H22: 建材問屋 | J22: 仕入先。発注実績: 3,475,273円/47件
A23: 19 | B23: 丸和住宅資材株式会社 | J23: 仕入先。発注実績: 446,380円/13件
A24: 20 | B24: 株式会社キツタカ | H24: 畳・襖・障子・網戸 | J24: 外注+仕入。外注: 757,180円/22件、仕入: 38,900円/2件

Sheet 案件テンプレート
A1: 案件シート（テンプレート）
A2: ※ 新規案件作成時にこのシートを複製して使用します
A4: ▼ 案件基本情報
A5: 案件ID | D5: 顧客ID | F5: 顧客名 | G5: =IFERROR(VLOOKUP(E5,顧客マスタ!A:C,3,FALSE),"") | I5: 敬称 | J5: =IFERROR(VLOOKUP(E5,顧客マスタ!A:D,4,FALSE),"") | M5: 担当者
A6: 工事名 | F6: 施工場所 | M6: 作成日 | N6: =TODAY() -> 46070
A7: 目標粗利率 | B7: 0.3 | D7: ※原価逆算型のデフォルト
A9: ▼ 原価管理表（見積 → 原価 → 客出し金額 → 発注管理）
A11: ※ A=原価逆算型（原価÷(1-粗利率)） B=定価固定型（客出し固定） C=単価固定型（クロス等市場単価×数量）
A12: 青字=手入力 黒字=自動計算 ★=発注情報 ◆E/F/H列はDB自動参照（上書きOK）
B13: 原価情報 | H13: 客出し情報 | L13: 利益 | N13: ★ 発注管理
A14: No. | B14: タイプ | C14: 工事カテゴリ | D14: 品名（小項目） | E14: 仕様・形状 | F14: 原価単価 | G14: 原価金額 | H14: 単位 | I14: 数量 | J14: 客出し単価 | K14: 客出し金額 | L14: 利益額 | M14: 利益率 | N14: 発注先 | O14: 発注日 | P14: 発注額 | Q14: 支払済 | R14: 備考
A15: 1 | E15: =IF(AND(C15<>"",D15<>""),IFERROR(INDEX(工事項目DB!D:D,MATCH(C15&"|"&D15,工事項目DB!L:L,0)),""),"") | F15: =IF(AND(C15<>"",D15<>""),IFERROR(INDEX(工事項目DB!F:F,MATCH(C15&"|"&D15,工事項目DB!L:L,0)),""),"") | G15: =IF(F15<>"",F15*I15,"") | H15: =IF(AND(C15<>"",D15<>""),IFERROR(INDEX(工事項目DB!E:E,MATCH(C15&"|"&D15,工事項目DB!L:L,0)),""),"") | J15: =IF(B15="A",IF(AND(F15<>"",I15<>""),ROUND(F15/(1-$B$7),0),""),"") | K15: =IF(AND(J15<>"",I15<>""),J15*I15,"") | L15: =IF(AND(K15<>"",G15<>""),K15-G15,"") | M15: =IFERROR(IF(AND(K15<>"",K15<>0),L15/K15,""),"") | P15: =IF(N15<>"",G15,"")
A16: 2 | E16: =IF(AND(C16<>"",D16<>""),IFERROR(INDEX(工事項目DB!D:D,MATCH(C16&"|"&D16,工事項目DB!L:L,0)),""),"") | F16: =IF(AND(C16<>"",D16<>""),IFERROR(INDEX(工事項目DB!F:F,MATCH(C16&"|"&D16,工事項目DB!L:L,0)),""),"") | G16: =IF(F16<>"",F16*I16,"") | H16: =IF(AND(C16<>"",D16<>""),IFERROR(INDEX(工事項目DB!E:E,MATCH(C16&"|"&D16,工事項目DB!L:L,0)),""),"") | K16: =IF(AND(J16<>"",I16<>""),J16*I16,"") | L16: =IF(AND(K16<>"",G16<>""),K16-G16,"") | M16: =IFERROR(IF(AND(K16<>"",K16<>0),L16/K16,""),"") | P16: =IF(N16<>"",G16,"")
A17: 3 | E17: =IF(AND(C17<>"",D17<>""),IFERROR(INDEX(工事項目DB!D:D,MATCH(C17&"|"&D17,工事項目DB!L:L,0)),""),"") | F17: =IF(AND(C17<>"",D17<>""),IFERROR(INDEX(工事項目DB!F:F,MATCH(C17&"|"&D17,工事項目DB!L:L,0)),""),"") | G17: =IF(F17<>"",F17*I17,"") | H17: =IF(AND(C17<>"",D17<>""),IFERROR(INDEX(工事項目DB!E:E,MATCH(C17&"|"&D17,工事項目DB!L:L,0)),""),"") | K17: =IF(AND(J17<>"",I17<>""),J17*I17,"") | L17: =IF(AND(K17<>"",G17<>""),K17-G17,"") | M17: =IFERROR(IF(AND(K17<>"",K17<>0),L17/K17,""),"") | P17: =IF(N17<>"",G17,"")
A18: 4 | C18: 仕上げ工事 | E18: =IF(AND(C18<>"",D18<>""),IFERROR(INDEX(工事項目DB!D:D,MATCH(C18&"|"&D18,工事項目DB!L:L,0)),""),"") | F18: =IF(AND(C18<>"",D18<>""),IFERROR(INDEX(工事項目DB!F:F,MATCH(C18&"|"&D18,工事項目DB!L:L,0)),""),"") | G18: =IF(F18<>"",F18*I18,"") | H18: =IF(AND(C18<>"",D18<>""),IFERROR(INDEX(工事項目DB!E:E,MATCH(C18&"|"&D18,工事項目DB!L:L,0)),""),"") | J18: =IF(B18="A",IF(AND(F18<>"",I18<>""),ROUND(F18/(1-$B$7),0),""),"") | K18: =IF(AND(J18<>"",I18<>""),J18*I18,"") | L18: =IF(AND(K18<>"",G18<>""),K18-G18,"") | M18: =IFERROR(IF(AND(K18<>"",K18<>0),L18/K18,""),"") | P18: =IF(N18<>"",G18,"")
A19: 5 | E19: =IF(AND(C19<>"",D19<>""),IFERROR(INDEX(工事項目DB!D:D,MATCH(C19&"|"&D19,工事項目DB!L:L,0)),""),"") | F19: =IF(AND(C19<>"",D19<>""),IFERROR(INDEX(工事項目DB!F:F,MATCH(C19&"|"&D19,工事項目DB!L:L,0)),""),"") | G19: =IF(F19<>"",F19*I19,"") | H19: =IF(AND(C19<>"",D19<>""),IFERROR(INDEX(工事項目DB!E:E,MATCH(C19&"|"&D19,工事項目DB!L:L,0)),""),"") | J19: =IF(B19="A",IF(AND(F19<>"",I19<>""),ROUND(F19/(1-$B$7),0),""),"") | K19: =IF(AND(J19<>"",I19<>""),J19*I19,"") | L19: =IF(AND(K19<>"",G19<>""),K19-G19,"") | M19: =IFERROR(IF(AND(K19<>"",K19<>0),L19/K19,""),"") | P19: =IF(N19<>"",G19,"")
A20: 6 | E20: =IF(AND(C20<>"",D20<>""),IFERROR(INDEX(工事項目DB!D:D,MATCH(C20&"|"&D20,工事項目DB!L:L,0)),""),"") | F20: =IF(AND(C20<>"",D20<>""),IFERROR(INDEX(工事項目DB!F:F,MATCH(C20&"|"&D20,工事項目DB!L:L,0)),""),"") | G20: =IF(F20<>"",F20*I20,"") | H20: =IF(AND(C20<>"",D20<>""),IFERROR(INDEX(工事項目DB!E:E,MATCH(C20&"|"&D20,工事項目DB!L:L,0)),""),"") | J20: =IF(B20="A",IF(AND(F20<>"",I20<>""),ROUND(F20/(1-$B$7),0),""),"") | K20: =IF(AND(J20<>"",I20<>""),J20*I20,"") | L20: =IF(AND(K20<>"",G20<>""),K20-G20,"") | M20: =IFERROR(IF(AND(K20<>"",K20<>0),L20/K20,""),"") | P20: =IF(N20<>"",G20,"")
A21: 7 | E21: =IF(AND(C21<>"",D21<>""),IFERROR(INDEX(工事項目DB!D:D,MATCH(C21&"|"&D21,工事項目DB!L:L,0)),""),"") | F21: =IF(AND(C21<>"",D21<>""),IFERROR(INDEX(工事項目DB!F:F,MATCH(C21&"|"&D21,工事項目DB!L:L,0)),""),"") | G21: =IF(F21<>"",F21*I21,"") | H21: =IF(AND(C21<>"",D21<>""),IFERROR(INDEX(工事項目DB!E:E,MATCH(C21&"|"&D21,工事項目DB!L:L,0)),""),"") | J21: =IF(B21="A",IF(AND(F21<>"",I21<>""),ROUND(F21/(1-$B$7),0),""),"") | K21: =IF(AND(J21<>"",I21<>""),J21*I21,"") | L21: =IF(AND(K21<>"",G21<>""),K21-G21,"") | M21: =IFERROR(IF(AND(K21<>"",K21<>0),L21/K21,""),"") | P21: =IF(N21<>"",G21,"")
A22: 8 | E22: =IF(AND(C22<>"",D22<>""),IFERROR(INDEX(工事項目DB!D:D,MATCH(C22&"|"&D22,工事項目DB!L:L,0)),""),"") | F22: =IF(AND(C22<>"",D22<>""),IFERROR(INDEX(工事項目DB!F:F,MATCH(C22&"|"&D22,工事項目DB!L:L,0)),""),"") | G22: =IF(F22<>"",F22*I22,"") | H22: =IF(AND(C22<>"",D22<>""),IFERROR(INDEX(工事項目DB!E:E,MATCH(C22&"|"&D22,工事項目DB!L:L,0)),""),"") | J22: =IF(B22="A",IF(AND(F22<>"",I22<>""),ROUND(F22/(1-$B$7),0),""),"") | K22: =IF(AND(J22<>"",I22<>""),J22*I22,"") | L22: =IF(AND(K22<>"",G22<>""),K22-G22,"") | M22: =IFERROR(IF(AND(K22<>"",K22<>0),L22/K22,""),"") | P22: =IF(N22<>"",G22,"")
A23: 9 | E23: =IF(AND(C23<>"",D23<>""),IFERROR(INDEX(工事項目DB!D:D,MATCH(C23&"|"&D23,工事項目DB!L:L,0)),""),"") | F23: =IF(AND(C23<>"",D23<>""),IFERROR(INDEX(工事項目DB!F:F,MATCH(C23&"|"&D23,工事項目DB!L:L,0)),""),"") | G23: =IF(F23<>"",F23*I23,"") | H23: =IF(AND(C23<>"",D23<>""),IFERROR(INDEX(工事項目DB!E:E,MATCH(C23&"|"&D23,工事項目DB!L:L,0)),""),"") | J23: =IF(B23="A",IF(AND(F23<>"",I23<>""),ROUND(F23/(1-$B$7),0),""),"") | K23: =IF(AND(J23<>"",I23<>""),J23*I23,"") | L23: =IF(AND(K23<>"",G23<>""),K23-G23,"") | M23: =IFERROR(IF(AND(K23<>"",K23<>0),L23/K23,""),"") | P23: =IF(N23<>"",G23,"")
A24: 10 | E24: =IF(AND(C24<>"",D24<>""),IFERROR(INDEX(工事項目DB!D:D,MATCH(C24&"|"&D24,工事項目DB!L:L,0)),""),"") | F24: =IF(AND(C24<>"",D24<>""),IFERROR(INDEX(工事項目DB!F:F,MATCH(C24&"|"&D24,工事項目DB!L:L,0)),""),"") | G24: =IF(F24<>"",F24*I24,"") | H24: =IF(AND(C24<>"",D24<>""),IFERROR(INDEX(工事項目DB!E:E,MATCH(C24&"|"&D24,工事項目DB!L:L,0)),""),"") | J24: =IF(B24="A",IF(AND(F24<>"",I24<>""),ROUND(F24/(1-$B$7),0),""),"") | K24: =IF(AND(J24<>"",I24<>""),J24*I24,"") | L24: =IF(AND(K24<>"",G24<>""),K24-G24,"") | M24: =IFERROR(IF(AND(K24<>"",K24<>0),L24/K24,""),"") | P24: =IF(N24<>"",G24,"")
A25: 11 | E25: =IF(AND(C25<>"",D25<>""),IFERROR(INDEX(工事項目DB!D:D,MATCH(C25&"|"&D25,工事項目DB!L:L,0)),""),"") | F25: =IF(AND(C25<>"",D25<>""),IFERROR(INDEX(工事項目DB!F:F,MATCH(C25&"|"&D25,工事項目DB!L:L,0)),""),"") | G25: =IF(F25<>"",F25*I25,"") | H25: =IF(AND(C25<>"",D25<>""),IFERROR(INDEX(工事項目DB!E:E,MATCH(C25&"|"&D25,工事項目DB!L:L,0)),""),"") | J25: =IF(B25="A",IF(AND(F25<>"",I25<>""),ROUND(F25/(1-$B$7),0),""),"") | K25: =IF(AND(J25<>"",I25<>""),J25*I25,"") | L25: =IF(AND(K25<>"",G25<>""),K25-G25,"") | M25: =IFERROR(IF(AND(K25<>"",K25<>0),L25/K25,""),"") | P25: =IF(N25<>"",G25,"")
A26: 12 | E26: =IF(AND(C26<>"",D26<>""),IFERROR(INDEX(工事項目DB!D:D,MATCH(C26&"|"&D26,工事項目DB!L:L,0)),""),"") | F26: =IF(AND(C26<>"",D26<>""),IFERROR(INDEX(工事項目DB!F:F,MATCH(C26&"|"&D26,工事項目DB!L:L,0)),""),"") | G26: =IF(F26<>"",F26*I26,"") | H26: =IF(AND(C26<>"",D26<>""),IFERROR(INDEX(工事項目DB!E:E,MATCH(C26&"|"&D26,工事項目DB!L:L,0)),""),"") | J26: =IF(B26="A",IF(AND(F26<>"",I26<>""),ROUND(F26/(1-$B$7),0),""),"") | K26: =IF(AND(J26<>"",I26<>""),J26*I26,"") | L26: =IF(AND(K26<>"",G26<>""),K26-G26,"") | M26: =IFERROR(IF(AND(K26<>"",K26<>0),L26/K26,""),"") | P26: =IF(N26<>"",G26,"")
A27: 13 | E27: =IF(AND(C27<>"",D27<>""),IFERROR(INDEX(工事項目DB!D:D,MATCH(C27&"|"&D27,工事項目DB!L:L,0)),""),"") | F27: =IF(AND(C27<>"",D27<>""),IFERROR(INDEX(工事項目DB!F:F,MATCH(C27&"|"&D27,工事項目DB!L:L,0)),""),"") | G27: =IF(F27<>"",F27*I27,"") | H27: =IF(AND(C27<>"",D27<>""),IFERROR(INDEX(工事項目DB!E:E,MATCH(C27&"|"&D27,工事項目DB!L:L,0)),""),"") | J27: =IF(B27="A",IF(AND(F27<>"",I27<>""),ROUND(F27/(1-$B$7),0),""),"") | K27: =IF(AND(J27<>"",I27<>""),J27*I27,"") | L27: =IF(AND(K27<>"",G27<>""),K27-G27,"") | M27: =IFERROR(IF(AND(K27<>"",K27<>0),L27/K27,""),"") | P27: =IF(N27<>"",G27,"")
A28: 14 | E28: =IF(AND(C28<>"",D28<>""),IFERROR(INDEX(工事項目DB!D:D,MATCH(C28&"|"&D28,工事項目DB!L:L,0)),""),"") | F28: =IF(AND(C28<>"",D28<>""),IFERROR(INDEX(工事項目DB!F:F,MATCH(C28&"|"&D28,工事項目DB!L:L,0)),""),"") | G28: =IF(F28<>"",F28*I28,"") | H28: =IF(AND(C28<>"",D28<>""),IFERROR(INDEX(工事項目DB!E:E,MATCH(C28&"|"&D28,工事項目DB!L:L,0)),""),"") | J28: =IF(B28="A",IF(AND(F28<>"",I28<>""),ROUND(F28/(1-$B$7),0),""),"") | K28: =IF(AND(J28<>"",I28<>""),J28*I28,"") | L28: =IF(AND(K28<>"",G28<>""),K28-G28,"") | M28: =IFERROR(IF(AND(K28<>"",K28<>0),L28/K28,""),"") | P28: =IF(N28<>"",G28,"")
A29: 15 | E29: =IF(AND(C29<>"",D29<>""),IFERROR(INDEX(工事項目DB!D:D,MATCH(C29&"|"&D29,工事項目DB!L:L,0)),""),"") | F29: =IF(AND(C29<>"",D29<>""),IFERROR(INDEX(工事項目DB!F:F,MATCH(C29&"|"&D29,工事項目DB!L:L,0)),""),"") | G29: =IF(F29<>"",F29*I29,"") | H29: =IF(AND(C29<>"",D29<>""),IFERROR(INDEX(工事項目DB!E:E,MATCH(C29&"|"&D29,工事項目DB!L:L,0)),""),"") | J29: =IF(B29="A",IF(AND(F29<>"",I29<>""),ROUND(F29/(1-$B$7),0),""),"") | K29: =IF(AND(J29<>"",I29<>""),J29*I29,"") | L29: =IF(AND(K29<>"",G29<>""),K29-G29,"") | M29: =IFERROR(IF(AND(K29<>"",K29<>0),L29/K29,""),"") | P29: =IF(N29<>"",G29,"")
A30: 16 | E30: =IF(AND(C30<>"",D30<>""),IFERROR(INDEX(工事項目DB!D:D,MATCH(C30&"|"&D30,工事項目DB!L:L,0)),""),"") | F30: =IF(AND(C30<>"",D30<>""),IFERROR(INDEX(工事項目DB!F:F,MATCH(C30&"|"&D30,工事項目DB!L:L,0)),""),"") | G30: =IF(F30<>"",F30*I30,"") | H30: =IF(AND(C30<>"",D30<>""),IFERROR(INDEX(工事項目DB!E:E,MATCH(C30&"|"&D30,工事項目DB!L:L,0)),""),"") | J30: =IF(B30="A",IF(AND(F30<>"",I30<>""),ROUND(F30/(1-$B$7),0),""),"") | K30: =IF(AND(J30<>"",I30<>""),J30*I30,"") | L30: =IF(AND(K30<>"",G30<>""),K30-G30,"") | M30: =IFERROR(IF(AND(K30<>"",K30<>0),L30/K30,""),"") | P30: =IF(N30<>"",G30,"")
... A44: 30 | E44: =IF(AND(C44<>"",D44<>""),IFERROR(INDEX(工事項目DB!D:D,MATCH(C44&"|"&D44,工事項目DB!L:L,0)),""),"") | F44: =IF(AND(C44<>"",D44<>""),IFERROR(INDEX(工事項目DB!F:F,MATCH(C44&"|"&D44,工事項目DB!L:L,0)),""),"") | G44: =IF(F44<>"",F44*I44,"") | H44: =IF(AND(C44<>"",D44<>""),IFERROR(INDEX(工事項目DB!E:E,MATCH(C44&"|"&D44,工事項目DB!L:L,0)),""),"") | J44: =IF(B44="A",IF(AND(F44<>"",I44<>""),ROUND(F44/(1-$B$7),0),""),"") | K44: =IF(AND(J44<>"",I44<>""),J44*I44,"") | L44: =IF(AND(K44<>"",G44<>""),K44-G44,"") | M44: =IFERROR(IF(AND(K44<>"",K44<>0),L44/K44,""),"") | P44: =IF(N44<>"",G44,"")
F45: 原価合計 | G45: =SUM(G15:G44) -> 0 | J45: 客出し合計 | K45: =SUM(K15:K44) -> 0 | L45: =K45-G45 -> 0 | M45: =IF(K45<>0,L45/K45,"") | P45: =SUM(P15:P44) -> 0
A47: ▼ 税計算
A48: 小計（税抜） | G48: =G45 -> 0 | K48: =K45 -> 0 | L48: =L45 -> 0 | M48: =M45
A49: 消費税（10%） | G49: =ROUND(G48*マスター設定!K24,0) -> 0 | K49: =ROUND(K48*マスター設定!K24,0) -> 0
A50: 合計（税込） | G50: =G48+G49 -> 0 | K50: =K48+K49 -> 0 | L50: =K50-G50 -> 0 | M50: =IF(K50<>0,L50/K50,"")
A53: ▼ 行操作ツール
A54: クリアしたい行No. | C54: ← 行No.を入力してClaudeに「行クリア」と伝えてください
A55: 入替え: 行A ↔ 行B | C55: ← | E55: ← 2つのNo.を入力してClaudeに「行入替え」と伝えてください
A56: ※ 直接セルを選択してDeleteキーでもクリアできます（数式は自動復元）
A60: ▼ DB参照（過去実績から自動表示）
A61: ※ 上の原価管理表で工事カテゴリ(C列)を入力すると、工事項目DBの過去実績がここに表示されます
A62: 💡 品名(D列)を入力 → 工事カテゴリ+品名がDBに一致すると仕様・単価・単位が自動入力されます。新規項目は手入力OK。
A63: 工事カテゴリ | B63: 品名 | C63: 仕様 | D63: 単位 | E63: 標準単価 | F63: 業者名 | G63: 最終使用日 | H63: 利益率 | I63: 使用回数 | J63: 案件名 | K63: → 転記方法
A64: {=IFERROR(_xlfn._xlws.SORT(_xlfn._xlws.FILTER(工事項目DB!B5:K50, (工事項目DB!A5:A50<>""), "データなし"), 1, 1), "データなし")} -> タイル左官工事 | B64: 浴槽タイルまし張り 壁床 | C64: 大判タイル 材料支給 | D64: 人工 | E64: 30000 | F64: 0 | G64: 45759 | H64: 0 | I64: 1 | J64: 南麻布レジデンス
A65: タイル左官工事 | B65: 目地 材工共 | C65: 0 | D65: 式 | E65: 65000 | F65: 0 | G65: 45759 | H65: 0 | I65: 1 | J65: 南麻布レジデンス
A66: タイル左官工事 | B66: 水回り コーキング | C66: 材工共 | D66: 式 | E66: 55000 | F66: 0 | G66: 45759 | H66: 0 | I66: 1 | J66: 南麻布レジデンス
A67: タイル左官工事 | B67: 既存ブロック塀 左官材工共 | C67: Magic coat flex クラウド仕上色 | D67: 式 | E67: 100000 | F67: 0 | G67: 45759 | H67: 0 | I67: 1 | J67: 南麻布レジデンス
A68: 衛生設備 | B68: 給排水配管工事 | C68: 材工共 | D68: 式 | E68: 120000 | F68: 0 | G68: 46070 | H68: 0.25 | I68: 1 | J68: P-003 吉野様邸 キッチンリフォーム
A69: 家具工事 | B69: 収納内部 引き出し付き什器 | C69: スライドレール取手金物込 | D69: 台 | E69: 248500 | F69: 0 | G69: 45759 | H69: 0 | I69: 1 | J69: 南麻布レジデンス
A70: 家具工事 | B70: ドロワー 本体代 | C70: 0 | D70: 台 | E70: 224850 | F70: 0 | G70: 45759 | H70: 0 | I70: 1 | J70: 南麻布レジデンス
A71: 家具工事 | B71: 大型障子 本体代 ワーロン | C71: 1800*1500x2 金物込 | D71: 組 | E71: 466500 | F71: 0 | G71: 45759 | H71: 0 | I71: 1 | J71: 南麻布レジデンス
A72: 家具工事 | B72: ベッド土台 ヘッドパネル | C72: ナラ突板 マットレス下脱着式 | D72: 組 | E72: 178560 | F72: 0 | G72: 45759 | H72: 0 | I72: 1 | J72: 南麻布レジデンス
A73: 家具工事 | B73: サイドボード ナラ突板 | C73: 照明コンセントスイッチ支給 | D73: 台 | E73: 78660 | F73: 0 | G73: 45759 | H73: 0 | I73: 1 | J73: 南麻布レジデンス
A74: 家具工事 | B74: 洗面台 ドレッサー コーリアン | C74: 0 | D74: 枚 | E74: 56000 | F74: 0 | G74: 45759 | H74: 0 | I74: 1 | J74: 南麻布レジデンス
A75: 家具工事 | B75: LIXIL システムキッチン シエラS | C75: W2550 IH・食洗機付 | D75: 台 | E75: 420000 | F75: 0 | G75: 46070 | H75: 0.25 | I75: 1 | J75: P-003 吉野様邸 キッチンリフォーム
A76: 解体工事 | B76: 発生材処理費 | C76: 混載 | D76: ㎥ | E76: 20000 | F76: 0 | G76: 45759 | H76: 0 | I76: 1 | J76: 南麻布レジデンス
A77: 解体工事 | B77: トラック | C77: 0 | D77: 台 | E77: 18000 | F77: 0 | G77: 45759 | H77: 0 | I77: 1 | J77: 南麻布レジデンス
A78: 解体工事 | B78: 運搬費 | C78: 0 | D78: 人工 | E78: 20000 | F78: 0 | G78: 45759 | H78: 0 | I78: 1 | J78: 南麻布レジデンス
A79: 解体工事 | B79: 既存キッチン解体・撤去 | C79: 材工共 | D79: 式 | E79: 85000 | F79: 0 | G79: 46070 | H79: 0 | I79: 1 | J79: P-003 吉野様邸 キッチンリフォーム
A80: 共通 | B80: 搬入費 | C80: 0 | D80: 式 | E80: 25000 | F80: 0 | G80: 45759 | H80: 0 | I80: 1 | J80: 南麻布レジデンス
A81: 共通 | B81: 副資材 | C81: 0 | D81: 式 | E81: 15200 | F81: 0 | G81: 45759 | H81: 0 | I81: 1 | J81: 南麻布レジデンス
A82: 共通 | B82: 発生材処理費 | C82: 0 | D82: 式 | E82: 6850 | F82: 0 | G82: 45759 | H82: 0 | I82: 1 | J82: 南麻布レジデンス
A83: 共通 | B83: 運搬費 | C83: 4t 2回分 | D83: 式 | E83: 100000 | F83: 0 | G83: 45759 | H83: 0 | I83: 1 | J83: 南麻布レジデンス
A84: 共通 | B84: 労務費（取付・現場加工） | C84: 0 | D84: 人工 | E84: 30000 | F84: 0 | G84: 45759 | H84: 0 | I84: 1 | J84: 南麻布レジデンス
A85: 共通 | B85: 資材運搬搬入費 | C85: 0 | D85: 式 | E85: 18000 | F85: 0 | G85: 45759 | H85: 0 | I85: 1 | J85: 南麻布レジデンス
A86: 共通 | B86: 産廃処理費 | C86: 混載 | D86: ㎥ | E86: 18000 | F86: 0 | G86: 46070 | H86: 0.25 | I86: 1 | J86: P-003 吉野様邸 キッチンリフォーム
A87: 建具工事 | B87: 1F-2F踊り場 障子 | C87: 797*474 金物含む | D87: 枚 | E87: 96520 | F87: 0 | G87: 45759 | H87: 0 | I87: 1 | J87: 南麻布レジデンス
A88: 建具工事 | B88: 2F廊下 障子 | C88: 500*572 金物含む | D88: 枚 | E88: 94500 | F88: 0 | G88: 45759 | H88: 0 | I88: 1 | J88: 南麻布レジデンス
A89: 建具工事 | B89: 2F廊下+2Fキッチン部分 障子 | C89: 2064*575 金物含む | D89: 枚 | E89: 166500 | F89: 0 | G89: 45759 | H89: 0 | I89: 1 | J89: 南麻布レジデンス
A90: 建具工事 | B90: WD2 新規建具 ナラ突板 | C90: 2121*667*36 金物取手枠込 | D90: 組 | E90: 200000 | F90: 0 | G90: 45759 | H90: 0 | I90: 1 | J90: 南麻布レジデンス
A91: 建具工事 | B91: WD3 新規引き戸 塗装仕上げ | C91: 2178*650*36 金物取手含む | D91: 組 | E91: 180000 | F91: 0 | G91: 45759 | H91: 0 | I91: 1 | J91: 南麻布レジデンス
A92: 建具工事 | B92: 運搬費 | C92: 新規建具３回 | D92: 式 | E92: 85000 | F92: 0 | G92: 45759 | H92: 0 | I92: 1 | J92: 南麻布レジデンス
A93: 建具工事 | B93: 副資材 | C93: 0 | D93: 式 | E93: 15200 | F93: 0 | G93: 45759 | H93: 0 | I93: 1 | J93: 南麻布レジデンス
A94: 仕上げ工事 | B94: 階段下 新規ベニヤ貼り後 塗装 | C94: 材工共 | D94: 式 | E94: 65000 | F94: 0 | G94: 45759 | H94: 0 | I94: 1 | J94: 南麻布レジデンス
A95: 仕上げ工事 | B95: クロス張替え | C95: 量産クロス SP級 | D95: ㎡ | E95: 650 | F95: 0 | G95: 46070 | H95: 0.38235294 | I95: 1 | J95: P-003 吉野様邸 キッチンリフォーム
A96: 仕上げ工事 | B96: CFシート張替え | C96: サンゲツ HM-10108 | D96: ㎡ | E96: 800 | F96: 0 | G96: 46070 | H96: 0.40909091 | I96: 1 | J96: P-003 吉野様邸 キッチンリフォーム
A97: 造作工事 | B97: 階段室下 シナベニヤ t12 材料費 | C97: 0 | D97: 枚 | E97: 11000 | F97: 0 | G97: 45759 | H97: 0 | I97: 1 | J97: 南麻布レジデンス
A98: 造作工事 | B98: 階段室下 間接照明隠蔽用 モクヒモ材 | C98: 0 | D98: 本 | E98: 15000 | F98: 0 | G98: 45759 | H98: 0 | I98: 1 | J98: 南麻布レジデンス
A99: 造作工事 | B99: シナベニヤ ダボ掘り込み 取付 | C99: 0 | D99: 式 | E99: 25000 | F99: 0 | G99: 45759 | H99: 0 | I99: 1 | J99: 南麻布レジデンス
A100: 造作工事 | B100: 折り上げ天井部 ナラ突板 | C100: 2m | D100: 本 | E100: 18500 | F100: 0 | G100: 45759 | H100: 0 | I100: 1 | J100: 南麻布レジデンス
A101: 造作工事 | B101: 労務費 | C101: 0 | D101: 人工 | E101: 30000 | F101: 0 | G101: 45759 | H101: 0 | I101: 1 | J101: 南麻布レジデンス
A102: 電気設備 | B102: コンセント増設・照明移設 | C102: 材工共 | D102: 式 | E102: 65000 | F102: 0 | G102: 46070 | H102: 0.55555556 | I102: 1 | J102: P-003 吉野様邸 キッチンリフォーム
A104: ▼ S表紙用 カテゴリ別集計
A105: 解体工事 | B105: =SUMIFS(K15:K44,C15:C44,A105) -> 0
A106: 造作工事 | B106: =SUMIFS(K15:K44,C15:C44,A106) -> 0
A107: 建具工事 | B107: =SUMIFS(K15:K44,C15:C44,A107) -> 0
A108: 家具工事 | B108: =SUMIFS(K15:K44,C15:C44,A108) -> 0
A109: 電気設備 | B109: =SUMIFS(K15:K44,C15:C44,A109) -> 0
A110: タイル左官工事 | B110: =SUMIFS(K15:K44,C15:C44,A110) -> 0
A111: 仕上げ工事 | B111: =SUMIFS(K15:K44,C15:C44,A111) -> 0
A112: 衛生設備 | B112: =SUMIFS(K15:K44,C15:C44,A112) -> 0
A113: 共通 | B113: =SUMIFS(K15:K44,C15:C44,A113) -> 0
A114: 下地工事 | B114: =SUMIFS(K15:K44,C15:C44,A114) -> 0
A115: 新規壁工事 | B115: =SUMIFS(K15:K44,C15:C44,A115) -> 0
A116: 床 | B116: =SUMIFS(K15:K44,C15:C44,A116) -> 0
A117: 空調 | B117: =SUMIFS(K15:K44,C15:C44,A117) -> 0
A118: シート工事 | B118: =SUMIFS(K15:K44,C15:C44,A118) -> 0
A119: 塗装工事 | B119: =SUMIFS(K15:K44,C15:C44,A119) -> 0
A120: 雑工事 | B120: =SUMIFS(K15:K44,C15:C44,A120) -> 0
A121: 防災工事 | B121: =SUMIFS(K15:K44,C15:C44,A121) -> 0
A122: ガス工事 | B122: =SUMIFS(K15:K44,C15:C44,A122) -> 0
A123: 産廃費 | B123: =SUMIFS(K15:K44,C15:C44,A123) -> 0
...

Sheet 設計書
A1: 見積作成ソフト 全体設計書
A3: ■ 1. システム概要
A5: 目的 | B5: 内装工事の見積作成・原価管理・CRM・帳票出力を一元管理するExcelソフト
A6: 対象業務 | B6: CRM(顧客管理→案件進捗)→原価管理(3パターン)→見積→発注書兼請求書→データ蓄積
A7: データ蓄積 | B7: 過去案件の工事項目・単価・業者・利益率をDBに蓄積し、次回見積で再利用可能にする
A9: ■ 2. シート構成（現在の実装状態）
A11: No. | B11: シート名 | C11: 役割 | D11: ステータス | E11: 新規/既存 | F11: 備考
A12: 1 | B12: 操作パネル | C12: 新規案件作成・システムナビゲーション（コントロールセンター） | D12: ✅ 実装済 | E12: ★新規 | F12: 全シートの基本情報をここから参照
A13: 2 | B13: ダッシュボード | C13: CRM KPI（7指標）+ ステータス分布 + 担当者別実績 + 顧客ランキング | D13: ✅ 実装済 | E13: ★新規 | F13: ドロップダウンの選択肢元。案件完了時に自動追加
A14: 3 | B14: 案件管理 | C14: 全案件パイプライン（20列：ID→ステータス→経過日数→滞留アラート） | D14: ✅ 実装済 | E14: ★新規 | F14: 注文書の宛先自動入力に使用
A15: 4 | B15: 案件テンプレート | C15: 原価管理表（A/B/C 3パターン原価＋見積金額＋利益率＋税計算） | D15: ✅ 実装済 | E15: 既存改良 | F15: マスター設定からの自動反映、工事項目の増減対応
A16: 5 | B16: 発注書兼請求書 | C16: 兼用帳票（モード切替：発注書⇔請求書）業者DB連動 | D16: ✅ 実装済 | E16: 既存改良 | F16: 現在の28行構造をベースに、行数可変化・DB連携
A17: 6 | B17: 顧客マスタ / マスター設定 / 工事項目DB / 業者DB | C17: データベース群（顧客・会社情報・工事項目・協力業者） | D17: ✅ 実装済 | E17: 既存改良 | F17: Ｓ表紙の金額を自動参照。実費入力で差異管理
A18: 7 | B18: P-xxx_案件名（個別案件シート） | C18: テンプレートから自動複製。案件別原価・見積・利益管理 | D18: ✅ 運用中 | E18: 既存改良 | F18: マスター設定＋業者DBから自動入力
A20: ■ 3. 機能詳細
A22: 【A】マスター設定シート（実装済）
A23: 項目 | B23: 内容 | C23: 連携先
A24: 会社情報 | B24: 株式会社LinK 住所・TEL・Mail（固定値） | C24: 案件テンプレート・発注書・全帳票
A25: 担当者マスタ | B25: スタッフ10名分（名前・メール・電話） | C25: 案件管理・案件テンプレート（VLOOKUP）
A26: 工事カテゴリ | B26: 20工種（チェックボックス＋小計金額VLOOKUP） | C26: S表紙・工事明細シート群
A28: 【A-2】原価管理3パターン（実装済）
A29: タイプA: 原価逆算型 | B29: 原価単価入力 → 目標粗利率で客出し自動計算 | C29: {=ROUND(F/(1-粗利率),0)} -> #NAME?
A30: タイプB: 定価固定型 | B30: 客出し金額固定、仕入原価固定 → 利益は結果 | C30: J列に手入力（市場価格）
A31: タイプC: 単価固定型 | B31: 客出し単価固定（市場相場）、原価は業者次第 → 利益は結果 | C31: J列に手入力（業者見積後）
A33: 【B】データベース群（実装済）
A34: DB名 | B34: 列数 | C34: レコード数 | D34: 主な項目
A35: 工事項目DB | B35: 10列 | C35: 32項目（初期データ） | D35: ID/カテゴリ/品名/仕様/単位/標準単価/業者/使用日
A36: 業者DB | B36: 10列 | C36: テンプレート10枠 | D36: ID/カテゴリ/業者名/担当者/TEL/Mail/住所/支払条件
A37: 顧客マスタ | B37: 20列 | C37: 100枠（C-001～C-100） | D37: ID/区分/氏名/敬称/TEL/Mail/住所/紹介元/累計案件/累計受注額
A38: 案件管理 | B38: 20列 | C38: 100枠（P-001～P-100） | D38: ID/顧客ID/案件名/ステータス/経過日数/滞留アラート/金額
A40: 【B-2】CRMダッシュボード（実装済）
A41: KPIカード×7 | B41: 全案件数/アクティブ/受注/失注/受注率/滞留/見積合計
A42: 分析テーブル×3 | B42: ステータス分布/担当者別実績/顧客ランキングTOP10
A44: 【C】業務フロー（実装版）
A45: STEP | B45: 操作 | C45: 動作 | D45: 実装状態
A46: ① | B46: 操作パネルで新規案件作成 | C46: 顧客ID選択→案件名→担当者→目標粗利率→作成 | D46: ✅
A47: ② | B47: 案件管理に自動登録 | C47: P-xxx ID自動採番、顧客名VLOOKUP、ステータス初期値 | D47: ✅
A48: ③ | B48: 案件シートで原価入力 | C48: タイプA/B/C選択→原価単価→数量→利益自動計算 | D48: ✅
A49: ④ | B49: 見積金額自動集計 | C49: 原価合計・客出し合計・利益率・消費税すべて自動 | D49: ✅
A50: ⑤ | B50: 発注書兼請求書で帳票出力 | C50: 案件ID+業者ID選択→金額自動反映→PDF出力 | D50: ✅
A51: ⑥ | B51: ステータス更新→ダッシュボード反映 | C51: KPI・チャート・ランキング全自動更新 | D51: ✅
A52: ⑦ | B52: 完工時→工事項目DBに実績蓄積 | C52: 使用した単価・業者・利益率をDB自動蓄積 | D52: ✅ 実装済
A53: ⑦ | B53: DB蓄積 | C53: 案件完了時に工事項目DBへ自動追加 | D53: 次回見積で単価実績として再利用可能
A55: ■ 4. 実装フェーズ（最新版）
A57: Phase | B57: 内容 | C57: 作業内容 | D57: ステータス
A58: Phase 1 | B58: 基盤構築 | C58: マスター設定 + 工事項目DB(32件) + 業者DB | D58: ✅ 完了
A59: Phase 2 | B59: CRM構築 | C59: 顧客マスタ(20列) + 案件管理(20列) + ダッシュボード(7KPI+チャート) | D59: ✅ 完了
A60: Phase 3 | B60: 原価管理+帳票 | C60: 案件テンプレート(3パターン原価) + 発注書兼請求書(兼用型) + 操作パネル | D60: ✅ 完了
A61: Phase 4 | B61: UI整備+テスト | C61: シートタブ整理 + 印刷設定 + 行操作ツール + P-003テスト案件作成・検証 | D61: ✅ 完了
A62: Phase 5 | B62: 蓄積+分析 | C62: DB自動蓄積 + 失注分析 + 運用改善 | D62: ✅ 完了
A64: ■ 5. CRMシステム設計（実装済）
A65: 【目的】顧客管理・案件進捗・見積履歴を一元管理。未経験者でも操作可能なUI設計。
A66: 【目的】顧客管理・案件進捗・見積履歴を一元管理。未経験者でも操作可能なUI設計。
A67: 【A】CRMシート構成（実装済）
A68: No. | B68: シート名 | C68: 役割 | D68: 主な項目
A69: 1 | B69: 顧客マスタ | C69: 顧客情報のDB（20列） | D69: 顧客ID/区分/氏名/敬称/TEL/Mail/住所/紹介元/累計案件数/累計受注額
A70: 2 | B70: 案件管理 | C70: 全案件パイプライン（20列） | D70: 案件ID/顧客ID/案件名/ステータス/経過日数/滞留アラート/金額/担当者
A71: 3 | B71: ダッシュボード | C71: KPI・サマリー・アラート | D71: 7KPIカード/ステータス分布/担当者別/顧客ランキングTOP10
A72: 3 | B72: ダッシュボード | C72: KPI・サマリー・アラート | D72: 受注率 / 月別推移 / ステータス分布 / 滞留アラート
A74: 【B】案件ステータスフロー（7段階）→ 実装済
A75: ① リード | B75: 問合せ・紹介を受けた段階 | C75: 顧客マスタに登録、経過日数カウント開始 | D75: ✅
A76: ② 商談中 | B76: 現地調査・ヒアリング実施中 | C76: ステータス変更日自動記録、経過日数リセット | D76: ✅
A77: ③ 見積作成中 | B77: 見積書を作成中 | C77: 操作パネルから案件シート自動生成→原価入力 | D77: ✅
A78: ④ 見積提出済 | B78: 見積書を顧客に提出 | C78: 提出日自動記録、回答待ち経過日数カウント | D78: ✅
A79: ⑤ 受注 | B79: 成約・契約素成 | C79: 発注書自動出力、実行予算確定 | D79: ✅
A80: ⑥ 失注 | B80: 不成約・見送り | C80: 失注理由記録（次回の改善に活用） | D80: ✅
A81: ⑦ 完工 | B81: 工事完了・引き渡し済み | C81: 工事項目DBに実績蓄積、請求書自動生成 | D81: ✅
A83: 【C】半自動見積フロー（実装済）
A84: ● 操作者： | B84: 顧客選択→案件名入力→担当者→原価タイプ選択+単価・数量入力のみ
A85: ● システム： | B85: 顧客反映/単価自動/金額計算/経過日数/滞留アラート/帳票生成/KPIを全自動
A87: ■ 6. 実装フェーズ（最新版）
A88: Phase | B88: 内容 | C88: 作業内容 | D88: ステータス
A89: Phase 1 | B89: 基盤構築 | C89: マスター設定 + 工事項目DB + 業者DB | D89: ✅ 完了
A90: Phase 2 | B90: CRM構築 | C90: 顧客マスタ + 案件管理 + ダッシュボード | D90: ✅ 完了
A91: Phase 3 | B91: 原価管理+帳票 | C91: 案件テンプレート + 発注書兼請求書 + 操作パネル | D91: ✅ 完了
A92: Phase 4 | B92: UI整備+テスト | C92: シート整理 + 印刷設定 + 行操作ツール + P-003テスト完了 | D92: ✅ 完了
A93: Phase 5 | B93: 蓄積+分析 | C93: DB自動蓄積 + 失注分析 + S表紙連動 + 運用改善 | D93: ✅ 完了

Sheet 請求書
B5: 御 請 求 書
J7: 45931
C10: 株式会社 figaro | F10: 様 | H10: 着手金御請求書
E14: 御請求金額 | F14: ￥ | G14: =I61 -> 2640000 | I14: (税込み）
C20: 工事名： | D20: =Ｓ表紙!D20 -> 吉野様邸 キッチンリフォーム
C22: 工 場 所 ： | D22: =Ｓ表紙!D22 -> 東京都港区南麻布
C24: 有効期間 ： | D24: 30日間
C26: 備考 | D26: お振込手数料のご負担をお願い申し上げます。
B27: 【 振込口座 】西武信用金庫 恵比寿支店（店番103） 普通 2232951 INTER DOOR 株式会社 インタードア （カ
A32: 内 訳 明 細 書
A35: Ｎｏ， | B35: 名称形状 | F35: 数量 | G35: 単位 | H35: 単価 | I35: 金額 | J35: 備考
A36: 1 | B36: 家具工事 | D36: 10月31日 ご入金予定 | I36: 2400000
A37: 2
A38: 3
A39: 4
A40: 5
A41: 6
A42: 7
A43: 8
A44: 9
A45: 10
A46: 11
A47: 12
A48: 13
A49: 14 | K49: 0
A50: 15
A51: 16
A52: 17
A53: 18
A54: 19
A55: 20
A56: 21
A57: 22
A58: 23
A59: 24 | B59: 消費税 | F59: 10 | G59: ％ | I59: =SUM(I36:I58)*0.1 -> 240000
A60: 25
B61: 小計 | I61: =SUM(I36:I60) -> 2640000

Sheet 請書 (2)
A1: 【 請 書 】
AY3: 収 入 印 紙
B4: =Ｓ表紙!C10 -> 矢島不動産管理株式会社 | V4: 殿 | AA4: 2025 | AE4: 年 | AG4: 4 | AI4: 月 | AK4: 12 | AM4: 日
A7: 施 工 場 所 | J7: : | K7: =Ｓ表紙!D22 -> 東京都港区南麻布
A8: 工 事 件 名 | J8: : | K8: =Ｓ表紙!D20 -> 吉野様邸 キッチンリフォーム
A9: 受 渡 期 限 | J9: : | K9: 2025年5月 ～ 2025年5月末
A10: 支 払 条 件 | J10: :
A11: 総 金 額 | J11: : | K11: =+AP41 -> 1573406 | Z11: （消費税含む）
A13: 名 称 | P13: 寸 法 | Y13: 単 位 | AB13: 数 量 | AI13: 単 価 | AP13: 金 額 | AZ13: 備 考
CA14: 08 | CB14: 1 | CC14: 2008 | CE14: 一式
A15: 直接工事費 | Y15: 式 | AB15: 1 | AP15: =SUM(Ｓ表紙!I36:I55) -> 1140400 | CA15: 09 | CB15: 2 | CC15: 2009 | CE15: m
CA16: 10 | CB16: 3 | CC16: 2010 | CE16: ㎥
A17: 現場経費 | Y17: 式 | AB17: 1 | AP17: =SUM(Ｓ表紙!I57) -> 57020 | CA17: 11 | CB17: 4 | CC17: 2011 | CE17: ㎡
CA18: 12 | CB18: 5 | CC18: 2012
A19: 会社経費 | Y19: 式 | AB19: 1 | AP19: =Ｓ表紙!I56 -> 114040 | CA19: 13 | CB19: 6 | CC19: 2013
CA20: 14 | CB20: 7 | CC20: 2014
A21: 現場管理費 | Y21: 式 | AB21: 1 | AP21: =Ｓ表紙!I58 -> 125000 | CA21: 15 | CB21: 8 | CC21: 2015
CA22: 16 | CB22: 9 | CC22: 2016
CA23: 17 | CB23: 10 | CC23: 2017
CA24: 18 | CB24: 11 | CC24: 2018
CA25: 19 | CB25: 12 | CC25: 2019
CA26: 20 | CB26: 13 | CC26: 2020
CB27: 14
CB28: 15
CB29: 16
CB30: 17
CB31: 18
CB32: 19
CB33: 20
CB34: 21
A35: 小 計 | AP35: =SUM(AP13:AY34) -> 1436460 | CB35: 22
CB36: 23
A37: 消 費 税 | AP37: =SUM(AP35)*0.1 -> 143646 | CB37: 24
CB38: 25
A39: お値引き | AP39: =Ｓ表紙!I60 -> -6700 | CB39: 26
CB40: 27
A41: 合 計 | AP41: =SUM(AP35:AY40) -> 1573406 | CB41: 28
CB42: 29
CB43: 30
A44: 【 条 件 】 | CB44: 31
CB45: 20
CB46: 21
CB47: 22
CB48: 23
CB49: 24
A50: 【 振込口座 】 | I50: 西武信用金庫 恵比寿支店（店番103） 普通 2232951 INTER DOOR 株式会社 インタードア （カ | CB50: 25
CB51: 26
CB52: 27
CB53: 28
CB54: 29
CB55: 30
CB56: 31

Sheet 実行予算　雛形
B1: 現場 実行予算表
B3: 発注元 | D3: =Ｓ表紙!C10 -> 矢島不動産管理株式会社 | K3: 着工年月日 | M3: 44966
B4: 所在地 | K4: 完成年月日 | M4: 44966
B5: 現場名 | D5: =Ｓ表紙!D20 -> 吉野様邸 キッチンリフォーム | K5: 予算 | M5: =Ｓ表紙!G14 -> 1573406
B6: 現場住所 | D6: =Ｓ表紙!D22 -> 東京都港区南麻布 | K6: 追加金額
B8: 予 算 | I8: 実 費
B9: 相手先 | E9: 工事内容 | H9: 金 額 | I9: 相手先 | L9: 摘 要 | O9: 金 額
B31: 予 算 合 計 | H31: =SUM(H10:H30) -> 0 | I31: 実 費 合 計 | O31: =SUM(O10:O30) -> 0
B33: 契約金額 | E33: 予算合計 | G33: 差引利益額 | I33: 契約金額 | L33: 予算合計 | N33: 差引利益額
B34: =M5 -> 1573406 | E34: =H31 -> 0 | G34: =B34-E34 -> 1573406 | I34: =SUM(M5,M6) -> 1573406 | L34: =O31 -> 0 | N34: =I34-L34 -> 1573406
B36: 入金
B41: 支払

Sheet 注文書(控)
A1: 【 注 文 書 ( 控 ) 】
B4: =+注文書!B4 -> 株式会社ＬｉｎＫ | V4: 殿 | AA4: =+注文書!AA4 -> 2024 | AE4: 年 | AG4: =+注文書!AG4 -> 4 | AI4: 月 | AK4: =+注文書!AK4 -> 12 | AM4: 日
AZ6: コピー保管 | BE6: 承 認 | BJ6: 作成･保管
A7: 施 工 場 所 | J7: : | K7: =+注文書!K7 -> 東京都港区南麻布 | AZ7: 工事責任者 | BE7: 社 長 | BJ7: 担 当 者
A8: 工 事 件 名 | J8: : | K8: =+注文書!K8 -> 吉野様邸 キッチンリフォーム
A9: 受 渡 期 限 | J9: : | K9: =+注文書!K9 -> 2024年5月 ～ 2024年5月末
A10: 支 払 条 件 | J10: : | K10: 毎月末日締切･翌月21日払い 現金100％
A11: 総 金 額 | J11: : | K11: =+注文書!K11 -> 1573406 | Z11: （消費税含む） | BA11: / | BC11: / | BF11: / | BH11: / | BK11: / | BM11: /
A12: ※ 注文書(控)原本は、総務部で保管･管理し、コピーを作業所管理とする。
A13: 名 称 | P13: 寸 法 | Y13: 単 位 | AB13: 数 量 | AI13: 単 価 | AP13: 金 額 | AZ13: 備 考
CA14: 08 | CB14: 1 | CC14: 2008
A15: =+注文書!A15 -> 直接工事費 | Y15: 式 | AB15: =+注文書!AB15 -> 1 | AP15: =+注文書!AP15 -> 1140400 | CA15: 09 | CB15: 2 | CC15: 2009
CA16: 10 | CB16: 3 | CC16: 2010
A17: =+注文書!A17 -> 現場経費 | Y17: 式 | AB17: =+注文書!AB17 -> 1 | AP17: =+注文書!AP17 -> 57020 | CA17: 11 | CB17: 4 | CC17: 2011
CA18: 12 | CB18: 5 | CC18: 2012
A19: =+注文書!A19 -> 会社経費 | Y19: 式 | AB19: =+注文書!AB19 -> 1 | AP19: =+注文書!AP19 -> 114040 | CA19: 13 | CB19: 6 | CC19: 2013
CA20: 14 | CB20: 7 | CC20: 2014
A21: =+注文書!A21 -> 現場管理費 | Y21: 式 | AB21: =+注文書!AB21 -> 1 | AP21: =+注文書!AP21 -> 125000 | CA21: 15 | CB21: 8 | CC21: 2015
CA22: 16 | CB22: 9 | CC22: 2016
CA23: 17 | CB23: 10 | CC23: 2017
CA24: 18 | CB24: 11 | CC24: 2018
CA25: 19 | CB25: 12 | CC25: 2019
CA26: 20 | CB26: 13 | CC26: 2020
CB27: 14
CB28: 15
CB29: 16
CB30: 17
CB31: 18
CB32: 19
CB33: 20
CB34: 21
A35: 小 計 | AP35: =+注文書!AP35 -> 1436460 | CB35: 22
CB36: 23
A37: 消 費 税 | AP37: =SUM(AP35)*0.1 -> 143646 | CB37: 24
CB38: 25
A39: お値引き | AP39: =Ｓ表紙!I60 -> -6700 | CB39: 26
CB40: 27
A41: 合 計 | AP41: =SUM(AP35:AY40) -> 1573406 | CB41: 28
CB42: 29
CB43: 30
A44: 【 条 件 】 | CB44: 31
G45: □ | H45: =+注文書!H45 -> 0 | CB45: 20
G46: □ | H46: =+注文書!H46 -> 0 | CB46: 21
G47: □ | H47: =+注文書!H47 -> 0 | CB47: 22
G48: □ | H48: =+注文書!H48 -> 0 | CB48: 23
G49: □ | H49: =+注文書!H49 -> 0 | CB49: 24
CB50: 25
CB51: 26
CB52: 27
CB53: 28
CB54: 29
CB55: 30
CB56: 31

Sheet 注文書
A1: 【 注 文 書 】
B4: 株式会社ＬｉｎＫ | V4: 殿 | AA4: =請書!AA4 -> 2024 | AE4: 年 | AG4: =請書!AG4 -> 4 | AI4: 月 | AK4: =請書!AK4 -> 12 | AM4: 日
A7: 施 工 場 所 | J7: : | K7: =請書!K7 -> 東京都港区南麻布
A8: 工 事 件 名 | J8: : | K8: =請書!K8 -> 吉野様邸 キッチンリフォーム
A9: 受 渡 期 限 | J9: : | K9: =請書!K9 -> 2024年5月 ～ 2024年5月末 | AQ9: 住 所
A10: 支 払 条 件 | J10: : | K10: =請書!K10 -> 0 | AQ10: 会社名
A11: 総 金 額 | J11: : | K11: =+AP41 -> 1573406 | Z11: （消費税含む） | AQ11: 代表者名 | BL11: ㊞
A13: 名 称 | P13: 寸 法 | Y13: 単 位 | AB13: 数 量 | AI13: 単 価 | AP13: 金 額 | AZ13: 備 考
CA14: 08 | CB14: 1 | CC14: 2008
A15: 直接工事費 | Y15: 式 | AB15: 1 | AP15: =SUM(Ｓ表紙!I36:I55) -> 1140400 | CA15: 09 | CB15: 2 | CC15: 2009
CA16: 10 | CB16: 3 | CC16: 2010
A17: 現場経費 | Y17: 式 | AB17: 1 | AP17: =SUM(Ｓ表紙!I57) -> 57020 | CA17: 11 | CB17: 4 | CC17: 2011
CA18: 12 | CB18: 5 | CC18: 2012
A19: 会社経費 | Y19: 式 | AB19: 1 | AP19: =Ｓ表紙!I56 -> 114040 | CA19: 13 | CB19: 6 | CC19: 2013
CA20: 14 | CB20: 7 | CC20: 2014
A21: 現場管理費 | Y21: 式 | AB21: 1 | AP21: =Ｓ表紙!I58 -> 125000 | CA21: 15 | CB21: 8 | CC21: 2015
CA22: 16 | CB22: 9 | CC22: 2016
CA23: 17 | CB23: 10 | CC23: 2017
CA24: 18 | CB24: 11 | CC24: 2018
CA25: 19 | CB25: 12 | CC25: 2019
CA26: 20 | CB26: 13 | CC26: 2020
CB27: 14
CB28: 15
CB29: 16
CB30: 17
CB31: 18
CB32: 19
CB33: 20
CB34: 21
A35: 小 計 | AP35: =SUM(AP13:AY34) -> 1436460 | CB35: 22
CB36: 23
A37: 消 費 税 | AP37: =SUM(AP35)*0.1 -> 143646 | CB37: 24
CB38: 25
A39: お値引き | AP39: =Ｓ表紙!I60 -> -6700 | CB39: 26
CB40: 27
A41: 合 計 | AP41: =SUM(AP35:AY40) -> 1573406 | CB41: 28
CB42: 29
CB43: 30
A44: 【 条 件 】 | CB44: 31

Sheet 請書
A1: 【 請 書 】
AY3: 収 入 印 紙
B4: =Ｓ表紙!C10 -> 矢島不動産管理株式会社 | V4: 殿 | AA4: 2024 | AE4: 年 | AG4: 4 | AI4: 月 | AK4: 12 | AM4: 日
A7: 施 工 場 所 | J7: : | K7: =Ｓ表紙!D22 -> 東京都港区南麻布
A8: 工 事 件 名 | J8: : | K8: =Ｓ表紙!D20 -> 吉野様邸 キッチンリフォーム
A9: 受 渡 期 限 | J9: : | K9: 2024年5月 ～ 2024年5月末
A10: 支 払 条 件 | J10: :
A11: 総 金 額 | J11: : | K11: =+AP41 -> 1573406 | Z11: （消費税含む）
A13: 名 称 | P13: 寸 法 | Y13: 単 位 | AB13: 数 量 | AI13: 単 価 | AP13: 金 額 | AZ13: 備 考
CA14: 08 | CB14: 1 | CC14: 2008 | CE14: 一式
A15: 直接工事費 | Y15: 式 | AB15: 1 | AP15: =SUM(Ｓ表紙!I36:I55) -> 1140400 | CA15: 09 | CB15: 2 | CC15: 2009 | CE15: m
CA16: 10 | CB16: 3 | CC16: 2010 | CE16: ㎥
A17: 現場経費 | Y17: 式 | AB17: 1 | AP17: =SUM(Ｓ表紙!I57) -> 57020 | CA17: 11 | CB17: 4 | CC17: 2011 | CE17: ㎡
CA18: 12 | CB18: 5 | CC18: 2012
A19: 会社経費 | Y19: 式 | AB19: 1 | AP19: =Ｓ表紙!I56 -> 114040 | CA19: 13 | CB19: 6 | CC19: 2013
CA20: 14 | CB20: 7 | CC20: 2014
A21: 現場管理費 | Y21: 式 | AB21: 1 | AP21: =Ｓ表紙!I58 -> 125000 | CA21: 15 | CB21: 8 | CC21: 2015
CA22: 16 | CB22: 9 | CC22: 2016
CA23: 17 | CB23: 10 | CC23: 2017
CA24: 18 | CB24: 11 | CC24: 2018
CA25: 19 | CB25: 12 | CC25: 2019
CA26: 20 | CB26: 13 | CC26: 2020
CB27: 14
CB28: 15
CB29: 16
CB30: 17
CB31: 18
CB32: 19
CB33: 20
CB34: 21
A35: 小 計 | AP35: =SUM(AP13:AY34) -> 1436460 | CB35: 22
CB36: 23
A37: 消 費 税 | AP37: =SUM(AP35)*0.1 -> 143646 | CB37: 24
CB38: 25
A39: お値引き | AP39: =Ｓ表紙!I60 -> -6700 | CB39: 26
CB40: 27
A41: 合 計 | AP41: =SUM(AP35:AY40) -> 1573406 | CB41: 28
CB42: 29
CB43: 30
A44: 【 条 件 】 | CB44: 31
CB45: 20
CB46: 21
CB47: 22
CB48: 23
CB49: 24
A50: 【 振込口座 】 | I50: 香川銀行（銀行コード0573） 満濃支店（店番316マンノウ） 普通 3541847 株式会社永光 カ）エイコウ | CB50: 25
CB51: 26
CB52: 27
CB53: 28
CB54: 29
CB55: 30
CB56: 31

Sheet 解体工事
A1: 内 訳 明 細 書
B3: 名称形状 | D3: 数量 | E3: 単位 | F3: 単価 | G3: 金額 | H3: 備考
B4: 解体工事
B5: 発生材処理費 | C5: 混載 | D5: 3 | E5: ㎥ | F5: 20000 | G5: =D5*F5 -> 60000 | K5: 0.1 | L5: =J5*K5 -> 0 | M5: =J5+L5 -> 0
B6: トラック | D6: 1 | E6: 台 | F6: 18000 | G6: =D6*F6 -> 18000 | K6: 0.1 | L6: =J6*K6 -> 0 | M6: =J6+L6 -> 0
B7: 運搬費 | D7: 1 | E7: 人工 | F7: 20000 | G7: =D7*F7 -> 20000 | K7: 0.1 | L7: =J7*K7 -> 0 | M7: =J7+L7 -> 0
K8: 0.1 | L8: =J8*K8 -> 0 | M8: =J8+L8 -> 0
K9: 0.1 | L9: =J9*K9 -> 0 | M9: =J9+L9 -> 0
K10: 0.1 | L10: =J10*K10 -> 0 | M10: =J10+L10 -> 0
K11: 0.1 | L11: =J11*K11 -> 0 | M11: =J11+L11 -> 0
K12: 0.1 | L12: =J12*K12 -> 0 | M12: =J12+L12 -> 0
K13: 0.1 | L13: =J13*K13 -> 0 | M13: =J13+L13 -> 0
K14: 0.1 | L14: =J14*K14 -> 0 | M14: =J14+L14 -> 0
K15: 0.1 | L15: =J15*K15 -> 0 | M15: =J15+L15 -> 0
K16: 0.1 | L16: =J16*K16 -> 0 | M16: =J16+L16 -> 0
K17: 0.1 | L17: =J17*K17 -> 0 | M17: =J17+L17 -> 0
K18: 0.1 | L18: =J18*K18 -> 0 | M18: =J18+L18 -> 0
K19: 0.2 | L19: =J19*K19 -> 0 | M19: =J19+L19 -> 0
... K25: 0.1 | L25: =J25*K25 -> 0 | M25: =J25+L25 -> 0
G26: =M26*J3 -> 0
F27: 小 計 | G27: =SUM(G5:G26) -> 98000

Sheet 産廃費
A1: 内 訳 明 細 書
B3: 名称形状 | D3: 数量 | E3: 単位 | F3: 単価 | G3: 金額 | H3: 備考
B4: 解体工事 | C4: 産廃費用
D5: 1 | E5: 式 | F5: =M5 -> 0 | G5: =D5*F5 -> 0 | K5: 0.2 | L5: =J5*K5 -> 0 | M5: =J5+L5 -> 0
D6: 1 | E6: 式 | F6: =M6 -> 0 | G6: =D6*F6 -> 0 | K6: 0.2 | L6: =J6*K6 -> 0 | M6: =J6+L6 -> 0
D7: 1 | E7: 式 | F7: =M7 -> 0 | G7: =D7*F7 -> 0 | K7: 0.2 | L7: =J7*K7 -> 0 | M7: =J7+L7 -> 0
D8: 1 | E8: 式 | F8: =M8 -> 0 | G8: =D8*F8 -> 0 | K8: 0.2 | L8: =J8*K8 -> 0 | M8: =J8+L8 -> 0
D9: 1 | E9: 式 | F9: =M9 -> 0 | G9: =D9*F9 -> 0 | K9: 0.2 | L9: =J9*K9 -> 0 | M9: =J9+L9 -> 0
D10: 1 | E10: 式 | F10: =M10 -> 0 | G10: =D10*F10 -> 0 | K10: 0.2 | L10: =J10*K10 -> 0 | M10: =J10+L10 -> 0
D11: 1 | E11: 式 | F11: =M11 -> 0 | G11: =D11*F11 -> 0 | K11: 0.2 | L11: =J11*K11 -> 0 | M11: =J11+L11 -> 0
D12: 1 | E12: 式 | F12: =M12 -> 0 | G12: =D12*F12 -> 0 | K12: 0.2 | L12: =J12*K12 -> 0 | M12: =J12+L12 -> 0
D13: 1 | E13: 式 | F13: =M13 -> 0 | G13: =D13*F13 -> 0 | K13: 0.2 | L13: =J13*K13 -> 0 | M13: =J13+L13 -> 0
D14: 1 | E14: 式 | F14: =M14 -> 0 | G14: =D14*F14 -> 0 | K14: 0.2 | L14: =J14*K14 -> 0 | M14: =J14+L14 -> 0
D15: 1 | E15: 式 | F15: =M15 -> 0 | G15: =D15*F15 -> 0 | K15: 0.2 | L15: =J15*K15 -> 0 | M15: =J15+L15 -> 0
D16: 1 | E16: 式 | F16: =M16 -> 0 | G16: =D16*F16 -> 0 | K16: 0.2 | L16: =J16*K16 -> 0 | M16: =J16+L16 -> 0
... D25: 1 | E25: 式 | F25: =M25 -> 0 | G25: =D25*F25 -> 0 | K25: 0.1 | L25: =J25*K25 -> 0 | M25: =J25+L25 -> 0
F27: 小 計 | G27: =SUM(G5:G26) -> 0

Sheet 仮設
A1: 内 訳 明 細 書
B3: 名称形状 | D3: 数量 | E3: 単位 | F3: 単価 | G3: 金額 | H3: 備考
B4: 仮設工事 | G4: =M4*J3 -> 0
D5: 1 | E5: 式 | F5: =M5 -> 0 | G5: =D5*F5 -> 0 | K5: 0.2 | L5: =J5*K5 -> 0 | M5: =J5+L5 -> 0
D6: 1 | E6: 式 | F6: =M6 -> 0 | G6: =D6*F6 -> 0 | K6: 0.2 | L6: =J6*K6 -> 0 | M6: =J6+L6 -> 0
D7: 1 | E7: 式 | F7: =M7 -> 0 | G7: =D7*F7 -> 0 | K7: 0.2 | L7: =J7*K7 -> 0 | M7: =J7+L7 -> 0
D8: 1 | E8: 式 | F8: =M8 -> 0 | G8: =D8*F8 -> 0 | K8: 0.2 | L8: =J8*K8 -> 0 | M8: =J8+L8 -> 0
D9: 1 | E9: 式 | F9: =M9 -> 0 | G9: =D9*F9 -> 0 | K9: 0.2 | L9: =J9*K9 -> 0 | M9: =J9+L9 -> 0
D10: 1 | E10: 式 | F10: =M10 -> 0 | G10: =D10*F10 -> 0 | K10: 0.2 | L10: =J10*K10 -> 0 | M10: =J10+L10 -> 0
D11: 1 | E11: 式 | F11: =M11 -> 0 | G11: =D11*F11 -> 0 | K11: 0.2 | L11: =J11*K11 -> 0 | M11: =J11+L11 -> 0
D12: 1 | E12: 式 | F12: =M12 -> 0 | G12: =D12*F12 -> 0 | K12: 0.2 | L12: =J12*K12 -> 0 | M12: =J12+L12 -> 0
D13: 1 | E13: 式 | F13: =M13 -> 0 | G13: =D13*F13 -> 0 | K13: 0.2 | L13: =J13*K13 -> 0 | M13: =J13+L13 -> 0
D14: 1 | E14: 式 | F14: =M14 -> 0 | G14: =D14*F14 -> 0 | K14: 0.2 | L14: =J14*K14 -> 0 | M14: =J14+L14 -> 0
D15: 1 | E15: 式 | F15: =M15 -> 0 | G15: =D15*F15 -> 0 | K15: 0.2 | L15: =J15*K15 -> 0 | M15: =J15+L15 -> 0
D16: 1 | E16: 式 | F16: =M16 -> 0 | G16: =D16*F16 -> 0 | K16: 0.2 | L16: =J16*K16 -> 0 | M16: =J16+L16 -> 0
... D25: 1 | E25: 式 | F25: =M25 -> 0 | G25: =D25*F25 -> 0 | K25: 0.1 | L25: =J25*K25 -> 0 | M25: =J25+L25 -> 0
F26: =IF(D26=0,0,G26/D26) -> 0
F27: 小 計 | G27: =SUM(G5:G26) -> 0

Sheet 解体後補修箇所
A1: 内 訳 明 細 書
B3: 名称形状 | D3: 数量 | E3: 単位 | F3: 単価 | G3: 金額 | H3: 備考
B4: 解体後補修工事
D5: 1 | E5: 式 | F5: =M5 -> 0 | G5: =D5*F5 -> 0 | K5: 0.2 | L5: =J5*K5 -> 0 | M5: =J5+L5 -> 0
D6: 1 | E6: 式 | F6: =M6 -> 0 | G6: =D6*F6 -> 0 | K6: 0.2 | L6: =J6*K6 -> 0 | M6: =J6+L6 -> 0
D7: 1 | E7: 式 | F7: =M7 -> 0 | G7: =D7*F7 -> 0 | K7: 0.2 | L7: =J7*K7 -> 0 | M7: =J7+L7 -> 0
D8: 1 | E8: 式 | F8: =M8 -> 0 | G8: =D8*F8 -> 0 | K8: 0.2 | L8: =J8*K8 -> 0 | M8: =J8+L8 -> 0
D9: 1 | E9: 式 | F9: =M9 -> 0 | G9: =D9*F9 -> 0 | K9: 0.2 | L9: =J9*K9 -> 0 | M9: =J9+L9 -> 0
D10: 1 | E10: 式 | F10: =M10 -> 0 | G10: =D10*F10 -> 0 | K10: 0.2 | L10: =J10*K10 -> 0 | M10: =J10+L10 -> 0
D11: 1 | E11: 式 | F11: =M11 -> 0 | G11: =D11*F11 -> 0 | K11: 0.2 | L11: =J11*K11 -> 0 | M11: =J11+L11 -> 0
D12: 1 | E12: 式 | F12: =M12 -> 0 | G12: =D12*F12 -> 0 | K12: 0.2 | L12: =J12*K12 -> 0 | M12: =J12+L12 -> 0
D13: 1 | E13: 式 | F13: =M13 -> 0 | G13: =D13*F13 -> 0 | K13: 0.2 | L13: =J13*K13 -> 0 | M13: =J13+L13 -> 0
D14: 1 | E14: 式 | F14: =M14 -> 0 | G14: =D14*F14 -> 0 | K14: 0.2 | L14: =J14*K14 -> 0 | M14: =J14+L14 -> 0
D15: 1 | E15: 式 | F15: =M15 -> 0 | G15: =D15*F15 -> 0 | K15: 0.2 | L15: =J15*K15 -> 0 | M15: =J15+L15 -> 0
D16: 1 | E16: 式 | F16: =M16 -> 0 | G16: =D16*F16 -> 0 | K16: 0.2 | L16: =J16*K16 -> 0 | M16: =J16+L16 -> 0
... D25: 1 | E25: 式 | F25: =M25 -> 0 | G25: =D25*F25 -> 0 | K25: 0.1 | L25: =J25*K25 -> 0 | M25: =J25+L25 -> 0
F27: 小 計 | G27: =SUM(G5:G26) -> 0

Sheet 新規壁工事
A1: 内 訳 明 細 書
B3: 名称形状 | D3: 数量 | E3: 単位 | F3: 単価 | G3: 金額 | H3: 備考
B4: 新規壁工事 | G4: =M4*J3 -> 0
D5: 1 | E5: 式 | G5: =D5*F5 -> 0 | K5: 0.2 | L5: =J5*K5 -> 0 | M5: =J5+L5 -> 0
D6: 1 | E6: 式 | G6: =D6*F6 -> 0 | K6: 0.2 | L6: =J6*K6 -> 0 | M6: =J6+L6 -> 0
D7: 1 | E7: 式 | G7: =D7*F7 -> 0 | K7: 0.2 | L7: =J7*K7 -> 0 | M7: =J7+L7 -> 0
D8: 1 | E8: 式 | G8: =D8*F8 -> 0 | K8: 0.2 | L8: =J8*K8 -> 0 | M8: =J8+L8 -> 0
D9: 1 | E9: 式 | F9: =M9 -> 0 | G9: =D9*F9 -> 0 | K9: 0.2 | L9: =J9*K9 -> 0 | M9: =J9+L9 -> 0
D10: 1 | E10: 式 | F10: =M10 -> 0 | G10: =D10*F10 -> 0 | K10: 0.2 | L10: =J10*K10 -> 0 | M10: =J10+L10 -> 0
D11: 1 | E11: 式 | F11: =M11 -> 0 | G11: =D11*F11 -> 0 | K11: 0.2 | L11: =J11*K11 -> 0 | M11: =J11+L11 -> 0
D12: 1 | E12: 式 | F12: =M12 -> 0 | G12: =D12*F12 -> 0 | K12: 0.2 | L12: =J12*K12 -> 0 | M12: =J12+L12 -> 0
D13: 1 | E13: 式 | F13: =M13 -> 0 | G13: =D13*F13 -> 0 | K13: 0.2 | L13: =J13*K13 -> 0 | M13: =J13+L13 -> 0
D14: 1 | E14: 式 | F14: =M14 -> 0 | G14: =D14*F14 -> 0 | K14: 0.2 | L14: =J14*K14 -> 0 | M14: =J14+L14 -> 0
D15: 1 | E15: 式 | F15: =M15 -> 0 | G15: =D15*F15 -> 0 | K15: 0.2 | L15: =J15*K15 -> 0 | M15: =J15+L15 -> 0
D16: 1 | E16: 式 | F16: =M16 -> 0 | G16: =D16*F16 -> 0 | K16: 0.2 | L16: =J16*K16 -> 0 | M16: =J16+L16 -> 0
D17: 1 | E17: 式 | F17: =M17 -> 0 | G17: =D17*F17 -> 0 | K17: 0.2 | L17: =J17*K17 -> 0 | M17: =J17+L17 -> 0
D18: 1 | E18: 式 | F18: =M18 -> 0 | G18: =D18*F18 -> 0 | K18: 0.2 | L18: =J18*K18 -> 0 | M18: =J18+L18 -> 0
D19: 1 | E19: 式 | F19: =M19 -> 0 | G19: =D19*F19 -> 0 | K19: 0.2 | L19: =J19*K19 -> 0 | M19: =J19+L19 -> 0
D20: 1 | E20: 式 | F20: =M20 -> 0 | G20: =D20*F20 -> 0 | K20: 0.2 | L20: =J20*K20 -> 0 | M20: =J20+L20 -> 0
... D25: 1 | E25: 式 | F25: =M25 -> 0 | G25: =D25*F25 -> 0 | K25: 0.1 | L25: =J25*K25 -> 0 | M25: =J25+L25 -> 0
F27: 小 計 | G27: =SUM(G5:G26) -> 0

Sheet 造作工事
A1: 内 訳 明 細 書
B3: 名称形状 | D3: 数量 | E3: 単位 | F3: 単価 | G3: 金額 | H3: 備考
B4: 造作関係 | G4: =M4*J3 -> 0
B5: 階段室下 シナベニヤ ｔ12 材料費 | D5: 4 | E5: 枚 | F5: 11000 | G5: =D5*F5 -> 44000 | K5: 0.2 | L5: =J5*K5 -> 0 | M5: =J5+L5 -> 0
B6: 階段室下 間接照明隠蔽用 モクヒモ材 | D6: 1 | E6: 本 | F6: 15000 | G6: =D6*F6 -> 15000 | K6: 0.2 | L6: =J6*K6 -> 0 | M6: =J6+L6 -> 0
B7: シナベニヤ ダボ掘り込み 取付 | D7: 1 | E7: 式 | F7: 25000 | G7: =D7*F7 -> 25000 | K7: 0.2 | L7: =J7*K7 -> 0 | M7: =J7+L7 -> 0
B8: 折り上げ天井部 ナラ突板 | C8: 2ｍ | D8: 4 | E8: 本 | F8: 18500 | G8: =D8*F8 -> 74000 | K8: 0.2 | L8: =J8*K8 -> 0 | M8: =J8+L8 -> 0
B9: 労務費 | D9: 1 | E9: 人工 | F9: 30000 | G9: =D9*F9 -> 30000 | K9: 0.2 | L9: =J9*K9 -> 0 | M9: =J9+L9 -> 0
B10: エントランス 下地造作（間接照明下地） ベニヤ | D10: 1 | E10: 箇所 | K10: 0.2 | L10: =J10*K10 -> 0 | M10: =J10+L10 -> 0
B11: 間接照明 L型羽出し造作 | C11: ナラ突板 | D11: 1 | E11: 組 | K11: 0.2 | L11: =J11*K11 -> 0 | M11: =J11+L11 -> 0
B12: 副資材 | D12: 1 | E12: 式 | K12: 0.2 | L12: =J12*K12 -> 0 | M12: =J12+L12 -> 0
B13: 資材運搬搬入費 | D13: 1 | E13: 式 | K13: 0.2 | L13: =J13*K13 -> 0 | M13: =J13+L13 -> 0
F14: =M14 -> 0 | G14: =D14*F14 -> 0 | K14: 0.2 | L14: =J14*K14 -> 0 | M14: =J14+L14 -> 0
B15: ウッドデッキ工事 労務費 | C15: 材料支給 | D15: 6 | E15: 人工 | K15: 0.2 | L15: =J15*K15 -> 0 | M15: =J15+L15 -> 0
B16: 副資材 糊 パッキン | D16: 1 | E16: 式 | K16: 0.2 | L16: =J16*K16 -> 0 | M16: =J16+L16 -> 0
B17: 運搬搬入費 | D17: 1 | E17: 人工 | K17: 0.2 | L17: =J17*K17 -> 0 | M17: =J17+L17 -> 0
F18: =M18 -> 0 | G18: =D18*F18 -> 0 | K18: 0.2 | L18: =J18*K18 -> 0 | M18: =J18+L18 -> 0
F19: =M19 -> 0 | G19: =D19*F19 -> 0 | K19: 0.2 | L19: =J19*K19 -> 0 | M19: =J19+L19 -> 0
F20: =M20 -> 0 | G20: =D20*F20 -> 0 | K20: 0.2 | L20: =J20*K20 -> 0 | M20: =J20+L20 -> 0
F21: =M21 -> 0 | G21: =D21*F21 -> 0 | K21: 0.2 | L21: =J21*K21 -> 0 | M21: =J21+L21 -> 0
F22: =M22 -> 0 | G22: =D22*F22 -> 0 | K22: 0.2 | L22: =J22*K22 -> 0 | M22: =J22+L22 -> 0
F23: =M23 -> 0 | G23: =D23*F23 -> 0 | K23: 0.2 | L23: =J23*K23 -> 0 | M23: =J23+L23 -> 0
F24: =M24 -> 0 | G24: =D24*F24 -> 0 | K24: 0.2 | L24: =J24*K24 -> 0 | M24: =J24+L24 -> 0
F25: =M25 -> 0 | G25: =D25*F25 -> 0 | K25: 0.1 | L25: =J25*K25 -> 0 | M25: =J25+L25 -> 0
F26: =IF(D26=0,0,G26/D26) -> 0
F27: 小 計 | G27: =SUM(G5:G26) -> 188000

Sheet 下地工事
A1: 内 訳 明 細 書
B3: 名称形状 | D3: 数量 | E3: 単位 | F3: 単価 | G3: 金額 | H3: 備考
B4: 下地工事 | G4: =M4*J3 -> 0
D5: 1 | E5: 式 | F5: =M5 -> 0 | G5: =D5*F5 -> 0 | K5: 0.2 | L5: =J5*K5 -> 0 | M5: =J5+L5 -> 0
D6: 1 | E6: 式 | F6: =M6 -> 0 | G6: =D6*F6 -> 0 | K6: 0.2 | L6: =J6*K6 -> 0 | M6: =J6+L6 -> 0
D7: 1 | E7: 式 | F7: =M7 -> 0 | G7: =D7*F7 -> 0 | K7: 0.2 | L7: =J7*K7 -> 0 | M7: =J7+L7 -> 0
D8: 1 | E8: 式 | F8: =M8 -> 0 | G8: =D8*F8 -> 0 | K8: 0.2 | L8: =J8*K8 -> 0 | M8: =J8+L8 -> 0
D9: 1 | E9: 式 | F9: =M9 -> 0 | G9: =D9*F9 -> 0 | K9: 0.2 | L9: =J9*K9 -> 0 | M9: =J9+L9 -> 0
D10: 1 | E10: 式 | F10: =M10 -> 0 | G10: =D10*F10 -> 0 | K10: 0.2 | L10: =J10*K10 -> 0 | M10: =J10+L10 -> 0
D11: 1 | E11: 式 | F11: =M11 -> 0 | G11: =D11*F11 -> 0 | K11: 0.2 | L11: =J11*K11 -> 0 | M11: =J11+L11 -> 0
D12: 1 | E12: 式 | F12: =M12 -> 0 | G12: =D12*F12 -> 0 | K12: 0.2 | L12: =J12*K12 -> 0 | M12: =J12+L12 -> 0
D13: 1 | E13: 式 | F13: =M13 -> 0 | G13: =D13*F13 -> 0 | K13: 0.2 | L13: =J13*K13 -> 0 | M13: =J13+L13 -> 0
D14: 1 | E14: 式 | F14: =M14 -> 0 | G14: =D14*F14 -> 0 | K14: 0.2 | L14: =J14*K14 -> 0 | M14: =J14+L14 -> 0
D15: 1 | E15: 式 | F15: =M15 -> 0 | G15: =D15*F15 -> 0 | K15: 0.2 | L15: =J15*K15 -> 0 | M15: =J15+L15 -> 0
D16: 1 | E16: 式 | F16: =M16 -> 0 | G16: =D16*F16 -> 0 | K16: 0.2 | L16: =J16*K16 -> 0 | M16: =J16+L16 -> 0
... D25: 1 | E25: 式 | F25: =M25 -> 0 | G25: =D25*F25 -> 0 | K25: 0.1 | L25: =J25*K25 -> 0 | M25: =J25+L25 -> 0
F27: 小 計 | G27: =SUM(G5:G26) -> 0

Sheet 建具工事
A1: 内 訳 明 細 書
B3: 名称形状 | D3: 数量 | E3: 単位 | F3: 単価 | G3: 金額 | H3: 備考
B4: 建具工事 | G4: =M4*J3 -> 0
B5: 1Fエントランス 障子 | C5: 944*572 金物含む | D5: 1 | E5: 枚 | K5: 0.2 | L5: =J5*K5 -> 0 | M5: =J5+L5 -> 0
B6: 1Fエントランス 障子 | C6: 2200*600*25 金物含む | D6: 1 | E6: 枚 | K6: 0.2 | L6: =J6*K6 -> 0 | M6: =J6+L6 -> 0
B7: 1F-2F踊り場 障子 | C7: 797*474 金物含む | D7: 1 | E7: 枚 | F7: 96520 | G7: =D7*F7 -> 96520 | K7: 0.2 | L7: =J7*K7 -> 0 | M7: =J7+L7 -> 0
B8: 2F廊下 障子 | C8: 500*572 金物含む | D8: 2 | E8: 枚 | F8: 94500 | G8: =D8*F8 -> 189000 | K8: 0.2 | L8: =J8*K8 -> 0 | M8: =J8+L8 -> 0
B9: 2F廊下+2Fキッチン部分 障子 | C9: 2064*575 金物含む | D9: 2 | E9: 枚 | F9: 166500 | G9: =D9*F9 -> 333000 | K9: 0.2 | L9: =J9*K9 -> 0 | M9: =J9+L9 -> 0
B10: WD1 既存建具枠+建具 塗装 | C10: 既存再利用 下地処理 プライマー含む | D10: 1 | E10: 本 | K10: 0.2 | L10: =J10*K10 -> 0 | M10: =J10+L10 -> 0
B11: WD2 新規建具 ナラ突板 | C11: 2121*667*36 金物 取手 枠 込み | D11: 1 | E11: 組 | F11: 200000 | G11: =D11*F11 -> 200000 | K11: 0.2 | L11: =J11*K11 -> 0 | M11: =J11+L11 -> 0
B12: WD3 新規引き戸 塗装仕上げ | C12: 2178*650*36 金物 取手含む | D12: 1 | E12: 組 | F12: 180000 | G12: =D12*F12 -> 180000 | K12: 0.2 | L12: =J12*K12 -> 0 | M12: =J12+L12 -> 0
B13: 同上 新規枠 塗装 | C13: 1710*250*30 | D13: 1 | E13: 組 | F13: 50000 | G13: =D13*F13 -> 50000 | K13: 0.2 | L13: =J13*K13 -> 0 | M13: =J13+L13 -> 0
B14: レール埋め込み用 シナ枠 | C14: 2000*52*35 | D14: 1 | E14: 本 | F14: 35000 | G14: =D14*F14 -> 35000 | K14: 0.2 | L14: =J14*K14 -> 0 | M14: =J14+L14 -> 0
B15: 収納内部 目隠しパネル メラミン | C15: 脱着式 | D15: 1 | E15: 枚 | F15: 48550 | G15: =D15*F15 -> 48550 | K15: 0.2 | L15: =J15*K15 -> 0 | M15: =J15+L15 -> 0
B16: 取付 現場加工費 枠取付 建具つり込み天井解体 PB復旧含む（仕上げ別途） | D16: 8 | E16: 人工 | K16: 0.2 | L16: =J16*K16 -> 0 | M16: =J16+L16 -> 0
B17: 運搬費 | C17: 新規建具3回 | D17: 1 | E17: 式 | F17: 85000 | G17: =D17*F17 -> 85000 | K17: 0.2 | L17: =J17*K17 -> 0 | M17: =J17+L17 -> 0
B18: 搬入費 | D18: 1 | E18: 式 | F18: 25000 | G18: =D18*F18 -> 25000 | K18: 0.2 | L18: =J18*K18 -> 0 | M18: =J18+L18 -> 0
B19: 副資材 | D19: 1 | E19: 式 | F19: 15200 | G19: =D19*F19 -> 15200 | K19: 0.2 | L19: =J19*K19 -> 0 | M19: =J19+L19 -> 0
B20: 発生材処理費 | D20: 1 | E20: 式 | F20: 6850 | G20: =D20*F20 -> 6850 | K20: 0.2 | L20: =J20*K20 -> 0 | M20: =J20+L20 -> 0
F21: =M21 -> 0 | G21: =D21*F21 -> 0 | K21: 0.2 | L21: =J21*K21 -> 0 | M21: =J21+L21 -> 0
F22: =M22 -> 0 | G22: =D22*F22 -> 0 | K22: 0.2 | L22: =J22*K22 -> 0 | M22: =J22+L22 -> 0
F23: =M23 -> 0 | G23: =D23*F23 -> 0 | K23: 0.2 | L23: =J23*K23 -> 0 | M23: =J23+L23 -> 0
F24: =M24 -> 0 | G24: =D24*F24 -> 0 | K24: 0.2 | L24: =J24*K24 -> 0 | M24: =J24+L24 -> 0
F25: =M25 -> 0 | G25: =D25*F25 -> 0 | K25: 0.1 | L25: =J25*K25 -> 0 | M25: =J25+L25 -> 0
F26: =IF(D26=0,0,G26/D26) -> 0
F27: 小 計 | G27: =SUM(G5:G26) -> 1264120

Sheet 家具
A1: 内 訳 明 細 書
B3: 名称形状 | D3: 数量 | E3: 単位 | F3: 単価 | G3: 金額 | H3: 備考
B4: 家具工事 | G4: =M4*J3 -> 0
B5: 収納内部 引き出し付き什器 | C5: スライドレール 取手金物込み | D5: 1 | E5: 台 | F5: 248500 | G5: =D5*F5 -> 248500 | K5: 0.2 | L5: =J5*K5 -> 0 | M5: =J5+L5 -> 0
B6: 同上 天板 タイル 材料費 | C6: セラミックタイル 品番不明 | D6: 1 | E6: 式 | F6: 60000 | G6: =D6*F6 -> 60000 | H6: 概算 | K6: 0.2 | L6: =J6*K6 -> 0 | M6: =J6+L6 -> 0
B7: 同上現場加工費 | D7: 1 | E7: 式 | F7: 35000 | G7: =D7*F7 -> 35000 | K7: 0.2 | L7: =J7*K7 -> 0 | M7: =J7+L7 -> 0
B8: タイル配送料 | D8: 1 | E8: 式 | F8: 6500 | G8: =D8*F8 -> 6500 | K8: 0.2 | L8: =J8*K8 -> 0 | M8: =J8+L8 -> 0
B9: 収納内部 ナラ突板 棚板 | D9: 2 | E9: 枚 | F9: 16250 | G9: =D9*F9 -> 32500 | K9: 0.2 | L9: =J9*K9 -> 0 | M9: =J9+L9 -> 0
B10: 棚柱 ロイヤル | D10: 2 | E10: 本 | F10: 5550 | G10: =D10*F10 -> 11100 | K10: 0.2 | L10: =J10*K10 -> 0 | M10: =J10+L10 -> 0
B11: 棚受け D250程度 | D11: 4 | E11: 本 | F11: 2530 | G11: =D11*F11 -> 10120 | K11: 0.2 | L11: =J11*K11 -> 0 | M11: =J11+L11 -> 0
B12: SUSポール 38π | D12: 1 | E12: 式 | F12: 8560 | G12: =D12*F12 -> 8560 | K12: 0.2 | L12: =J12*K12 -> 0 | M12: =J12+L12 -> 0
B13: ポール受金物 | D13: 2 | E13: 個 | F13: 560 | G13: =D13*F13 -> 1120 | K13: 0.2 | L13: =J13*K13 -> 0 | M13: =J13+L13 -> 0
B14: ドロワー 本体代 | D14: 1 | E14: 台 | F14: 224850 | G14: =D14*F14 -> 224850 | H14: 先行配線別途 | K14: 0.2 | L14: =J14*K14 -> 0 | M14: =J14+L14 -> 0
B15: ミラー | D15: 1 | E15: 枚 | F15: 8560 | G15: =D15*F15 -> 8560 | K15: 0.2 | L15: =J15*K15 -> 0 | M15: =J15+L15 -> 0
B16: 大型障子 本体代 ワーロン | C16: 1800*1500ｘ2 金物込み | D16: 1 | E16: 組 | F16: 466500 | G16: =D16*F16 -> 466500 | K16: 0.2 | L16: =J16*K16 -> 0 | M16: =J16+L16 -> 0
B17: 障子横 造作壁 ナラ突板 | D17: 1 | E17: 組 | F17: 68950 | G17: =D17*F17 -> 68950 | K17: 0.2 | L17: =J17*K17 -> 0 | M17: =J17+L17 -> 0
B18: ベッド土台 ヘッドパネル | C18: ナラ突板 マットレス下脱着式 6枚分割 | D18: 1 | E18: 組 | F18: 178560 | G18: =D18*F18 -> 178560 | K18: 0.2 | L18: =J18*K18 -> 0 | M18: =J18+L18 -> 0
B19: サイドボード ナラ突板 | C19: 照明、コンセントスイッチ、支給 | D19: 2 | E19: 台 | F19: 78660 | G19: =D19*F19 -> 157320 | H19: 先行配線別途 | K19: 0.2 | L19: =J19*K19 -> 0 | M19: =J19+L19 -> 0
B20: ベット上 壁面パネル | C20: ナラ突板 マットレス下脱着式 | D20: 1 | E20: 式 | F20: 177850 | G20: =D20*F20 -> 177850 | K20: 0.2 | L20: =J20*K20 -> 0 | M20: =J20+L20 -> 0
K21: 0.2 | L21: =J21*K21 -> 0 | M21: =J21+L21 -> 0
K22: 0.2 | L22: =J22*K22 -> 0 | M22: =J22+L22 -> 0
K23: 0.2 | L23: =J23*K23 -> 0 | M23: =J23+L23 -> 0
K24: 0.2 | L24: =J24*K24 -> 0 | M24: =J24+L24 -> 0
K25: 0.1 | L25: =J25*K25 -> 0 | M25: =J25+L25 -> 0
F26: =IF(D26=0,0,G26/D26) -> 0 | G26: =D26*F26 -> 0
F27: 小 計 | G27: =SUM(G5:G26) -> 1695990
A31: 内 訳 明 細 書
B33: 名称形状 | D33: 数量 | E33: 単位 | F33: 単価 | G33: 金額 | H33: 備考
B34: 家具工事 | G34: =M34*J33 -> 0
B35: ベッドフレーム土台（6分割パネル下） | D35: 1 | E35: 組 | F35: 65000 | G35: =D35*F35 -> 65000
B36: ベッドフレーム 幕板 ナラ突板 | C36: 150*2200*20 | D36: 3 | E36: 本 | F36: 28500 | G36: =D36*F36 -> 85500
B37: ヘッドボード ナラ突板 | C37: 1000*2375*100 | D37: 1 | E37: 組 | F37: 76500 | G37: =D37*F37 -> 76500
B38: アクリル板 | C38: 158*3*2375 | D38: 2 | E38: 枚 | F38: 10000 | G38: =D38*F38 -> 20000
B39: クッション 材料支給 | C39: 取付内装側 | G39: =D39*F39 -> 0
B40: 洗面台 ドレッサー コーリアン | D40: 1 | E40: 枚 | F40: 56000 | G40: =D40*F40 -> 56000
B41: 洗面台 ドレッサー 本体代 | C41: 925*550*600 | D41: 1 | E41: 台 | F41: 135000 | G41: =D41*F41 -> 135000
B42: 洗面ボウル | D42: 1 | E42: 台 | F42: 69000 | G42: =D42*F42 -> 69000
B43: 排水 給水 金物 | D43: 1 | E43: 式 | F43: 20000 | G43: =D43*F43 -> 20000
B44: 水栓 | D44: 1 | E44: 台 | F44: 46500 | G44: =D44*F44 -> 46500
B45: 姿見収納 本体代 | C45: 600*800*137 | D45: 1 | E45: 台 | F45: 150000 | G45: =D45*F45 -> 150000
B46: 取付 現場加工費 | D46: 11 | E46: 人工 | F46: 30000 | G46: =D46*F46 -> 330000
B47: 水回り繋ぎ込み 既存給排水管 切り回し タイル前脱着 | D47: 3 | E47: 人工 | F47: 35000 | G47: =D47*F47 -> 105000
B48: 副資材 発生材処理費 | D48: 1 | E48: 式 | F48: 11200 | G48: =D48*F48 -> 11200
B49: 搬入費 | D49: 2 | E49: 人工 | F49: 24000 | G49: =D49*F49 -> 48000
B50: 運搬費 | C50: 4ｔ 2回分 | D50: 1 | E50: 式 | F50: 100000 | G50: =D50*F50 -> 100000
F57: 小 計 | G57: =SUM(G35:G56) -> 1317700

Sheet 床
A1: 内 訳 明 細 書
B3: 名称形状 | D3: 数量 | E3: 単位 | F3: 単価 | G3: 金額 | H3: 備考
B4: 床工事 | G4: =M4*J3 -> 0
D5: 1 | E5: 式 | F5: =M5 -> 0 | G5: =D5*F5 -> 0 | K5: 0.2 | L5: =J5*K5 -> 0 | M5: =J5+L5 -> 0
D6: 1 | E6: 式 | F6: =M6 -> 0 | G6: =D6*F6 -> 0 | K6: 0.2 | L6: =J6*K6 -> 0 | M6: =J6+L6 -> 0
D7: 1 | E7: 式 | F7: =M7 -> 0 | G7: =D7*F7 -> 0 | K7: 0.2 | L7: =J7*K7 -> 0 | M7: =J7+L7 -> 0
D8: 1 | E8: 式 | F8: =M8 -> 0 | G8: =D8*F8 -> 0 | K8: 0.2 | L8: =J8*K8 -> 0 | M8: =J8+L8 -> 0
D9: 1 | E9: 式 | F9: =M9 -> 0 | G9: =D9*F9 -> 0 | K9: 0.2 | L9: =J9*K9 -> 0 | M9: =J9+L9 -> 0
D10: 1 | E10: 式 | F10: =M10 -> 0 | G10: =D10*F10 -> 0 | K10: 0.2 | L10: =J10*K10 -> 0 | M10: =J10+L10 -> 0
D11: 1 | E11: 式 | F11: =M11 -> 0 | G11: =D11*F11 -> 0 | K11: 0.2 | L11: =J11*K11 -> 0 | M11: =J11+L11 -> 0
D12: 1 | E12: 式 | F12: =M12 -> 0 | G12: =D12*F12 -> 0 | K12: 0.2 | L12: =J12*K12 -> 0 | M12: =J12+L12 -> 0
D13: 1 | E13: 式 | F13: =M13 -> 0 | G13: =D13*F13 -> 0 | K13: 0.2 | L13: =J13*K13 -> 0 | M13: =J13+L13 -> 0
D14: 1 | E14: 式 | F14: =M14 -> 0 | G14: =D14*F14 -> 0 | K14: 0.2 | L14: =J14*K14 -> 0 | M14: =J14+L14 -> 0
D15: 1 | E15: 式 | F15: =M15 -> 0 | G15: =D15*F15 -> 0 | K15: 0.2 | L15: =J15*K15 -> 0 | M15: =J15+L15 -> 0
D16: 1 | E16: 式 | F16: =M16 -> 0 | G16: =D16*F16 -> 0 | K16: 0.2 | L16: =J16*K16 -> 0 | M16: =J16+L16 -> 0
... D25: 1 | E25: 式 | F25: =M25 -> 0 | G25: =D25*F25 -> 0 | K25: 0.1 | L25: =J25*K25 -> 0 | M25: =J25+L25 -> 0
F26: =IF(D26=0,0,G26/D26) -> 0
F27: 小 計 | G27: =SUM(G5:G26) -> 0

Sheet 電気設備‘
A1: 内 訳 明 細 書
B3: 名称形状 | D3: 数量 | E3: 単位 | F3: 単価 | G3: 金額 | H3: 備考
B4: 電気設備工事 | G4: =M4*J3 -> 0
B5: 家具取付時 照明器具関係繋ぎ込み 新規先行配線含む | D5: 4 | E5: 人工 | K5: 0.2 | L5: =J5*K5 -> 0 | M5: =J5+L5 -> 0
B6: 器具支給 先行配線別途 | F6: =M6 -> 0 | G6: =D6*F6 -> 0 | K6: 0.2 | L6: =J6*K6 -> 0 | M6: =J6+L6 -> 0
B7: 階段下収納 間接照明 本体代 | D7: 1 | E7: 本 | F7: 26500 | G7: =D7*F7 -> 26500 | K7: 0.2 | L7: =J7*K7 -> 0 | M7: =J7+L7 -> 0
B8: ベッドヘッド 間接照明 本体代 | D8: 2 | E8: 本 | F8: 26500 | G8: =D8*F8 -> 53000 | K8: 0.2 | L8: =J8*K8 -> 0 | M8: =J8+L8 -> 0
B9: 障子後ろ 間接照明 本体代 | D9: 2 | E9: 本 | F9: 26500 | G9: =D9*F9 -> 53000 | K9: 0.2 | L9: =J9*K9 -> 0 | M9: =J9+L9 -> 0
B10: コンセント 本体代 | D10: 2 | E10: 台 | F10: 2500 | G10: =D10*F10 -> 5000 | K10: 0.2 | L10: =J10*K10 -> 0 | M10: =J10+L10 -> 0
B11: 折り上げ天井 間接照明 本体代 | D11: 4 | E11: 本 | F11: 26500 | G11: =D11*F11 -> 106000 | K11: 0.2 | L11: =J11*K11 -> 0 | M11: =J11+L11 -> 0
B12: トランス | D12: 4 | E12: 台 | K12: 0.2 | L12: =J12*K12 -> 0 | M12: =J12+L12 -> 0
B13: エントランス 羽出し間接照明 本体代 | D13: 4 | E13: 本 | K13: 0.2 | L13: =J13*K13 -> 0 | M13: =J13+L13 -> 0
F14: =M14 -> 0 | G14: =D14*F14 -> 0 | K14: 0.2 | L14: =J14*K14 -> 0 | M14: =J14+L14 -> 0
F15: =M15 -> 0 | G15: =D15*F15 -> 0 | K15: 0.2 | L15: =J15*K15 -> 0 | M15: =J15+L15 -> 0
F16: =M16 -> 0 | G16: =D16*F16 -> 0 | K16: 0.2 | L16: =J16*K16 -> 0 | M16: =J16+L16 -> 0
F17: =M17 -> 0 | G17: =D17*F17 -> 0 | K17: 0.2 | L17: =J17*K17 -> 0 | M17: =J17+L17 -> 0
F18: =M18 -> 0 | G18: =D18*F18 -> 0 | K18: 0.2 | L18: =J18*K18 -> 0 | M18: =J18+L18 -> 0
F19: =M19 -> 0 | G19: =D19*F19 -> 0 | K19: 0.2 | L19: =J19*K19 -> 0 | M19: =J19+L19 -> 0
F20: =M20 -> 0 | G20: =D20*F20 -> 0 | K20: 0.2 | L20: =J20*K20 -> 0 | M20: =J20+L20 -> 0
F21: =M21 -> 0 | G21: =D21*F21 -> 0 | K21: 0.2 | L21: =J21*K21 -> 0 | M21: =J21+L21 -> 0
F22: =M22 -> 0 | G22: =D22*F22 -> 0 | K22: 0.2 | L22: =J22*K22 -> 0 | M22: =J22+L22 -> 0
F23: =M23 -> 0 | G23: =D23*F23 -> 0 | K23: 0.2 | L23: =J23*K23 -> 0 | M23: =J23+L23 -> 0
F24: =M24 -> 0 | G24: =D24*F24 -> 0 | K24: 0.2 | L24: =J24*K24 -> 0 | M24: =J24+L24 -> 0
F25: =M25 -> 0 | G25: =D25*F25 -> 0 | K25: 0.1 | L25: =J25*K25 -> 0 | M25: =J25+L25 -> 0
F27: 小 計 | G27: =SUM(G5:G26) -> 243500

Sheet 空調
A1: 内 訳 明 細 書
B3: 名称形状 | D3: 数量 | E3: 単位 | F3: 単価 | G3: 金額 | H3: 備考
B4: 空調工事 | G4: =M4*J3 -> 0
D5: 1 | E5: 式 | F5: =M5 -> 0 | G5: =D5*F5 -> 0 | K5: 0.2 | L5: =J5*K5 -> 0 | M5: =J5+L5 -> 0
D6: 1 | E6: 式 | F6: =M6 -> 0 | G6: =D6*F6 -> 0 | K6: 0.2 | L6: =J6*K6 -> 0 | M6: =J6+L6 -> 0
D7: 1 | E7: 式 | F7: =M7 -> 0 | G7: =D7*F7 -> 0 | K7: 0.2 | L7: =J7*K7 -> 0 | M7: =J7+L7 -> 0
D8: 1 | E8: 式 | F8: =M8 -> 0 | G8: =D8*F8 -> 0 | K8: 0.2 | L8: =J8*K8 -> 0 | M8: =J8+L8 -> 0
D9: 1 | E9: 式 | F9: =M9 -> 0 | G9: =D9*F9 -> 0 | K9: 0.2 | L9: =J9*K9 -> 0 | M9: =J9+L9 -> 0
D10: 1 | E10: 式 | F10: =M10 -> 0 | G10: =D10*F10 -> 0 | K10: 0.2 | L10: =J10*K10 -> 0 | M10: =J10+L10 -> 0
D11: 1 | E11: 式 | F11: =M11 -> 0 | G11: =D11*F11 -> 0 | K11: 0.2 | L11: =J11*K11 -> 0 | M11: =J11+L11 -> 0
D12: 1 | E12: 式 | F12: =M12 -> 0 | G12: =D12*F12 -> 0 | K12: 0.2 | L12: =J12*K12 -> 0 | M12: =J12+L12 -> 0
D13: 1 | E13: 式 | F13: =M13 -> 0 | G13: =D13*F13 -> 0 | K13: 0.2 | L13: =J13*K13 -> 0 | M13: =J13+L13 -> 0
D14: 1 | E14: 式 | F14: =M14 -> 0 | G14: =D14*F14 -> 0 | K14: 0.2 | L14: =J14*K14 -> 0 | M14: =J14+L14 -> 0
D15: 1 | E15: 式 | F15: =M15 -> 0 | G15: =D15*F15 -> 0 | K15: 0.2 | L15: =J15*K15 -> 0 | M15: =J15+L15 -> 0
D16: 1 | E16: 式 | F16: =M16 -> 0 | G16: =D16*F16 -> 0 | K16: 0.2 | L16: =J16*K16 -> 0 | M16: =J16+L16 -> 0
... D25: 1 | E25: 式 | F25: =M25 -> 0 | G25: =D25*F25 -> 0 | K25: 0.1 | L25: =J25*K25 -> 0 | M25: =J25+L25 -> 0
F26: =IF(D26=0,0,G26/D26) -> 0
F27: 小 計 | G27: =SUM(G5:G26) -> 0

Sheet タイル左官工事
A1: 内 訳 明 細 書
B3: 名称形状 | D3: 数量 | E3: 単位 | F3: 単価 | G3: 金額 | H3: 備考
B4: タイル左官工事 | G4: =M4*J3 -> 0
B5: 浴槽タイルまし張り 壁床 | C5: 大判タイル 材料支給 | D5: 6 | E5: 人工 | F5: 30000 | G5: =D5*F5 -> 180000 | K5: 0.2 | L5: =J5*K5 -> 0 | M5: =J5+L5 -> 0
B6: 目地 材工共 | D6: 1 | E6: 式 | F6: 65000 | G6: =D6*F6 -> 65000 | K6: 0.2 | L6: =J6*K6 -> 0 | M6: =J6+L6 -> 0
B7: 糊 | D7: 1 | E7: 式 | F7: 15000 | G7: =D7*F7 -> 15000 | K7: 0.2 | L7: =J7*K7 -> 0 | M7: =J7+L7 -> 0
B8: 副資材 | D8: 1 | E8: 式 | F8: 8500 | G8: =D8*F8 -> 8500 | K8: 0.2 | L8: =J8*K8 -> 0 | M8: =J8+L8 -> 0
B9: 水回り コーキング | C9: 材工共 | D9: 1 | E9: 式 | F9: 55000 | G9: =D9*F9 -> 55000 | K9: 0.2 | L9: =J9*K9 -> 0 | M9: =J9+L9 -> 0
F10: =M10 -> 0 | G10: =D10*F10 -> 0 | K10: 0.2 | L10: =J10*K10 -> 0 | M10: =J10+L10 -> 0
B11: 既存ブロック塀 左官材工共 | C11: Magic coat flex クラウド仕上色 21-80B | D11: 1 | E11: 式 | F11: 100000 | G11: =D11*F11 -> 100000 | K11: 0.2 | L11: =J11*K11 -> 0 | M11: =J11+L11 -> 0
F12: =M12 -> 0 | G12: =D12*F12 -> 0 | K12: 0.2 | L12: =J12*K12 -> 0 | M12: =J12+L12 -> 0
F13: =M13 -> 0 | G13: =D13*F13 -> 0 | K13: 0.2 | L13: =J13*K13 -> 0 | M13: =J13+L13 -> 0
F14: =M14 -> 0 | G14: =D14*F14 -> 0 | K14: 0.2 | L14: =J14*K14 -> 0 | M14: =J14+L14 -> 0
F15: =M15 -> 0 | G15: =D15*F15 -> 0 | K15: 0.2 | L15: =J15*K15 -> 0 | M15: =J15+L15 -> 0
F16: =M16 -> 0 | G16: =D16*F16 -> 0 | K16: 0.2 | L16: =J16*K16 -> 0 | M16: =J16+L16 -> 0
F17: =M17 -> 0 | G17: =D17*F17 -> 0 | K17: 0.2 | L17: =J17*K17 -> 0 | M17: =J17+L17 -> 0
F18: =M18 -> 0 | G18: =D18*F18 -> 0 | K18: 0.2 | L18: =J18*K18 -> 0 | M18: =J18+L18 -> 0
F19: =M19 -> 0 | G19: =D19*F19 -> 0 | K19: 0.2 | L19: =J19*K19 -> 0 | M19: =J19+L19 -> 0
F20: =M20 -> 0 | G20: =D20*F20 -> 0 | K20: 0.2 | L20: =J20*K20 -> 0 | M20: =J20+L20 -> 0
F21: =M21 -> 0 | G21: =D21*F21 -> 0 | K21: 0.2 | L21: =J21*K21 -> 0 | M21: =J21+L21 -> 0
F22: =M22 -> 0 | G22: =D22*F22 -> 0 | K22: 0.2 | L22: =J22*K22 -> 0 | M22: =J22+L22 -> 0
F23: =M23 -> 0 | G23: =D23*F23 -> 0 | K23: 0.2 | L23: =J23*K23 -> 0 | M23: =J23+L23 -> 0
... F25: =M25 -> 0 | G25: =D25*F25 -> 0 | K25: 0.1 | L25: =J25*K25 -> 0 | M25: =J25+L25 -> 0
F26: =IF(D26=0,0,G26/D26) -> 0
F27: 小 計 | G27: =SUM(G5:G26) -> 423500

Sheet 雑工事
A1: 内 訳 明 細 書
B3: 名称形状 | D3: 数量 | E3: 単位 | F3: 単価 | G3: 金額 | H3: 備考
B4: 雑工事 | G4: =M4*J3 -> 0
D5: 1 | E5: 式 | F5: =M5 -> 0 | G5: =D5*F5 -> 0 | K5: 0.2 | L5: =J5*K5 -> 0 | M5: =J5+L5 -> 0
D6: 1 | E6: 式 | F6: =M6 -> 0 | G6: =D6*F6 -> 0 | K6: 0.2 | L6: =J6*K6 -> 0 | M6: =J6+L6 -> 0
D7: 1 | E7: 式 | F7: =M7 -> 0 | G7: =D7*F7 -> 0 | K7: 0.2 | L7: =J7*K7 -> 0 | M7: =J7+L7 -> 0
D8: 1 | E8: 式 | F8: =M8 -> 0 | G8: =D8*F8 -> 0 | K8: 0.2 | L8: =J8*K8 -> 0 | M8: =J8+L8 -> 0
D9: 1 | E9: 式 | F9: =M9 -> 0 | G9: =D9*F9 -> 0 | K9: 0.2 | L9: =J9*K9 -> 0 | M9: =J9+L9 -> 0
D10: 1 | E10: 式 | F10: =M10 -> 0 | G10: =D10*F10 -> 0 | K10: 0.2 | L10: =J10*K10 -> 0 | M10: =J10+L10 -> 0
D11: 1 | E11: 式 | F11: =M11 -> 0 | G11: =D11*F11 -> 0 | K11: 0.2 | L11: =J11*K11 -> 0 | M11: =J11+L11 -> 0
D12: 1 | E12: 式 | F12: =M12 -> 0 | G12: =D12*F12 -> 0 | K12: 0.2 | L12: =J12*K12 -> 0 | M12: =J12+L12 -> 0
D13: 1 | E13: 式 | F13: =M13 -> 0 | G13: =D13*F13 -> 0 | K13: 0.2 | L13: =J13*K13 -> 0 | M13: =J13+L13 -> 0
D14: 1 | E14: 式 | F14: =M14 -> 0 | G14: =D14*F14 -> 0 | K14: 0.2 | L14: =J14*K14 -> 0 | M14: =J14+L14 -> 0
D15: 1 | E15: 式 | F15: =M15 -> 0 | G15: =D15*F15 -> 0 | K15: 0.2 | L15: =J15*K15 -> 0 | M15: =J15+L15 -> 0
D16: 1 | E16: 式 | F16: =M16 -> 0 | G16: =D16*F16 -> 0 | K16: 0.2 | L16: =J16*K16 -> 0 | M16: =J16+L16 -> 0
... D25: 1 | E25: 式 | F25: =M25 -> 0 | G25: =D25*F25 -> 0 | K25: 0.1 | L25: =J25*K25 -> 0 | M25: =J25+L25 -> 0
F27: 小 計 | G27: =SUM(G5:G26) -> 0

Sheet シート工事
A1: 内 訳 明 細 書
B3: 名称形状 | D3: 数量 | E3: 単位 | F3: 単価 | G3: 金額 | H3: 備考
B4: シート工事
D5: 1 | E5: 式 | F5: =M5 -> 0 | G5: =D5*F5 -> 0 | K5: 0.2 | L5: =J5*K5 -> 0 | M5: =J5+L5 -> 0
D6: 1 | E6: 式 | F6: =M6 -> 0 | G6: =D6*F6 -> 0 | K6: 0.2 | L6: =J6*K6 -> 0 | M6: =J6+L6 -> 0
D7: 1 | E7: 式 | F7: =M7 -> 0 | G7: =D7*F7 -> 0 | K7: 0.2 | L7: =J7*K7 -> 0 | M7: =J7+L7 -> 0
D8: 1 | E8: 式 | F8: =M8 -> 0 | G8: =D8*F8 -> 0 | K8: 0.2 | L8: =J8*K8 -> 0 | M8: =J8+L8 -> 0
D9: 1 | E9: 式 | F9: =M9 -> 0 | G9: =D9*F9 -> 0 | K9: 0.2 | L9: =J9*K9 -> 0 | M9: =J9+L9 -> 0
D10: 1 | E10: 式 | F10: =M10 -> 0 | G10: =D10*F10 -> 0 | K10: 0.2 | L10: =J10*K10 -> 0 | M10: =J10+L10 -> 0
D11: 1 | E11: 式 | F11: =M11 -> 0 | G11: =D11*F11 -> 0 | K11: 0.2 | L11: =J11*K11 -> 0 | M11: =J11+L11 -> 0
D12: 1 | E12: 式 | F12: =M12 -> 0 | G12: =D12*F12 -> 0 | K12: 0.2 | L12: =J12*K12 -> 0 | M12: =J12+L12 -> 0
D13: 1 | E13: 式 | F13: =M13 -> 0 | G13: =D13*F13 -> 0 | K13: 0.2 | L13: =J13*K13 -> 0 | M13: =J13+L13 -> 0
D14: 1 | E14: 式 | F14: =M14 -> 0 | G14: =D14*F14 -> 0 | K14: 0.2 | L14: =J14*K14 -> 0 | M14: =J14+L14 -> 0
D15: 1 | E15: 式 | F15: =M15 -> 0 | G15: =D15*F15 -> 0 | K15: 0.2 | L15: =J15*K15 -> 0 | M15: =J15+L15 -> 0
D16: 1 | E16: 式 | F16: =M16 -> 0 | G16: =D16*F16 -> 0 | K16: 0.2 | L16: =J16*K16 -> 0 | M16: =J16+L16 -> 0
... D25: 1 | E25: 式 | F25: =M25 -> 0 | G25: =D25*F25 -> 0 | K25: 0.1 | L25: =J25*K25 -> 0 | M25: =J25+L25 -> 0
F26: 0
F27: 小 計 | G27: =SUM(G4:G26) -> 0

Sheet 仕上げ工事
A1: 内 訳 明 細 書
B3: 名称形状 | D3: 数量 | E3: 単位 | F3: 単価 | G3: 金額 | H3: 備考
B4: 仕上げ工事
B5: エントランス、寝室 下地既存利用 | C5: SGM1318~SANGETSU 天壁 | D5: 68 | E5: ㎡ | K5: 0.2 | L5: =J5*K5 -> 0 | M5: =J5+L5 -> 0
B6: 副資材 | D6: 1 | E6: 式 | K6: 0.2 | L6: =J6*K6 -> 0 | M6: =J6+L6 -> 0
B7: 資材運搬搬入費 | D7: 1 | E7: 式 | K7: 0.2 | L7: =J7*K7 -> 0 | M7: =J7+L7 -> 0
F8: =M8 -> 0 | G8: =D8*F8 -> 0 | K8: 0.2 | L8: =J8*K8 -> 0 | M8: =J8+L8 -> 0
B9: 階段下 新規ベニヤ貼り後 塗装 | C9: 材工共 | D9: 1 | E9: 式 | F9: 65000 | G9: =D9*F9 -> 65000 | K9: 0.2 | L9: =J9*K9 -> 0 | M9: =J9+L9 -> 0
F10: =M10 -> 0 | G10: =D10*F10 -> 0 | K10: 0.2 | L10: =J10*K10 -> 0 | M10: =J10+L10 -> 0
F11: =M11 -> 0 | G11: =D11*F11 -> 0 | K11: 0.2 | L11: =J11*K11 -> 0 | M11: =J11+L11 -> 0
F12: =M12 -> 0 | G12: =D12*F12 -> 0 | K12: 0.2 | L12: =J12*K12 -> 0 | M12: =J12+L12 -> 0
F13: =M13 -> 0 | G13: =D13*F13 -> 0 | K13: 0.2 | L13: =J13*K13 -> 0 | M13: =J13+L13 -> 0
F14: =M14 -> 0 | G14: =D14*F14 -> 0 | K14: 0.2 | L14: =J14*K14 -> 0 | M14: =J14+L14 -> 0
F15: =M15 -> 0 | G15: =D15*F15 -> 0 | K15: 0.2 | L15: =J15*K15 -> 0 | M15: =J15+L15 -> 0
F16: =M16 -> 0 | G16: =D16*F16 -> 0 | K16: 0.2 | L16: =J16*K16 -> 0 | M16: =J16+L16 -> 0
F17: =M17 -> 0 | G17: =D17*F17 -> 0 | K17: 0.2 | L17: =J17*K17 -> 0 | M17: =J17+L17 -> 0
F18: =M18 -> 0 | G18: =D18*F18 -> 0 | K18: 0.2 | L18: =J18*K18 -> 0 | M18: =J18+L18 -> 0
F19: =M19 -> 0 | G19: =D19*F19 -> 0 | K19: 0.2 | L19: =J19*K19 -> 0 | M19: =J19+L19 -> 0
F20: =M20 -> 0 | G20: =D20*F20 -> 0 | K20: 0.2 | L20: =J20*K20 -> 0 | M20: =J20+L20 -> 0
F21: =M21 -> 0 | G21: =D21*F21 -> 0 | K21: 0.2 | L21: =J21*K21 -> 0 | M21: =J21+L21 -> 0
... F25: =M25 -> 0 | G25: =D25*F25 -> 0 | K25: 0.1 | L25: =J25*K25 -> 0 | M25: =J25+L25 -> 0
F26: =IF(D26=0,0,G26/D26) -> 0
F27: 小 計 | G27: =SUM(G5:G26) -> 65000

Sheet 衛生設備
A1: 内 訳 明 細 書
B3: 名称形状 | D3: 数量 | E3: 単位 | F3: 単価 | G3: 金額 | H3: 備考
B4: 衛生設備
D5: 1 | E5: 式 | F5: =M5 -> 0 | G5: =D5*F5 -> 0 | K5: 0.2 | L5: =J5*K5 -> 0 | M5: =J5+L5 -> 0
D6: 1 | E6: 式 | F6: =M6 -> 0 | G6: =D6*F6 -> 0 | K6: 0.2 | L6: =J6*K6 -> 0 | M6: =J6+L6 -> 0
D7: 1 | E7: 式 | F7: =M7 -> 0 | G7: =D7*F7 -> 0 | K7: 0.2 | L7: =J7*K7 -> 0 | M7: =J7+L7 -> 0
D8: 1 | E8: 式 | F8: =M8 -> 0 | G8: =D8*F8 -> 0 | K8: 0.2 | L8: =J8*K8 -> 0 | M8: =J8+L8 -> 0
D9: 1 | E9: 式 | F9: =M9 -> 0 | G9: =D9*F9 -> 0 | K9: 0.2 | L9: =J9*K9 -> 0 | M9: =J9+L9 -> 0
D10: 1 | E10: 式 | F10: =M10 -> 0 | G10: =D10*F10 -> 0 | K10: 0.2 | L10: =J10*K10 -> 0 | M10: =J10+L10 -> 0
D11: 1 | E11: 式 | F11: =M11 -> 0 | G11: =D11*F11 -> 0 | K11: 0.2 | L11: =J11*K11 -> 0 | M11: =J11+L11 -> 0
D12: 1 | E12: 式 | F12: =M12 -> 0 | G12: =D12*F12 -> 0 | K12: 0.2 | L12: =J12*K12 -> 0 | M12: =J12+L12 -> 0
D13: 1 | E13: 式 | F13: =M13 -> 0 | G13: =D13*F13 -> 0 | K13: 0.2 | L13: =J13*K13 -> 0 | M13: =J13+L13 -> 0
D14: 1 | E14: 式 | F14: =M14 -> 0 | G14: =D14*F14 -> 0 | K14: 0.2 | L14: =J14*K14 -> 0 | M14: =J14+L14 -> 0
D15: 1 | E15: 式 | F15: =M15 -> 0 | G15: =D15*F15 -> 0 | K15: 0.2 | L15: =J15*K15 -> 0 | M15: =J15+L15 -> 0
D16: 1 | E16: 式 | F16: =M16 -> 0 | G16: =D16*F16 -> 0 | K16: 0.2 | L16: =J16*K16 -> 0 | M16: =J16+L16 -> 0
... D25: 1 | E25: 式 | F25: =M25 -> 0 | G25: =D25*F25 -> 0 | K25: 0.1 | L25: =J25*K25 -> 0 | M25: =J25+L25 -> 0
F26: =IF(D26=0,0,G26/D26) -> 0 | G26: =M26*J3 -> 0
F27: 小 計 | G27: =SUM(G5:G26) -> 0

Sheet 塗装工事
A1: 内 訳 明 細 書
B3: 名称形状 | D3: 数量 | E3: 単位 | F3: 単価 | G3: 金額 | H3: 備考
B4: 塗装工事 | F4: =IF(D4=0,0,G4/D4) -> 0 | G4: =M4*J3 -> 0
D5: 1 | E5: 式 | F5: =M5 -> 0 | G5: =D5*F5 -> 0 | K5: 0.2 | L5: =J5*K5 -> 0 | M5: =J5+L5 -> 0
D6: 1 | E6: 式 | F6: =M6 -> 0 | G6: =D6*F6 -> 0 | K6: 0.2 | L6: =J6*K6 -> 0 | M6: =J6+L6 -> 0
D7: 1 | E7: 式 | F7: =M7 -> 0 | G7: =D7*F7 -> 0 | K7: 0.2 | L7: =J7*K7 -> 0 | M7: =J7+L7 -> 0
D8: 1 | E8: 式 | F8: =M8 -> 0 | G8: =D8*F8 -> 0 | K8: 0.2 | L8: =J8*K8 -> 0 | M8: =J8+L8 -> 0
D9: 1 | E9: 式 | F9: =M9 -> 0 | G9: =D9*F9 -> 0 | K9: 0.2 | L9: =J9*K9 -> 0 | M9: =J9+L9 -> 0
D10: 1 | E10: 式 | F10: =M10 -> 0 | G10: =D10*F10 -> 0 | K10: 0.2 | L10: =J10*K10 -> 0 | M10: =J10+L10 -> 0
D11: 1 | E11: 式 | F11: =M11 -> 0 | G11: =D11*F11 -> 0 | K11: 0.2 | L11: =J11*K11 -> 0 | M11: =J11+L11 -> 0
D12: 1 | E12: 式 | F12: =M12 -> 0 | G12: =D12*F12 -> 0 | K12: 0.2 | L12: =J12*K12 -> 0 | M12: =J12+L12 -> 0
D13: 1 | E13: 式 | F13: =M13 -> 0 | G13: =D13*F13 -> 0 | K13: 0.2 | L13: =J13*K13 -> 0 | M13: =J13+L13 -> 0
D14: 1 | E14: 式 | F14: =M14 -> 0 | G14: =D14*F14 -> 0 | K14: 0.2 | L14: =J14*K14 -> 0 | M14: =J14+L14 -> 0
D15: 1 | E15: 式 | F15: =M15 -> 0 | G15: =D15*F15 -> 0 | K15: 0.2 | L15: =J15*K15 -> 0 | M15: =J15+L15 -> 0
D16: 1 | E16: 式 | F16: =M16 -> 0 | G16: =D16*F16 -> 0 | K16: 0.2 | L16: =J16*K16 -> 0 | M16: =J16+L16 -> 0
... D25: 1 | E25: 式 | F25: =M25 -> 0 | G25: =D25*F25 -> 0 | K25: 0.1 | L25: =J25*K25 -> 0 | M25: =J25+L25 -> 0
F26: =IF(D26=0,0,G26/D26) -> 0
F27: 小 計 | G27: =SUM(G5:G26) -> 0

Sheet 防災工事
A1: 内 訳 明 細 書
B3: 名称形状 | D3: 数量 | E3: 単位 | F3: 単価 | G3: 金額 | H3: 備考
B4: 防災工事 | F4: =IF(D4=0,0,G4/D4) -> 0 | G4: =M4*J3 -> 0
D5: 1 | E5: 式 | F5: =M5 -> 0 | G5: =D5*F5 -> 0 | K5: 0.2 | L5: =J5*K5 -> 0 | M5: =J5+L5 -> 0
D6: 1 | E6: 式 | F6: =M6 -> 0 | G6: =D6*F6 -> 0 | K6: 0.2 | L6: =J6*K6 -> 0 | M6: =J6+L6 -> 0
D7: 1 | E7: 式 | F7: =M7 -> 0 | G7: =D7*F7 -> 0 | K7: 0.2 | L7: =J7*K7 -> 0 | M7: =J7+L7 -> 0
D8: 1 | E8: 式 | F8: =M8 -> 0 | G8: =D8*F8 -> 0 | K8: 0.2 | L8: =J8*K8 -> 0 | M8: =J8+L8 -> 0
D9: 1 | E9: 式 | F9: =M9 -> 0 | G9: =D9*F9 -> 0 | K9: 0.2 | L9: =J9*K9 -> 0 | M9: =J9+L9 -> 0
D10: 1 | E10: 式 | F10: =M10 -> 0 | G10: =D10*F10 -> 0 | K10: 0.2 | L10: =J10*K10 -> 0 | M10: =J10+L10 -> 0
D11: 1 | E11: 式 | F11: =M11 -> 0 | G11: =D11*F11 -> 0 | K11: 0.2 | L11: =J11*K11 -> 0 | M11: =J11+L11 -> 0
D12: 1 | E12: 式 | F12: =M12 -> 0 | G12: =D12*F12 -> 0 | K12: 0.2 | L12: =J12*K12 -> 0 | M12: =J12+L12 -> 0
D13: 1 | E13: 式 | F13: =M13 -> 0 | G13: =D13*F13 -> 0 | K13: 0.2 | L13: =J13*K13 -> 0 | M13: =J13+L13 -> 0
D14: 1 | E14: 式 | F14: =M14 -> 0 | G14: =D14*F14 -> 0 | K14: 0.2 | L14: =J14*K14 -> 0 | M14: =J14+L14 -> 0
D15: 1 | E15: 式 | F15: =M15 -> 0 | G15: =D15*F15 -> 0 | K15: 0.2 | L15: =J15*K15 -> 0 | M15: =J15+L15 -> 0
D16: 1 | E16: 式 | F16: =M16 -> 0 | G16: =D16*F16 -> 0 | K16: 0.2 | L16: =J16*K16 -> 0 | M16: =J16+L16 -> 0
... D25: 1 | E25: 式 | F25: =M25 -> 0 | G25: =D25*F25 -> 0 | K25: 0.1 | L25: =J25*K25 -> 0 | M25: =J25+L25 -> 0
F26: =IF(D26=0,0,G26/D26) -> 0
F27: 小 計 | G27: =SUM(G5:G26) -> 0

Sheet ガス工事
A1: 内 訳 明 細 書
B3: 名称形状 | D3: 数量 | E3: 単位 | F3: 単価 | G3: 金額 | H3: 備考
B4: ガス工事 | F4: =IF(D4=0,0,G4/D4) -> 0 | G4: =M4*J3 -> 0
D5: 1 | E5: 式 | F5: =M5 -> 0 | G5: =D5*F5 -> 0 | K5: 0.2 | L5: =J5*K5 -> 0 | M5: =J5+L5 -> 0
D6: 1 | E6: 式 | F6: =M6 -> 0 | G6: =D6*F6 -> 0 | K6: 0.2 | L6: =J6*K6 -> 0 | M6: =J6+L6 -> 0
D7: 1 | E7: 式 | F7: =M7 -> 0 | G7: =D7*F7 -> 0 | K7: 0.2 | L7: =J7*K7 -> 0 | M7: =J7+L7 -> 0
D8: 1 | E8: 式 | F8: =M8 -> 0 | G8: =D8*F8 -> 0 | K8: 0.2 | L8: =J8*K8 -> 0 | M8: =J8+L8 -> 0
D9: 1 | E9: 式 | F9: =M9 -> 0 | G9: =D9*F9 -> 0 | K9: 0.2 | L9: =J9*K9 -> 0 | M9: =J9+L9 -> 0
D10: 1 | E10: 式 | F10: =M10 -> 0 | G10: =D10*F10 -> 0 | K10: 0.2 | L10: =J10*K10 -> 0 | M10: =J10+L10 -> 0
D11: 1 | E11: 式 | F11: =M11 -> 0 | G11: =D11*F11 -> 0 | K11: 0.2 | L11: =J11*K11 -> 0 | M11: =J11+L11 -> 0
D12: 1 | E12: 式 | F12: =M12 -> 0 | G12: =D12*F12 -> 0 | K12: 0.2 | L12: =J12*K12 -> 0 | M12: =J12+L12 -> 0
D13: 1 | E13: 式 | F13: =M13 -> 0 | G13: =D13*F13 -> 0 | K13: 0.2 | L13: =J13*K13 -> 0 | M13: =J13+L13 -> 0
D14: 1 | E14: 式 | F14: =M14 -> 0 | G14: =D14*F14 -> 0 | K14: 0.2 | L14: =J14*K14 -> 0 | M14: =J14+L14 -> 0
D15: 1 | E15: 式 | F15: =M15 -> 0 | G15: =D15*F15 -> 0 | K15: 0.2 | L15: =J15*K15 -> 0 | M15: =J15+L15 -> 0
D16: 1 | E16: 式 | F16: =M16 -> 0 | G16: =D16*F16 -> 0 | K16: 0.2 | L16: =J16*K16 -> 0 | M16: =J16+L16 -> 0
... D25: 1 | E25: 式 | F25: =M25 -> 0 | G25: =D25*F25 -> 0 | K25: 0.1 | L25: =J25*K25 -> 0 | M25: =J25+L25 -> 0
F26: =IF(D26=0,0,G26/D26) -> 0 | G26: =M26*J3 -> 0
F27: 小 計 | G27: =SUM(G5:G26) -> 0

Sheet Claude Log
A1: Turn # | B1: Date | C1: User Request | D1: Action Taken | E1: Details | F1: Outcome
A2: 1 | B2: 46064 | C2: 見積書の構造分析依頼。この書式で見積作成ソフトを作りたい。大項目→中項目→小項目の階層構造を分析してほしい。 | D2: 全27シートの構造・数式・データ・レイアウトを詳細に分析 | E2: Ｓ表紙（総括）、7種の工事明細シート（解体/造作/建具/家具/電気設備/タイル左官/仕上げ）、未使用テンプレート13枚、請求書/注文書/請書/実行予算の帳票4種を確認。数式リンク・列構成・行構成すべて把握。 | F2: 分析完了。構造レポートをチャットで提示。
A3: 2 | B3: 46064 | C3: 見積ソフトの要件確認。ベースは固定+カスタム追加、データ蓄積、見積+実行予算連動を希望。 | D3: 全体設計書シートを作成し、4フェーズの実装計画を策定 | E3: マスター設定・工事項目DB・業者DB・Ｓ表紙改良・明細テンプレート改良・実行予算連動・帳票自動化・DB蓄積の7つのシート構成と、①〜⑦のデータフロー、Phase1〜4の段階的実装計画を設計 | F3: 設計書シートに全体設計を記載。ユーザー確認待ち。
A4: 3 | B4: 46064 | C4: 会社情報提供（株式会社LinK）。担当者は5名以上、ロゴは後日共有、見積+実行予算連動希望。Phase 1着手指示。 | D4: Phase 1完了：マスター設定・工事項目DB・業者DBの3シートを構築 | E4: マスター設定: 会社情報固定(株式会社LinK)+担当者リスト10名分+案件情報入力+経費率設定+工事カテゴリ20種チェック式選択(各シート小計数式リンク済)。工事項目DB: 32件の既存データを初期登録。業者DB: 10件分の空テンプレート。担当者ドロップダウン+メールVLOOKUP連動済。 | F4: Phase 1完了。次はPhase 2（Ｓ表紙改良+明細テンプレート+DB連携）へ。
A5: 4 | B5: 46064 | C5: CRMシステムの設計構築も併せて依頼。顧客・案件管理、ステータス管理、経過日数滞留アラート、半自動見積作成、未経験者対応のUIを希望。ロゴファイル共有（手動貼付が必要）。 | D5: 設計書に■5.CRMシステム設計と■6.実装フェーズ改訂版を追記 | E5: CRM設計: 顧客マスタ+案件管理+ダッシュボードの3シート構成。ステータス7段階（リード→商談→見積作成→提出→受注/失注→完工）。ダッシュボードKPI: 受注率・月別売上・ステータス分布・滞留アラート・顧客別実績。実装Phaseを5段階に拡張。 | F5: 設計書更新完了。Phase 2（CRM構築）に着手予定。
A6: 6 | B6: 46064 | C6: 案件管理シート作成の続行（会話圧縮後の再開）。顧客マスタと案件管理の連携確認。 | D6: 案件管理シート完成 + 顧客マスタ連携フォーミュラ修正 | E6: 案件管理(SheetID:35): 20列構成（案件ID〜備考）。自動計算: C列=VLOOKUP顧客名, H列=粗利率, K列=経過日数, L列=滞留アラート(30日超で⚠表示)。データバリデーション: I列=7段階ステータス, M列=担当者(マスター設定連携), B列=顧客ID(顧客マスタ連携)。条件付き書式: ステータス色分け(受注=緑/失注=灰/完工=青/提出済=黄), 滞留赤背景, 粗利率カラースケール, 経過日数データバー。顧客マスタL列=COUNTIF案件数, M列=SUMIFS受注額(⑤受注+⑦完工)。 | F6: 案件管理シート完成。サンプルデータ2件(P-001受注済, P-002見積提出済⚠滞留)で動作確認済。顧客マスタC-001: 累計案件数2, 累計受注額¥3,500,000と正常連携。次: ダッシュボード作成。
A7: 7 | B7: 46064 | C7: ダッシュボード作成依頼。CRM KPIを一画面で可視化。 | D7: ダッシュボード(SheetID:36)を完成。4セクション構築 + チャート2枚作成。 | E7: 【KPIサマリー】7カード: 総案件数, アクティブ案件, 受注数, 失注数, 成約率(100%), 滞留数, 見積総額(¥5,300,000)。下段: 受注金額, アクティブ金額, 受注金額, 失注金額, 平均経過日数, 滞留平均日数, 金額ベース成約率。【ステータス別分布】7段階×5列(件数/構成比/金額/平均経過日数) + ドーナツチャート。【担当者別実績】マスター設定連携10名分(案件数/受注数/受注率/受注金額/滞留数) + 棒グラフ。【滞留案件一覧】FILTER関数で動的抽出。【顧客別実績TOP10】SORTBY+FILTERで受注額降順。顧客マスタL列(COUNTIF)→M列(SUMIFS)連携修正済。総案件数計算式修正(COUNTA)。 | F7: ダッシュボード完成。サンプルデータ: 総案件2件, 成約率100%, 滞留1件(P-002: 379日), 吉野博: 受注率50%。Phase 2 CRM完了。次: Phase 3 見積連携。
A8: 8 | B8: 46064 | C8: 発注書兼請求書作成＋案件別データ管理＋原価管理システムの要望。兼用型の是非を検討依頼。職人の請求書との不一致問題を解決したい。 | D8: 既存帳票（注文書/請求書/請書/実行予算雛形/S表紙/工事明細）を全分析。業務フローと課題を整理し、設計提案を準備。 | E8: 既存シート全35枚を調査。注文書=業者向け発注(施工場所/件名/期限/支払条件/直接工事費/現場経費/会社経費/現場管理費)。請求書=顧客向け請求(着手金/完工金)。実行予算=予算vs実費の2列管理(相手先/工事内容/金額)。S表紙=見積総括(顧客名/工事名/場所/金額)。各工事シート=明細(名称/数量/単位/単価/金額)。現状の問題: 手入力依存、業者DBとの連携なし、案件ごとの原価追跡不可。 | F8: 分析完了。設計提案を作成中。ユーザーの課題: ①職人が発注書と異なる金額の請求書を送る→発注書で金額固定化 ②案件ごとの原価管理ができない→実行予算+発注+実績の3段階管理 ③シートが増えすぎる→案件別管理方式の最適化が必要
A9: 9 | B9: 46064 | C9: 発注書兼請求書＋案件テンプレート(原価管理)＋操作パネル作成。3タイプ原価ロジック(A原価逆算/B定価固定/C単価固定)の設計・実装。 | D9: 3シート新規作成: 案件テンプレート(ID:37), 発注書兼請求書(ID:38), 操作パネル(ID:39) | E9: 【案件テンプレート】18列: 基本情報(案件ID/顧客/工事名/場所/担当/目標粗利率) + 原価管理表(No./タイプABC/カテゴリ/品名/仕様/原価単価/原価金額→客出し単価/客出し金額→利益額/利益率→発注先/発注日/発注額/支払済/備考)。タイプA=ROUND(原価/(1-粗利率))で自動逆算、B/C=手入力。30行×全自動計算。税計算(10%)付。サンプル検証: A=30.0%✅ B=40.0%✅ C=40.9%✅。【発注書兼請求書】ドロップダウン1つで発注書⇔請求書切替。業者DB連携(宛先/支払条件自動)。明細20行+小計/税/合計。「本発注書記載の金額にてご請求をお願いいたします」の文言で金額統制。【操作パネル】新規案件作成の入口。手順ガイド+システム構成一覧。 | F9: 3シート完成。Phase 3(見積連携)+Phase 4(予算・帳票)の核心部分を実装。次: Claudeへ「新規案件作成」と伝えるとテンプレート複製+自動入力する機能の運用テスト。
A10: 10 | B10: 46064 | C10: 原価管理表で項目を間違えた際の行クリア・行入替え機能の要望。 | D10: 案件テンプレートに行操作ツール(行クリア/行入替え)セクション追加。数式セルに入力警告メッセージ追加。 | E10: 【行操作ツール】A53:R56に設置。B54=クリアしたい行No.(1-30)入力→Claudeに依頼で該当行のデータクリア+数式復元。B55/D55=入替え行No.2つ入力→Claudeに依頼で行データスワップ。数値バリデーション(1-30)追加。【数式保護】G/K/L/M/P列にデータバリデーションプロンプト追加(「⚠自動計算セル」警告表示)。ユーザーが誤って数式セルに入力しようとした際に警告。直接Delete可能だが、行クリア機能で数式含めて復元可能な設計。 | F10: 行操作ツール完成。ユーザーがDeleteキーで直接クリアも可能、Claudeに依頼して数式ごと復元も可能の二重対応。
A11: 11 | B11: 46064 | C11: PDF出力ボタン＋UI整備の要望。全帳票の印刷設定＋シート整理＋ボーダー・レイアウト改善。 | D11: 全帳票の印刷エリア・用紙設定完了。シートタブ順序整理(操作パネル先頭)。旧帳票6枚を非表示化。全シートにボーダー追加・UIポリッシュ。 | E11: 【印刷設定】発注書兼請求書=A4縦(印刷エリアA1:I48)。案件テンプレート=A3横(A1:R51)。S表紙=A4縦。マージン最適化済。【シート整理】タブ順: ①操作パネル②ダッシュボード③案件管理④案件テンプレート⑤発注書兼請求書⑥顧客マスタ⑦マスター設定⑧工事項目DB⑨業者DB⑩S表紙(+工事シート群)→設計書→Claude Log。旧シート非表示: 注文書/注文書(控)/請書/請書(2)/請求書/実行予算雛形。【UIポリッシュ】案件テンプレート: セクション区切りボーダー(原価/客出し/利益/発注の境界を太線)、税計算エリアボーダー。発注書兼請求書: 総金額ダブルライン、施工情報枠、社判枠。操作パネル: 入力エリア枠、システム構成テーブル枠、PDFガイドテーブル枠。 | F11: UI整備完了。PDF化はExcel標準機能(Ctrl+P→Microsoft Print to PDF)で対応。操作パネルにPDFガイド追加済。全シートの印刷エリア・用紙サイズ・向き設定済。
A12: 12 | B12: 46064 | C12: おすすめで進行→新規案件作成の実テスト実施。操作パネル→テンプレート複製→データ入力→案件管理登録の一気通貫テスト。 | D12: P-003_吉野様邸キッチン シートを新規作成。7工事項目入力。案件管理に自動登録。全3タイプ動作確認。 | E12: 【テスト案件】P-003 吉野様邸キッチンリフォーム(C-001/吉野博/目標粗利25%)。【入力7項目】①解体(A型)¥85,000→¥113,333(25.0%) ②給排水(A型)¥120,000→¥160,000(25.0%) ③LIXILキッチン(B型)仕入¥420,000/定価¥680,000(38.2%) ④クロス(C型)¥650→¥1,100/㎡(40.9%) ⑤CFシート(C型)¥800→¥1,800/㎡(55.6%) ⑥電気(A型)¥65,000→¥86,667(25.0%) ⑦産廃(A型)¥18,000→¥48,000(25.0%)。【集計】原価¥753,800/客出し¥1,140,400/利益¥386,600(33.9%)/税込¥1,254,440。J16数式消失を検出→復元済。案件管理F7に税込見積額¥1,254,440を登録。 | F12: 新規案件作成フロー完全動作確認。A/B/Cタイプ全て正常。目標粗利25%設定でA型項目は全て25.0%で自動算出。B/C型は固定単価で利益率が自動変動。全体利益率33.9%。
A13: 13 | B13: 46064 | C13: セッション再開（要約後）→ 設計書の更新 | D13: 設計書を現在の実装状態に合わせて全面更新 | E13: セクション1-6全て更新: システム概要、シート構成、機能詳細(A/Bセクション)、業務フロー、CRM設計、フェーズ状態(Phase1-4完了、Phase5次回) | F13: 設計書が現在の実装状態を正確に反映。Phase5がNEXTとして明記
... A18: 17 | B18: 46064 | C18: 「7番実装して」→ 設計書の⑦完工時→工事項目DBに実績蓄積の実装依頼 | D18: ⑦完工フローを実装。案件管理P-003のステータス更新+完工日記録+請求予定額設定+工事項目DB登録日更新+設計書ステータス更新 | E18: 案件管理I7=⑦完工, J7/P7=TODAY(), Q7=F7(¥1,254,440)。工事項目DB ID33-39のH列(最終使用日)・L列(登録日)をTODAY()で更新。顧客マスタM5の累計受注額が¥3,500,000→¥4,754,440に自動連動(SUMIFS式が⑦完工も集計)。設計書D52/D81を⏳→✅に更新。 | F18: ⑦完工フロー実装完了。全ステップ(①~⑦)が✅実装済みとなり、業務フロー全体が完成。P-003がテスト完工処理済み。
A19: 18 | B19: =TODAY() -> 46070 | C19: DB蓄積もお願いします→ 工事項目DBに利益率列追加+P-003実績利益率記録+FILTER数式修正 | D19: 工事項目DBにI列「利益率」を新規追加。P-003の7項目(ID33-39)の実績利益率を記録。列挿入に伴うFILTER数式の範囲修正。 | E19: 工事項目DB: H列後にI列「利益率」挿入(0.0%書式)。P-003利益率: 解体=25.0%/衛生=25.0%/LIXIL=38.2%/クロス=40.9%/CF=55.6%/電気=25.0%/産廃=25.0%。テンプレート+P-003のDB参照FILTER範囲をB:Kに修正、ヘッダーに利益率列追加。検索キー列(L列)は非表示。 | F19: DB蓄積完了。工事項目DB=13列(A-M)構成。利益率列追加により次回見積時に過去実績の利益率も参照可能に。全シートのDB参照セクションも整合済。
A20: 19 | B20: =TODAY() -> 46070 | C20: 過去に伝えたことの再出力依頼。まだ実装されていないものを確認したい。 | D20: Claude Log全履歴+設計書を精査し、実装済み11件+未実装/未対応5件(A-E)をリスト化して提示 | E20: 未実装項目: A=ロゴ貼付(待ち), B=実行予算連動, C=S表紙連動, D=完工時請求書自動生成, E=業者DB実データ登録 | F20: ユーザーに未実装項目を提示。次のアクションを確認中。
A21: 20 | B21: =TODAY() -> 46070 | C21: 複数要望: 1)余日管理 2)表紙連動 3)インタードア→LinK更新 4)請求書/入金管理+ダッシュボード反映 5)業者DBサンプル作成 6)ロゴは送済みとのこと | D21: Phase6一括実装: 6-1)注文書B4「INTER DOOR」→「株式会社LinK」更新 6-2)業者DB5社サンプル 6-3)案件管理U-AC列追加(完工予定日/工期余日/アラート/請求書ステータス/請求日/請求金額/入金ステータス/入金日/入金額) 6-4)S表紙連動(案件ID+シート名入力→顧客名/工事名/施工場所/カテゴリ別金額自動反映) 6-5)ダッシュボードに請求・入金管理セクション(KPI+未入金一覧+未発行一覧) | E21: 注文書B4=LinK(控も自動連動)。業者DB: 山田建設/アクア工業/佐藤電気/美装クラフト/松本建具。5社登録。案件管理: 9列追加(U-AC), ドロップダウン(発行済/未発行, 入金済/未入金), 日付書式, P-004~P-100に数式テンプレート。S表紙: J3=案件ID, J2=シート名入力→VLOOKUPで顧客名/工事名自動, B36-B55=20工種, I36-I55=SUMIFSでカテゴリ別客出し金額集計。ダッシュボード: KPI7カード(発行済/未発行/入金済/未入金/未回収率+金額), FILTERで未入金・未発行一覧動的抽出。 | F21: Phase6全完了。案件管理=29列(A-AC)。P-001=発行済・入金済、5社, P-002=未発行・未入金, P-003=発行済・未入金。未回収残高¥1,254,440。S表紙=P-003連動中(合計¥1,573,406)。業者DB=5社登録済。
A22: 21 | B22: =TODAY() -> 46070 | C22: 請求書自動発行と工程表(ガントチャート)の自動作成が可能か質問。構造や方式の説明を求めている。 | D22: 請求書発行3方式と工程表3方式の選択肢を提示。それぞれのメリット・デメリットを説明。 | E22: 請求書: 発注書兼請求書への自動反映を推奨。工程表: 条件付き書式でバー表示のガントチャート型。案件シート内組み込み or 専用シート or 切替式の3パターン。 | F22: ユーザーの回答待ち。方式決定後に実装着手予定。
A23: 22 | B23: =TODAY() -> 46070 | C23: 工程表(ガントチャート)作成とステータス(受注/未受注/失注)の追加を要望。A4横、84日(12週間)、お客様に送付する用途。 | D23: 1)工程表シート構築: ヘッダー(案件ID→VLOOKUP自動表示)、日付軸(3日/列×28列=84日)、20工種行にガントバー数式、条件付き書式(■→青塗)、A4横印刷設定 2)受注区分列AD列追加(案件管理): ⑤受注/⑦完工→🟢受注、⑥失注→🔴失注、その他→🟡未受注 3)ダッシュボードに受注区分管理セクション追加 | E23: 工程表: B2=案件ID入力→B3工事名/B4顧客名/E4施工場所自動、E2=着工日→日付軸自動生成、D/E列に開始日/終了日入力→F列日数自動+G-AH列にガント表示。条件付き書式で■セルを青背景に。印刷:A4横/65%縮小/印刷範囲A1:AH29。受注区分: IF(OR(I=⑤受注,⑦完工),🟢,IF(⑥失注,🔴,🟡))。ダッシュボード: KPI(受注2件/未受注1件/失注0件/受注率100%/受注金額¥4,754,440)+未受注一覧FILTER+失注一覧FILTER | F23: 工程表完成(P-003サンプルデータ8工程入力済み)。受注区分=P-001🟢受注/P-002🟡未受注/P-003🟢受注。ダッシュボードRow57-70に受注区分管理セクション追加完了。
A24: 23 | B24: =TODAY() -> 46070 | C24: （継続）工程表の罫線・列幅調整・行高さ設定の仕上げ作業 | D24: 罫線追加(ヘッダー下太線/F列右太線/外枠太線)、列幅最適化(A=25,B=55,C=80,D-E=40,F=30,G-AH=18pt)、行高さ(タイトル30/情報20/ヘッダー18/工事項目16pt) | E24: A4横印刷時に全体が1ページに収まるよう設計。ガントエリアと情報エリアの境界を太罫線で視覚的に区別。 | F24: Phase7実装完了。工程表+受注区分+ダッシュボード受注管理の3機能が稼働中。
A25: 24 | B25: =TODAY() -> 46070 | C25: 工程表B列が固定20工種に紐づいている点を指摘。自由自在に操れるようにしたいとの要望。 | D25: B7:B26を固定工種→自由入力に変更。A列を自動連番(B列入力時のみ表示)に。旧散在サンプルデータをクリアし、キッチンリフォーム工程順(8工程)で再入力。 | E25: A列=IF(B<>"",ROW()-6,"")で自動連番。B列=青字の自由入力欄。C列=施工内容詳細。D/E列=開始日/終了日→F列日数自動+ガントバー自動。20行確保、使わない行はNo.非表示。 | F25: 工程表が自由記述式に改修完了。B列に好きな工程名を入力可能。8工程サンプル動作確認済(連番/日数/ガントバーすべて正常)。
A26: 25 | B26: =TODAY() -> 46070 | C26: 工程表Row9-20の空行が不要との指摘。また、見積もり作成方法が分からないので一から説明してほしいとの要望。 | D26: 1)工程表の印刷範囲をA1:AH16に縮小、備考欄をRow15-16に移動、旧Row27-30クリア。2)チャットでシステム全体の使い方を①顧客登録→②案件登録→③見積作成→④提出→⑤受注→⑥工程表→⑦発注→⑧請求入金→⑨完工の9ステップで詳細説明。 | E26: 見積の3タイプ(A原価逆算/B定価固定/C単価固定)の使い分け、青字=手入力/黒字=自動計算のルール、案件テンプレートの複製方法、工程表は案件IDで紐づくが行は自由記述であること等を解説。 | F26: 工程表のレイアウト改善完了（印刷範囲最適化）。ユーザーがシステム全体の操作フローを理解できるよう詳細マニュアルを提供。
A27: 26 | B27: =TODAY() -> 46070 | C27: 見積作成方法の説明と、見積書作成で全体に反映される仕組み化ができているか確認、設計を一から見直すよう指示。 | D27: 全シートの連携状況を総点検。重大な設計問題を発見: 案件シート→案件管理のF/G/Q列が手入力のまま、発注書兼請求書が未連携。INDIRECT制約のため「逆方向参照」設計を提案。 | E27: 問題: ①案件管理F/G/Q=手入力(見積変更が反映されない) ②発注書兼請求書=未連携 ③S表紙=手動切替。解決策: 各案件シートから案件管理への直接参照数式で、見積変更→全自動反映を実現。 | F27: 設計見直し方針をユーザーに提示。承認待ち。
A28: 27 | B28: =TODAY() -> 46070 | C28: 全体設計を一から見直し、問題点を全て分析・調査して設計図に書き起こすよう指示。見積作成で全シートに自動反映される仕組みか確認。 | D28: 全シート(12枚)を徹底調査。致命的問題11件を発見。「設計図v2」シートを新規作成し、6セクション構成で書き起こし: ①連携マップ(問題11件) ②改善後データフロー ③改修タスク一覧(FIX-01〜07) ④システム構成図 ⑤新規案件作成手順(11ステップ) ⑥推奨実施順序(Phase A〜D) | E28: 致命的問題: ①カテゴリ名三重不一致(マスター/S表紙/案件シートで名称・順序バラバラ) ②案件管理F/G列が手入力(見積変更が反映されない) ③S表紙がP-003固定(他案件で使えない) ④発注書兼請求書が完全未連携。改修方針: 案件シートを唯一の入力源とし、直接参照数式で全自動反映を実現。 | F28: 設計図v2シート(ID:42)完成。問題の全体像と改修計画をユーザーに提示。Phase A(カテゴリ統一)→B(連携構築)→C(帳票連携)→D(マニュアル)の4段階で改修予定。ユーザー承認待ち。
